Workbook
Name BUENAVISTA: nombres!$D$105:$D$109
Name GIVAUDAN: nombres!$D$100:$D$102
Name HUIMILPAN: nombres!$D$58:$D$99
Name LIRA_GALERAS: nombres!$D$2:$D$41
Name PECO_AGROS: nombres!$D$42:$D$57
Name PIE_DE_GALLO: nombres!$D$110:$D$121
Name SAN_GIL: nombres!$D$103:$D$104
Name SegmentaciónDeDatos_nombre_actividad: #N/A

Sheet diario
A1: Fecha | B1: Brigada | C1: Sistema | D1: Ducto | E1: Actividades | F1: inicio | G1: fin | H1: Avance_km | I1: Avance_Med | J1: Codigo_actividad | K1: nombre_actividad | L1: Length | M1: EV | N1: Observaciones
A2: 45964 | B2: A | C2: LIRA_GALERAS | D2: AC 8-6-4 in La Lira-Galeras | E2: Reunión de arranque y revisión de información oficinas ENGIE Querétaro. Localización de Tubería con Equipo de RadioDetección. | F2: 0 | G2: 1100 | H2: =IF(Tabla1[[#This Row],[Codigo_actividad]]<>2.5,IF(((Tabla1[[#This Row],[fin]]-Tabla1[[#This Row],[inicio]])/1000)=0,"",((Tabla1[[#This Row],[fin]]-Tabla1[[#This Row],[inicio]])/1000)),"") -> 1.1 | J2: 2.6 | K2: =IF(_xlfn.XLOOKUP($J2,Catalogo!$B$7:$B$210,Catalogo!$I$7:$I$210,"",0)=0,"",_xlfn.XLOOKUP($J2,Catalogo!$B$7:$B$210,Catalogo!$I$7:$I$210,"",0)) -> Localizacion | L2: 31.54 | M2: =IF(Tabla1[[#This Row],[Avance_km]]<>"",Tabla1[[#This Row],[Avance_km]],Tabla1[[#This Row],[Avance_Med]])*_xlfn.XLOOKUP(Tabla1[[#This Row],[Codigo_actividad]],Catalogo!$B$6:$B$51,Catalogo!$F$6:$F$51,0) -> 2483.162
A3: 45965 | B3: A | C3: LIRA_GALERAS | D3: AC 8-6-4 in La Lira-Galeras | E3: Localización de Tubería con Equipo de RadioDetección. | F3: 1100 | G3: 4000 | H3: =IF(Tabla1[[#This Row],[Codigo_actividad]]<>2.5,IF(((Tabla1[[#This Row],[fin]]-Tabla1[[#This Row],[inicio]])/1000)=0,"",((Tabla1[[#This Row],[fin]]-Tabla1[[#This Row],[inicio]])/1000)),"") -> 2.9 | J3: 2.6 | K3: =IF(_xlfn.XLOOKUP($J3,Catalogo!$B$7:$B$210,Catalogo!$I$7:$I$210,"",0)=0,"",_xlfn.XLOOKUP($J3,Catalogo!$B$7:$B$210,Catalogo!$I$7:$I$210,"",0)) -> Localizacion | L3: 31.54 | M3: =IF(Tabla1[[#This Row],[Avance_km]]<>"",Tabla1[[#This Row],[Avance_km]],Tabla1[[#This Row],[Avance_Med]])*_xlfn.XLOOKUP(Tabla1[[#This Row],[Codigo_actividad]],Catalogo!$B$6:$B$51,Catalogo!$F$6:$F$51,0) -> 6546.518
A4: 45966 | B4: A | C4: LIRA_GALERAS | D4: AC 8-6-4 in La Lira-Galeras | E4: Localización de Tubería con Equipo de RadioDetección. | F4: 4000 | G4: 8000 | H4: =IF(Tabla1[[#This Row],[Codigo_actividad]]<>2.5,IF(((Tabla1[[#This Row],[fin]]-Tabla1[[#This Row],[inicio]])/1000)=0,"",((Tabla1[[#This Row],[fin]]-Tabla1[[#This Row],[inicio]])/1000)),"") -> 4 | J4: 2.6 | K4: =IF(_xlfn.XLOOKUP($J4,Catalogo!$B$7:$B$210,Catalogo!$I$7:$I$210,"",0)=0,"",_xlfn.XLOOKUP($J4,Catalogo!$B$7:$B$210,Catalogo!$I$7:$I$210,"",0)) -> Localizacion | L4: 31.54 | M4: =IF(Tabla1[[#This Row],[Avance_km]]<>"",Tabla1[[#This Row],[Avance_km]],Tabla1[[#This Row],[Avance_Med]])*_xlfn.XLOOKUP(Tabla1[[#This Row],[Codigo_actividad]],Catalogo!$B$6:$B$51,Catalogo!$F$6:$F$51,0) -> 9029.68
A5: 45967 | B5: A | C5: LIRA_GALERAS | D5: AC 8-6-4 in La Lira-Galeras | E5: Localización de Tubería con Equipo de RadioDetección. | F5: 8000 | G5: 13500 | H5: =IF(Tabla1[[#This Row],[Codigo_actividad]]<>2.5,IF(((Tabla1[[#This Row],[fin]]-Tabla1[[#This Row],[inicio]])/1000)=0,"",((Tabla1[[#This Row],[fin]]-Tabla1[[#This Row],[inicio]])/1000)),"") -> 5.5 | J5: 2.6 | K5: =IF(_xlfn.XLOOKUP($J5,Catalogo!$B$7:$B$210,Catalogo!$I$7:$I$210,"",0)=0,"",_xlfn.XLOOKUP($J5,Catalogo!$B$7:$B$210,Catalogo!$I$7:$I$210,"",0)) -> Localizacion | L5: 31.54 | M5: =IF(Tabla1[[#This Row],[Avance_km]]<>"",Tabla1[[#This Row],[Avance_km]],Tabla1[[#This Row],[Avance_Med]])*_xlfn.XLOOKUP(Tabla1[[#This Row],[Codigo_actividad]],Catalogo!$B$6:$B$51,Catalogo!$F$6:$F$51,0) -> 12415.81
A6: 45968 | B6: A | C6: LIRA_GALERAS | D6: AC 8-6-4 in La Lira-Galeras | E6: Localización de Tubería con Equipo de RadioDetección. | F6: 13500 | G6: 17500 | H6: =IF(Tabla1[[#This Row],[Codigo_actividad]]<>2.5,IF(((Tabla1[[#This Row],[fin]]-Tabla1[[#This Row],[inicio]])/1000)=0,"",((Tabla1[[#This Row],[fin]]-Tabla1[[#This Row],[inicio]])/1000)),"") -> 4 | J6: 2.6 | K6: =IF(_xlfn.XLOOKUP($J6,Catalogo!$B$7:$B$210,Catalogo!$I$7:$I$210,"",0)=0,"",_xlfn.XLOOKUP($J6,Catalogo!$B$7:$B$210,Catalogo!$I$7:$I$210,"",0)) -> Localizacion | L6: 31.54 | M6: =IF(Tabla1[[#This Row],[Avance_km]]<>"",Tabla1[[#This Row],[Avance_km]],Tabla1[[#This Row],[Avance_Med]])*_xlfn.XLOOKUP(Tabla1[[#This Row],[Codigo_actividad]],Catalogo!$B$6:$B$51,Catalogo!$F$6:$F$51,0) -> 9029.68
A7: 45969 | B7: A | C7: LIRA_GALERAS | D7: AC 8-6-4 in La Lira-Galeras | E7: Localización de Tubería con Equipo de RadioDetección. | F7: 17500 | G7: 20500 | H7: =IF(Tabla1[[#This Row],[Codigo_actividad]]<>2.5,IF(((Tabla1[[#This Row],[fin]]-Tabla1[[#This Row],[inicio]])/1000)=0,"",((Tabla1[[#This Row],[fin]]-Tabla1[[#This Row],[inicio]])/1000)),"") -> 3 | J7: 2.6 | K7: =IF(_xlfn.XLOOKUP($J7,Catalogo!$B$7:$B$210,Catalogo!$I$7:$I$210,"",0)=0,"",_xlfn.XLOOKUP($J7,Catalogo!$B$7:$B$210,Catalogo!$I$7:$I$210,"",0)) -> Localizacion | L7: 31.54 | M7: =IF(Tabla1[[#This Row],[Avance_km]]<>"",Tabla1[[#This Row],[Avance_km]],Tabla1[[#This Row],[Avance_Med]])*_xlfn.XLOOKUP(Tabla1[[#This Row],[Codigo_actividad]],Catalogo!$B$6:$B$51,Catalogo!$F$6:$F$51,0) -> 6772.26
A8: 45971 | B8: A | C8: LIRA_GALERAS | D8: AC 8-6-4 in La Lira-Galeras | E8: Localización de Tubería con Equipo de RadioDetección. | F8: 20500 | G8: 26000 | H8: =IF(Tabla1[[#This Row],[Codigo_actividad]]<>2.5,IF(((Tabla1[[#This Row],[fin]]-Tabla1[[#This Row],[inicio]])/1000)=0,"",((Tabla1[[#This Row],[fin]]-Tabla1[[#This Row],[inicio]])/1000)),"") -> 5.5 | J8: 2.6 | K8: =IF(_xlfn.XLOOKUP($J8,Catalogo!$B$7:$B$210,Catalogo!$I$7:$I$210,"",0)=0,"",_xlfn.XLOOKUP($J8,Catalogo!$B$7:$B$210,Catalogo!$I$7:$I$210,"",0)) -> Localizacion | L8: 31.54 | M8: =IF(Tabla1[[#This Row],[Avance_km]]<>"",Tabla1[[#This Row],[Avance_km]],Tabla1[[#This Row],[Avance_Med]])*_xlfn.XLOOKUP(Tabla1[[#This Row],[Codigo_actividad]],Catalogo!$B$6:$B$51,Catalogo!$F$6:$F$51,0) -> 12415.81
A9: 45972 | B9: A | C9: LIRA_GALERAS | D9: AC 8-6-4 in La Lira-Galeras | E9: Localización de Tubería con Equipo de RadioDetección. | F9: 26000 | G9: 31540 | H9: =IF(Tabla1[[#This Row],[Codigo_actividad]]<>2.5,IF(((Tabla1[[#This Row],[fin]]-Tabla1[[#This Row],[inicio]])/1000)=0,"",((Tabla1[[#This Row],[fin]]-Tabla1[[#This Row],[inicio]])/1000)),"") -> 5.54 | J9: 2.6 | K9: =IF(_xlfn.XLOOKUP($J9,Catalogo!$B$7:$B$210,Catalogo!$I$7:$I$210,"",0)=0,"",_xlfn.XLOOKUP($J9,Catalogo!$B$7:$B$210,Catalogo!$I$7:$I$210,"",0)) -> Localizacion | L9: 31.54 | M9: =IF(Tabla1[[#This Row],[Avance_km]]<>"",Tabla1[[#This Row],[Avance_km]],Tabla1[[#This Row],[Avance_Med]])*_xlfn.XLOOKUP(Tabla1[[#This Row],[Codigo_actividad]],Catalogo!$B$6:$B$51,Catalogo!$F$6:$F$51,0) -> 12506.107
A10: 45973 | B10: A | C10: LIRA_GALERAS | D10: ALESTRA | E10: Localización de Tubería con Equipo de RadioDetección. | F10: 0 | G10: 1982 | H10: =IF(Tabla1[[#This Row],[Codigo_actividad]]<>2.5,IF(((Tabla1[[#This Row],[fin]]-Tabla1[[#This Row],[inicio]])/1000)=0,"",((Tabla1[[#This Row],[fin]]-Tabla1[[#This Row],[inicio]])/1000)),"") -> 1.982 | J10: 2.6 | K10: =IF(_xlfn.XLOOKUP($J10,Catalogo!$B$7:$B$210,Catalogo!$I$7:$I$210,"",0)=0,"",_xlfn.XLOOKUP($J10,Catalogo!$B$7:$B$210,Catalogo!$I$7:$I$210,"",0)) -> Localizacion | L10: 1.982 | M10: =IF(Tabla1[[#This Row],[Avance_km]]<>"",Tabla1[[#This Row],[Avance_km]],Tabla1[[#This Row],[Avance_Med]])*_xlfn.XLOOKUP(Tabla1[[#This Row],[Codigo_actividad]],Catalogo!$B$6:$B$51,Catalogo!$F$6:$F$51,0) -> 4474.2064
A11: 45973 | B11: A | C11: LIRA_GALERAS | D11: HUAWEI | E11: Localización de Tubería con Equipo de RadioDetección. | F11: 0 | G11: 175 | H11: =IF(Tabla1[[#This Row],[Codigo_actividad]]<>2.5,IF(((Tabla1[[#This Row],[fin]]-Tabla1[[#This Row],[inicio]])/1000)=0,"",((Tabla1[[#This Row],[fin]]-Tabla1[[#This Row],[inicio]])/1000)),"") -> 0.175 | J11: 2.6 | K11: =IF(_xlfn.XLOOKUP($J11,Catalogo!$B$7:$B$210,Catalogo!$I$7:$I$210,"",0)=0,"",_xlfn.XLOOKUP($J11,Catalogo!$B$7:$B$210,Catalogo!$I$7:$I$210,"",0)) -> Localizacion | L11: 0.175 | M11: =IF(Tabla1[[#This Row],[Avance_km]]<>"",Tabla1[[#This Row],[Avance_km]],Tabla1[[#This Row],[Avance_Med]])*_xlfn.XLOOKUP(Tabla1[[#This Row],[Codigo_actividad]],Catalogo!$B$6:$B$51,Catalogo!$F$6:$F$51,0) -> 395.0485
A12: 45973 | B12: A | C12: LIRA_GALERAS | D12: ITASA | E12: Localización de Tubería con Equipo de RadioDetección. | F12: 0 | G12: 15 | H12: =IF(Tabla1[[#This Row],[Codigo_actividad]]<>2.5,IF(((Tabla1[[#This Row],[fin]]-Tabla1[[#This Row],[inicio]])/1000)=0,"",((Tabla1[[#This Row],[fin]]-Tabla1[[#This Row],[inicio]])/1000)),"") -> 0.015 | J12: 2.6 | K12: =IF(_xlfn.XLOOKUP($J12,Catalogo!$B$7:$B$210,Catalogo!$I$7:$I$210,"",0)=0,"",_xlfn.XLOOKUP($J12,Catalogo!$B$7:$B$210,Catalogo!$I$7:$I$210,"",0)) -> Localizacion | L12: 0.015 | M12: =IF(Tabla1[[#This Row],[Avance_km]]<>"",Tabla1[[#This Row],[Avance_km]],Tabla1[[#This Row],[Avance_Med]])*_xlfn.XLOOKUP(Tabla1[[#This Row],[Codigo_actividad]],Catalogo!$B$6:$B$51,Catalogo!$F$6:$F$51,0) -> 33.8613
A13: 45973 | B13: A | C13: LIRA_GALERAS | D13: ED PARQUE INDUSTRIAL FINSA II | E13: Localización de Tubería con Equipo de RadioDetección. | F13: 0 | G13: 1020 | H13: =IF(Tabla1[[#This Row],[Codigo_actividad]]<>2.5,IF(((Tabla1[[#This Row],[fin]]-Tabla1[[#This Row],[inicio]])/1000)=0,"",((Tabla1[[#This Row],[fin]]-Tabla1[[#This Row],[inicio]])/1000)),"") -> 1.02 | J13: 2.6 | K13: =IF(_xlfn.XLOOKUP($J13,Catalogo!$B$7:$B$210,Catalogo!$I$7:$I$210,"",0)=0,"",_xlfn.XLOOKUP($J13,Catalogo!$B$7:$B$210,Catalogo!$I$7:$I$210,"",0)) -> Localizacion | L13: 1.02 | M13: =IF(Tabla1[[#This Row],[Avance_km]]<>"",Tabla1[[#This Row],[Avance_km]],Tabla1[[#This Row],[Avance_Med]])*_xlfn.XLOOKUP(Tabla1[[#This Row],[Codigo_actividad]],Catalogo!$B$6:$B$51,Catalogo!$F$6:$F$51,0) -> 2302.5684
... A25: 45980 | B25: B | C25: PECO_AGROS | D25: PECO II - GALERAS 10 | E25: Localización de Tubería con Equipo de RadioDetección. | F25: 15000 | G25: 18300 | H25: =IF(Tabla1[[#This Row],[Codigo_actividad]]<>2.5,IF(((Tabla1[[#This Row],[fin]]-Tabla1[[#This Row],[inicio]])/1000)=0,"",((Tabla1[[#This Row],[fin]]-Tabla1[[#This Row],[inicio]])/1000)),"") -> 3.3 | J25: 2.6 | K25: =IF(_xlfn.XLOOKUP($J25,Catalogo!$B$7:$B$210,Catalogo!$I$7:$I$210,"",0)=0,"",_xlfn.XLOOKUP($J25,Catalogo!$B$7:$B$210,Catalogo!$I$7:$I$210,"",0)) -> Localizacion | L25: 25.4 | M25: =IF(Tabla1[[#This Row],[Avance_km]]<>"",Tabla1[[#This Row],[Avance_km]],Tabla1[[#This Row],[Avance_Med]])*_xlfn.XLOOKUP(Tabla1[[#This Row],[Codigo_actividad]],Catalogo!$B$6:$B$51,Catalogo!$F$6:$F$51,0) -> 7449.486
A26: 45980 | B26: C | C26: LIRA_GALERAS | D26: AC 8-6-4 in La Lira-Galeras | E26: Resistividades pH BRS BPA | F26: 0 | G26: 4500 | H26: =IF(Tabla1[[#This Row],[Codigo_actividad]]<>2.5,IF(((Tabla1[[#This Row],[fin]]-Tabla1[[#This Row],[inicio]])/1000)=0,"",((Tabla1[[#This Row],[fin]]-Tabla1[[#This Row],[inicio]])/1000)),"") | I26: 9 | J26: 2.5 | K26: =IF(_xlfn.XLOOKUP($J26,Catalogo!$B$7:$B$210,Catalogo!$I$7:$I$210,"",0)=0,"",_xlfn.XLOOKUP($J26,Catalogo!$B$7:$B$210,Catalogo!$I$7:$I$210,"",0)) -> Resistividades pH BSR BPA | L26: 31.54 | M26: =IF(Tabla1[[#This Row],[Avance_km]]<>"",Tabla1[[#This Row],[Avance_km]],Tabla1[[#This Row],[Avance_Med]])*_xlfn.XLOOKUP(Tabla1[[#This Row],[Codigo_actividad]],Catalogo!$B$6:$B$51,Catalogo!$F$6:$F$51,0) -> 41922
A27: 45981 | B27: A | C27: LIRA_GALERAS | D27: AC 8-6-4 in La Lira-Galeras | E27: Close Interval Survey CIS | F27: 15000 | G27: 18500 | H27: =IF(Tabla1[[#This Row],[Codigo_actividad]]<>2.5,IF(((Tabla1[[#This Row],[fin]]-Tabla1[[#This Row],[inicio]])/1000)=0,"",((Tabla1[[#This Row],[fin]]-Tabla1[[#This Row],[inicio]])/1000)),"") -> 3.5 | J27: 2.1 | K27: =IF(_xlfn.XLOOKUP($J27,Catalogo!$B$7:$B$210,Catalogo!$I$7:$I$210,"",0)=0,"",_xlfn.XLOOKUP($J27,Catalogo!$B$7:$B$210,Catalogo!$I$7:$I$210,"",0)) -> CIPS | L27: 31.54 | M27: =IF(Tabla1[[#This Row],[Avance_km]]<>"",Tabla1[[#This Row],[Avance_km]],Tabla1[[#This Row],[Avance_Med]])*_xlfn.XLOOKUP(Tabla1[[#This Row],[Codigo_actividad]],Catalogo!$B$6:$B$51,Catalogo!$F$6:$F$51,0) -> 50824.935
A28: 45981 | B28: B | C28: PECO_AGROS | D28: PECO II - GALERAS 10 | E28: Localización de Tubería con Equipo de RadioDetección. | F28: 18300 | G28: 25000 | H28: =IF(Tabla1[[#This Row],[Codigo_actividad]]<>2.5,IF(((Tabla1[[#This Row],[fin]]-Tabla1[[#This Row],[inicio]])/1000)=0,"",((Tabla1[[#This Row],[fin]]-Tabla1[[#This Row],[inicio]])/1000)),"") -> 6.7 | J28: 2.6 | K28: =IF(_xlfn.XLOOKUP($J28,Catalogo!$B$7:$B$210,Catalogo!$I$7:$I$210,"",0)=0,"",_xlfn.XLOOKUP($J28,Catalogo!$B$7:$B$210,Catalogo!$I$7:$I$210,"",0)) -> Localizacion | L28: 25.4 | M28: =IF(Tabla1[[#This Row],[Avance_km]]<>"",Tabla1[[#This Row],[Avance_km]],Tabla1[[#This Row],[Avance_Med]])*_xlfn.XLOOKUP(Tabla1[[#This Row],[Codigo_actividad]],Catalogo!$B$6:$B$51,Catalogo!$F$6:$F$51,0) -> 15124.714
A29: 45981 | B29: C | C29: LIRA_GALERAS | D29: AC 8-6-4 in La Lira-Galeras | E29: Resistividades pH BRS BPA | F29: 4500 | G29: 10000 | H29: =IF(Tabla1[[#This Row],[Codigo_actividad]]<>2.5,IF(((Tabla1[[#This Row],[fin]]-Tabla1[[#This Row],[inicio]])/1000)=0,"",((Tabla1[[#This Row],[fin]]-Tabla1[[#This Row],[inicio]])/1000)),"") | I29: 12 | J29: 2.5 | K29: =IF(_xlfn.XLOOKUP($J29,Catalogo!$B$7:$B$210,Catalogo!$I$7:$I$210,"",0)=0,"",_xlfn.XLOOKUP($J29,Catalogo!$B$7:$B$210,Catalogo!$I$7:$I$210,"",0)) -> Resistividades pH BSR BPA | L29: 31.54 | M29: =IF(Tabla1[[#This Row],[Avance_km]]<>"",Tabla1[[#This Row],[Avance_km]],Tabla1[[#This Row],[Avance_Med]])*_xlfn.XLOOKUP(Tabla1[[#This Row],[Codigo_actividad]],Catalogo!$B$6:$B$51,Catalogo!$F$6:$F$51,0) -> 55896
A30: 45982 | B30: A | C30: LIRA_GALERAS | D30: AC 8-6-4 in La Lira-Galeras | E30: Close Interval Survey CIS | F30: 18500 | G30: 24000 | H30: =IF(Tabla1[[#This Row],[Codigo_actividad]]<>2.5,IF(((Tabla1[[#This Row],[fin]]-Tabla1[[#This Row],[inicio]])/1000)=0,"",((Tabla1[[#This Row],[fin]]-Tabla1[[#This Row],[inicio]])/1000)),"") -> 5.5 | J30: 2.1 | K30: =IF(_xlfn.XLOOKUP($J30,Catalogo!$B$7:$B$210,Catalogo!$I$7:$I$210,"",0)=0,"",_xlfn.XLOOKUP($J30,Catalogo!$B$7:$B$210,Catalogo!$I$7:$I$210,"",0)) -> CIPS | L30: 31.54 | M30: =IF(Tabla1[[#This Row],[Avance_km]]<>"",Tabla1[[#This Row],[Avance_km]],Tabla1[[#This Row],[Avance_Med]])*_xlfn.XLOOKUP(Tabla1[[#This Row],[Codigo_actividad]],Catalogo!$B$6:$B$51,Catalogo!$F$6:$F$51,0) -> 79867.755
A31: 45982 | B31: B | C31: PECO_AGROS | D31: PECO II - GALERAS 10 | E31: Localización de Tubería con Equipo de RadioDetección. | F31: 25000 | G31: 25400 | H31: =IF(Tabla1[[#This Row],[Codigo_actividad]]<>2.5,IF(((Tabla1[[#This Row],[fin]]-Tabla1[[#This Row],[inicio]])/1000)=0,"",((Tabla1[[#This Row],[fin]]-Tabla1[[#This Row],[inicio]])/1000)),"") -> 0.4 | J31: 2.6 | K31: =IF(_xlfn.XLOOKUP($J31,Catalogo!$B$7:$B$210,Catalogo!$I$7:$I$210,"",0)=0,"",_xlfn.XLOOKUP($J31,Catalogo!$B$7:$B$210,Catalogo!$I$7:$I$210,"",0)) -> Localizacion | L31: 25.4 | M31: =IF(Tabla1[[#This Row],[Avance_km]]<>"",Tabla1[[#This Row],[Avance_km]],Tabla1[[#This Row],[Avance_Med]])*_xlfn.XLOOKUP(Tabla1[[#This Row],[Codigo_actividad]],Catalogo!$B$6:$B$51,Catalogo!$F$6:$F$51,0) -> 902.968
A32: 45982 | B32: B | C32: PECO_AGROS | D32: ED AGROPARK II (GAS PRIMO) | E32: Localización de Tubería con Equipo de RadioDetección. | F32: 0 | G32: 9 | H32: =IF(Tabla1[[#This Row],[Codigo_actividad]]<>2.5,IF(((Tabla1[[#This Row],[fin]]-Tabla1[[#This Row],[inicio]])/1000)=0,"",((Tabla1[[#This Row],[fin]]-Tabla1[[#This Row],[inicio]])/1000)),"") -> 0.009 | J32: 2.6 | K32: =IF(_xlfn.XLOOKUP($J32,Catalogo!$B$7:$B$210,Catalogo!$I$7:$I$210,"",0)=0,"",_xlfn.XLOOKUP($J32,Catalogo!$B$7:$B$210,Catalogo!$I$7:$I$210,"",0)) -> Localizacion | L32: 0.009 | M32: =IF(Tabla1[[#This Row],[Avance_km]]<>"",Tabla1[[#This Row],[Avance_km]],Tabla1[[#This Row],[Avance_Med]])*_xlfn.XLOOKUP(Tabla1[[#This Row],[Codigo_actividad]],Catalogo!$B$6:$B$51,Catalogo!$F$6:$F$51,0) -> 20.31678
A33: 45982 | B33: B | C33: PECO_AGROS | D33: LA BONITA | E33: Localización de Tubería con Equipo de RadioDetección. | F33: 0 | G33: 479 | H33: =IF(Tabla1[[#This Row],[Codigo_actividad]]<>2.5,IF(((Tabla1[[#This Row],[fin]]-Tabla1[[#This Row],[inicio]])/1000)=0,"",((Tabla1[[#This Row],[fin]]-Tabla1[[#This Row],[inicio]])/1000)),"") -> 0.479 | J33: 2.6 | K33: =IF(_xlfn.XLOOKUP($J33,Catalogo!$B$7:$B$210,Catalogo!$I$7:$I$210,"",0)=0,"",_xlfn.XLOOKUP($J33,Catalogo!$B$7:$B$210,Catalogo!$I$7:$I$210,"",0)) -> Localizacion | L33: 0.479 | M33: =IF(Tabla1[[#This Row],[Avance_km]]<>"",Tabla1[[#This Row],[Avance_km]],Tabla1[[#This Row],[Avance_Med]])*_xlfn.XLOOKUP(Tabla1[[#This Row],[Codigo_actividad]],Catalogo!$B$6:$B$51,Catalogo!$F$6:$F$51,0) -> 1081.3042
A34: 45982 | B34: C | C34: LIRA_GALERAS | D34: AC 8-6-4 in La Lira-Galeras | E34: Resistividades pH BRS BPA | F34: 10000 | G34: 15000 | H34: =IF(Tabla1[[#This Row],[Codigo_actividad]]<>2.5,IF(((Tabla1[[#This Row],[fin]]-Tabla1[[#This Row],[inicio]])/1000)=0,"",((Tabla1[[#This Row],[fin]]-Tabla1[[#This Row],[inicio]])/1000)),"") | I34: 11 | J34: 2.5 | K34: =IF(_xlfn.XLOOKUP($J34,Catalogo!$B$7:$B$210,Catalogo!$I$7:$I$210,"",0)=0,"",_xlfn.XLOOKUP($J34,Catalogo!$B$7:$B$210,Catalogo!$I$7:$I$210,"",0)) -> Resistividades pH BSR BPA | L34: 31.54 | M34: =IF(Tabla1[[#This Row],[Avance_km]]<>"",Tabla1[[#This Row],[Avance_km]],Tabla1[[#This Row],[Avance_Med]])*_xlfn.XLOOKUP(Tabla1[[#This Row],[Codigo_actividad]],Catalogo!$B$6:$B$51,Catalogo!$F$6:$F$51,0) -> 51238
A35: 45983 | B35: A | C35: LIRA_GALERAS | D35: AC 8-6-4 in La Lira-Galeras | E35: Close Interval Survey CIS | F35: 24000 | G35: 28500 | H35: =IF(Tabla1[[#This Row],[Codigo_actividad]]<>2.5,IF(((Tabla1[[#This Row],[fin]]-Tabla1[[#This Row],[inicio]])/1000)=0,"",((Tabla1[[#This Row],[fin]]-Tabla1[[#This Row],[inicio]])/1000)),"") -> 4.5 | J35: 2.1 | K35: =IF(_xlfn.XLOOKUP($J35,Catalogo!$B$7:$B$210,Catalogo!$I$7:$I$210,"",0)=0,"",_xlfn.XLOOKUP($J35,Catalogo!$B$7:$B$210,Catalogo!$I$7:$I$210,"",0)) -> CIPS | M35: =IF(Tabla1[[#This Row],[Avance_km]]<>"",Tabla1[[#This Row],[Avance_km]],Tabla1[[#This Row],[Avance_Med]])*_xlfn.XLOOKUP(Tabla1[[#This Row],[Codigo_actividad]],Catalogo!$B$6:$B$51,Catalogo!$F$6:$F$51,0) -> 65346.345
A36: 45983 | B36: A | C36: PECO_AGROS | D36: ERM FH FIBRAS | E36: Localización de Tubería con Equipo de RadioDetección. | F36: 0 | G36: 40 | H36: =IF(Tabla1[[#This Row],[Codigo_actividad]]<>2.5,IF(((Tabla1[[#This Row],[fin]]-Tabla1[[#This Row],[inicio]])/1000)=0,"",((Tabla1[[#This Row],[fin]]-Tabla1[[#This Row],[inicio]])/1000)),"") -> 0.04 | J36: 2.6 | K36: =IF(_xlfn.XLOOKUP($J36,Catalogo!$B$7:$B$210,Catalogo!$I$7:$I$210,"",0)=0,"",_xlfn.XLOOKUP($J36,Catalogo!$B$7:$B$210,Catalogo!$I$7:$I$210,"",0)) -> Localizacion | L36: 0.04 | M36: =IF(Tabla1[[#This Row],[Avance_km]]<>"",Tabla1[[#This Row],[Avance_km]],Tabla1[[#This Row],[Avance_Med]])*_xlfn.XLOOKUP(Tabla1[[#This Row],[Codigo_actividad]],Catalogo!$B$6:$B$51,Catalogo!$F$6:$F$51,0) -> 90.2968
A37: 45983 | B37: A | C37: PECO_AGROS | D37: ERM DESHITEC | E37: Localización de Tubería con Equipo de RadioDetección. | F37: 0 | G37: 120 | H37: =IF(Tabla1[[#This Row],[Codigo_actividad]]<>2.5,IF(((Tabla1[[#This Row],[fin]]-Tabla1[[#This Row],[inicio]])/1000)=0,"",((Tabla1[[#This Row],[fin]]-Tabla1[[#This Row],[inicio]])/1000)),"") -> 0.12 | J37: 2.6 | K37: =IF(_xlfn.XLOOKUP($J37,Catalogo!$B$7:$B$210,Catalogo!$I$7:$I$210,"",0)=0,"",_xlfn.XLOOKUP($J37,Catalogo!$B$7:$B$210,Catalogo!$I$7:$I$210,"",0)) -> Localizacion | L37: 0.12 | M37: =IF(Tabla1[[#This Row],[Avance_km]]<>"",Tabla1[[#This Row],[Avance_km]],Tabla1[[#This Row],[Avance_Med]])*_xlfn.XLOOKUP(Tabla1[[#This Row],[Codigo_actividad]],Catalogo!$B$6:$B$51,Catalogo!$F$6:$F$51,0) -> 270.8904
A38: 45983 | B38: B | C38: PECO_AGROS | D38: ED ARKANSAS | E38: Localización de Tubería con Equipo de RadioDetección. | F38: 0 | G38: 1195 | H38: =IF(Tabla1[[#This Row],[Codigo_actividad]]<>2.5,IF(((Tabla1[[#This Row],[fin]]-Tabla1[[#This Row],[inicio]])/1000)=0,"",((Tabla1[[#This Row],[fin]]-Tabla1[[#This Row],[inicio]])/1000)),"") -> 1.195 | J38: 2.6 | K38: =IF(_xlfn.XLOOKUP($J38,Catalogo!$B$7:$B$210,Catalogo!$I$7:$I$210,"",0)=0,"",_xlfn.XLOOKUP($J38,Catalogo!$B$7:$B$210,Catalogo!$I$7:$I$210,"",0)) -> Localizacion | L38: 1.195 | M38: =IF(Tabla1[[#This Row],[Avance_km]]<>"",Tabla1[[#This Row],[Avance_km]],Tabla1[[#This Row],[Avance_Med]])*_xlfn.XLOOKUP(Tabla1[[#This Row],[Codigo_actividad]],Catalogo!$B$6:$B$51,Catalogo!$F$6:$F$51,0) -> 2697.6169
A39: 45984 | B39: A | C39: LIRA_GALERAS | D39: AC 8-6-4 in La Lira-Galeras | E39: Close Interval Survey CIS | F39: 28500 | G39: 31540 | H39: =IF(Tabla1[[#This Row],[Codigo_actividad]]<>2.5,IF(((Tabla1[[#This Row],[fin]]-Tabla1[[#This Row],[inicio]])/1000)=0,"",((Tabla1[[#This Row],[fin]]-Tabla1[[#This Row],[inicio]])/1000)),"") -> 3.04 | J39: 2.1 | K39: =IF(_xlfn.XLOOKUP($J39,Catalogo!$B$7:$B$210,Catalogo!$I$7:$I$210,"",0)=0,"",_xlfn.XLOOKUP($J39,Catalogo!$B$7:$B$210,Catalogo!$I$7:$I$210,"",0)) -> CIPS | L39: 31.54 | M39: =IF(Tabla1[[#This Row],[Avance_km]]<>"",Tabla1[[#This Row],[Avance_km]],Tabla1[[#This Row],[Avance_Med]])*_xlfn.XLOOKUP(Tabla1[[#This Row],[Codigo_actividad]],Catalogo!$B$6:$B$51,Catalogo!$F$6:$F$51,0) -> 44145.086
A40: 45985 | B40: A | C40: LIRA_GALERAS | D40: AC 8-6-4 in La Lira-Galeras | E40: Direct Current Voltage Gradient DCVG | F40: 9000 | G40: 12000 | H40: =IF(Tabla1[[#This Row],[Codigo_actividad]]<>2.5,IF(((Tabla1[[#This Row],[fin]]-Tabla1[[#This Row],[inicio]])/1000)=0,"",((Tabla1[[#This Row],[fin]]-Tabla1[[#This Row],[inicio]])/1000)),"") -> 3 | J40: 2.3 | K40: =IF(_xlfn.XLOOKUP($J40,Catalogo!$B$7:$B$210,Catalogo!$I$7:$I$210,"",0)=0,"",_xlfn.XLOOKUP($J40,Catalogo!$B$7:$B$210,Catalogo!$I$7:$I$210,"",0)) -> DCVG | L40: 31.54 | M40: =IF(Tabla1[[#This Row],[Avance_km]]<>"",Tabla1[[#This Row],[Avance_km]],Tabla1[[#This Row],[Avance_Med]])*_xlfn.XLOOKUP(Tabla1[[#This Row],[Codigo_actividad]],Catalogo!$B$6:$B$51,Catalogo!$F$6:$F$51,0) -> 40666.89
A41: 45985 | B41: B | C41: LIRA_GALERAS | D41: VIBORILLAS | E41: Localización de Tubería con Equipo de RadioDetección. | F41: 0 | G41: 1488 | H41: =IF(Tabla1[[#This Row],[Codigo_actividad]]<>2.5,IF(((Tabla1[[#This Row],[fin]]-Tabla1[[#This Row],[inicio]])/1000)=0,"",((Tabla1[[#This Row],[fin]]-Tabla1[[#This Row],[inicio]])/1000)),"") -> 1.488 | J41: 2.6 | K41: =IF(_xlfn.XLOOKUP($J41,Catalogo!$B$7:$B$210,Catalogo!$I$7:$I$210,"",0)=0,"",_xlfn.XLOOKUP($J41,Catalogo!$B$7:$B$210,Catalogo!$I$7:$I$210,"",0)) -> Localizacion | L41: 1.488 | M41: =IF(Tabla1[[#This Row],[Avance_km]]<>"",Tabla1[[#This Row],[Avance_km]],Tabla1[[#This Row],[Avance_Med]])*_xlfn.XLOOKUP(Tabla1[[#This Row],[Codigo_actividad]],Catalogo!$B$6:$B$51,Catalogo!$F$6:$F$51,0) -> 3359.041
A42: 45985 | B42: B | C42: LIRA_GALERAS | D42: ERM VIBORILLAS | E42: Localización de Tubería con Equipo de RadioDetección. | F42: 0 | G42: 7 | H42: =IF(Tabla1[[#This Row],[Codigo_actividad]]<>2.5,IF(((Tabla1[[#This Row],[fin]]-Tabla1[[#This Row],[inicio]])/1000)=0,"",((Tabla1[[#This Row],[fin]]-Tabla1[[#This Row],[inicio]])/1000)),"") -> 0.007 | J42: 2.6 | K42: =IF(_xlfn.XLOOKUP($J42,Catalogo!$B$7:$B$210,Catalogo!$I$7:$I$210,"",0)=0,"",_xlfn.XLOOKUP($J42,Catalogo!$B$7:$B$210,Catalogo!$I$7:$I$210,"",0)) -> Localizacion | L42: 0.007 | M42: =IF(Tabla1[[#This Row],[Avance_km]]<>"",Tabla1[[#This Row],[Avance_km]],Tabla1[[#This Row],[Avance_Med]])*_xlfn.XLOOKUP(Tabla1[[#This Row],[Codigo_actividad]],Catalogo!$B$6:$B$51,Catalogo!$F$6:$F$51,0) -> 15.80194
A43: 45985 | B43: B | C43: LIRA_GALERAS | D43: ED BOMBARDIER | E43: Localización de Tubería con Equipo de RadioDetección. | F43: 0 | G43: 1855 | H43: =IF(Tabla1[[#This Row],[Codigo_actividad]]<>2.5,IF(((Tabla1[[#This Row],[fin]]-Tabla1[[#This Row],[inicio]])/1000)=0,"",((Tabla1[[#This Row],[fin]]-Tabla1[[#This Row],[inicio]])/1000)),"") -> 1.855 | J43: 2.6 | K43: =IF(_xlfn.XLOOKUP($J43,Catalogo!$B$7:$B$210,Catalogo!$I$7:$I$210,"",0)=0,"",_xlfn.XLOOKUP($J43,Catalogo!$B$7:$B$210,Catalogo!$I$7:$I$210,"",0)) -> Localizacion | L43: 1.855 | M43: =IF(Tabla1[[#This Row],[Avance_km]]<>"",Tabla1[[#This Row],[Avance_km]],Tabla1[[#This Row],[Avance_Med]])*_xlfn.XLOOKUP(Tabla1[[#This Row],[Codigo_actividad]],Catalogo!$B$6:$B$51,Catalogo!$F$6:$F$51,0) -> 4187.5141
A44: 45985 | B44: C | C44: LIRA_GALERAS | D44: AC 8-6-4 in La Lira-Galeras | E44: Resistividades pH BRS BPA | F44: 15000 | G44: 18500 | H44: =IF(Tabla1[[#This Row],[Codigo_actividad]]<>2.5,IF(((Tabla1[[#This Row],[fin]]-Tabla1[[#This Row],[inicio]])/1000)=0,"",((Tabla1[[#This Row],[fin]]-Tabla1[[#This Row],[inicio]])/1000)),"") | I44: 6 | J44: 2.5 | K44: =IF(_xlfn.XLOOKUP($J44,Catalogo!$B$7:$B$210,Catalogo!$I$7:$I$210,"",0)=0,"",_xlfn.XLOOKUP($J44,Catalogo!$B$7:$B$210,Catalogo!$I$7:$I$210,"",0)) -> Resistividades pH BSR BPA | L44: 31.54 | M44: =IF(Tabla1[[#This Row],[Avance_km]]<>"",Tabla1[[#This Row],[Avance_km]],Tabla1[[#This Row],[Avance_Med]])*_xlfn.XLOOKUP(Tabla1[[#This Row],[Codigo_actividad]],Catalogo!$B$6:$B$51,Catalogo!$F$6:$F$51,0) -> 27948
A45: 45986 | B45: A | C45: LIRA_GALERAS | D45: AC 8-6-4 in La Lira-Galeras | E45: Direct Current Voltage Gradient DCVG | F45: 0 | G45: 5000 | H45: =IF(Tabla1[[#This Row],[Codigo_actividad]]<>2.5,IF(((Tabla1[[#This Row],[fin]]-Tabla1[[#This Row],[inicio]])/1000)=0,"",((Tabla1[[#This Row],[fin]]-Tabla1[[#This Row],[inicio]])/1000)),"") -> 5 | J45: 2.3 | K45: =IF(_xlfn.XLOOKUP($J45,Catalogo!$B$7:$B$210,Catalogo!$I$7:$I$210,"",0)=0,"",_xlfn.XLOOKUP($J45,Catalogo!$B$7:$B$210,Catalogo!$I$7:$I$210,"",0)) -> DCVG | L45: 31.54 | M45: =IF(Tabla1[[#This Row],[Avance_km]]<>"",Tabla1[[#This Row],[Avance_km]],Tabla1[[#This Row],[Avance_Med]])*_xlfn.XLOOKUP(Tabla1[[#This Row],[Codigo_actividad]],Catalogo!$B$6:$B$51,Catalogo!$F$6:$F$51,0) -> 67778.15
A46: 45986 | B46: B | C46: LIRA_GALERAS | D46: AC 8-6-4 in La Lira-Galeras | E46: Direct Current Voltage Gradient DCVG | F46: 5000 | G46: 9000 | H46: =IF(Tabla1[[#This Row],[Codigo_actividad]]<>2.5,IF(((Tabla1[[#This Row],[fin]]-Tabla1[[#This Row],[inicio]])/1000)=0,"",((Tabla1[[#This Row],[fin]]-Tabla1[[#This Row],[inicio]])/1000)),"") -> 4 | J46: 2.3 | K46: =IF(_xlfn.XLOOKUP($J46,Catalogo!$B$7:$B$210,Catalogo!$I$7:$I$210,"",0)=0,"",_xlfn.XLOOKUP($J46,Catalogo!$B$7:$B$210,Catalogo!$I$7:$I$210,"",0)) -> DCVG | L46: 31.54 | M46: =IF(Tabla1[[#This Row],[Avance_km]]<>"",Tabla1[[#This Row],[Avance_km]],Tabla1[[#This Row],[Avance_Med]])*_xlfn.XLOOKUP(Tabla1[[#This Row],[Codigo_actividad]],Catalogo!$B$6:$B$51,Catalogo!$F$6:$F$51,0) -> 54222.52
A47: 45986 | B47: C | C47: LIRA_GALERAS | D47: AC 8-6-4 in La Lira-Galeras | E47: Resistividades pH BRS BPA | F47: 18500 | G47: 24500 | H47: =IF(Tabla1[[#This Row],[Codigo_actividad]]<>2.5,IF(((Tabla1[[#This Row],[fin]]-Tabla1[[#This Row],[inicio]])/1000)=0,"",((Tabla1[[#This Row],[fin]]-Tabla1[[#This Row],[inicio]])/1000)),"") | I47: 10 | J47: 2.5 | K47: =IF(_xlfn.XLOOKUP($J47,Catalogo!$B$7:$B$210,Catalogo!$I$7:$I$210,"",0)=0,"",_xlfn.XLOOKUP($J47,Catalogo!$B$7:$B$210,Catalogo!$I$7:$I$210,"",0)) -> Resistividades pH BSR BPA | L47: 31.54 | M47: =IF(Tabla1[[#This Row],[Avance_km]]<>"",Tabla1[[#This Row],[Avance_km]],Tabla1[[#This Row],[Avance_Med]])*_xlfn.XLOOKUP(Tabla1[[#This Row],[Codigo_actividad]],Catalogo!$B$6:$B$51,Catalogo!$F$6:$F$51,0) -> 46580
A48: 45987 | B48: A | C48: LIRA_GALERAS | D48: AC 8-6-4 in La Lira-Galeras | E48: Direct Current Voltage Gradient DCVG | F48: 18000 | G48: 24000 | H48: =IF(Tabla1[[#This Row],[Codigo_actividad]]<>2.5,IF(((Tabla1[[#This Row],[fin]]-Tabla1[[#This Row],[inicio]])/1000)=0,"",((Tabla1[[#This Row],[fin]]-Tabla1[[#This Row],[inicio]])/1000)),"") -> 6 | J48: 2.3 | K48: =IF(_xlfn.XLOOKUP($J48,Catalogo!$B$7:$B$210,Catalogo!$I$7:$I$210,"",0)=0,"",_xlfn.XLOOKUP($J48,Catalogo!$B$7:$B$210,Catalogo!$I$7:$I$210,"",0)) -> DCVG | L48: 31.54 | M48: =IF(Tabla1[[#This Row],[Avance_km]]<>"",Tabla1[[#This Row],[Avance_km]],Tabla1[[#This Row],[Avance_Med]])*_xlfn.XLOOKUP(Tabla1[[#This Row],[Codigo_actividad]],Catalogo!$B$6:$B$51,Catalogo!$F$6:$F$51,0) -> 81333.78
A49: 45987 | B49: B | C49: LIRA_GALERAS | D49: AC 8-6-4 in La Lira-Galeras | E49: Direct Current Voltage Gradient DCVG | F49: 12000 | G49: 18000 | H49: =IF(Tabla1[[#This Row],[Codigo_actividad]]<>2.5,IF(((Tabla1[[#This Row],[fin]]-Tabla1[[#This Row],[inicio]])/1000)=0,"",((Tabla1[[#This Row],[fin]]-Tabla1[[#This Row],[inicio]])/1000)),"") -> 6 | J49: 2.3 | K49: =IF(_xlfn.XLOOKUP($J49,Catalogo!$B$7:$B$210,Catalogo!$I$7:$I$210,"",0)=0,"",_xlfn.XLOOKUP($J49,Catalogo!$B$7:$B$210,Catalogo!$I$7:$I$210,"",0)) -> DCVG | L49: 31.54 | M49: =IF(Tabla1[[#This Row],[Avance_km]]<>"",Tabla1[[#This Row],[Avance_km]],Tabla1[[#This Row],[Avance_Med]])*_xlfn.XLOOKUP(Tabla1[[#This Row],[Codigo_actividad]],Catalogo!$B$6:$B$51,Catalogo!$F$6:$F$51,0) -> 81333.78
A50: 45987 | B50: C | C50: LIRA_GALERAS | D50: AC 8-6-4 in La Lira-Galeras | E50: Resistividades pH BRS BPA | F50: 24500 | G50: 30000 | H50: =IF(Tabla1[[#This Row],[Codigo_actividad]]<>2.5,IF(((Tabla1[[#This Row],[fin]]-Tabla1[[#This Row],[inicio]])/1000)=0,"",((Tabla1[[#This Row],[fin]]-Tabla1[[#This Row],[inicio]])/1000)),"") | I50: 12 | J50: 2.5 | K50: =IF(_xlfn.XLOOKUP($J50,Catalogo!$B$7:$B$210,Catalogo!$I$7:$I$210,"",0)=0,"",_xlfn.XLOOKUP($J50,Catalogo!$B$7:$B$210,Catalogo!$I$7:$I$210,"",0)) -> Resistividades pH BSR BPA | L50: 31.54 | M50: =IF(Tabla1[[#This Row],[Avance_km]]<>"",Tabla1[[#This Row],[Avance_km]],Tabla1[[#This Row],[Avance_Med]])*_xlfn.XLOOKUP(Tabla1[[#This Row],[Codigo_actividad]],Catalogo!$B$6:$B$51,Catalogo!$F$6:$F$51,0) -> 55896
H51: =IF(Tabla1[[#This Row],[Codigo_actividad]]<>2.5,IF(((Tabla1[[#This Row],[fin]]-Tabla1[[#This Row],[inicio]])/1000)=0,"",((Tabla1[[#This Row],[fin]]-Tabla1[[#This Row],[inicio]])/1000)),"") | K51: =IF(_xlfn.XLOOKUP($J51,Catalogo!$B$7:$B$210,Catalogo!$I$7:$I$210,"",0)=0,"",_xlfn.XLOOKUP($J51,Catalogo!$B$7:$B$210,Catalogo!$I$7:$I$210,"",0)) | M51: =IF(Tabla1[[#This Row],[Avance_km]]<>"",Tabla1[[#This Row],[Avance_km]],Tabla1[[#This Row],[Avance_Med]])*_xlfn.XLOOKUP(Tabla1[[#This Row],[Codigo_actividad]],Catalogo!$B$6:$B$51,Catalogo!$F$6:$F$51,0) -> 0
A52: 45988 | B52: A | C52: LIRA_GALERAS | D52: AC 8-6-4 in La Lira-Galeras | E52: Direct Current Voltage Gradient DCVG | F52: 24000 | G52: 28000 | H52: =IF(Tabla1[[#This Row],[Codigo_actividad]]<>2.5,IF(((Tabla1[[#This Row],[fin]]-Tabla1[[#This Row],[inicio]])/1000)=0,"",((Tabla1[[#This Row],[fin]]-Tabla1[[#This Row],[inicio]])/1000)),"") -> 4 | J52: 2.3 | K52: =IF(_xlfn.XLOOKUP($J52,Catalogo!$B$7:$B$210,Catalogo!$I$7:$I$210,"",0)=0,"",_xlfn.XLOOKUP($J52,Catalogo!$B$7:$B$210,Catalogo!$I$7:$I$210,"",0)) -> DCVG | L52: 31.54 | M52: =IF(Tabla1[[#This Row],[Avance_km]]<>"",Tabla1[[#This Row],[Avance_km]],Tabla1[[#This Row],[Avance_Med]])*_xlfn.XLOOKUP(Tabla1[[#This Row],[Codigo_actividad]],Catalogo!$B$6:$B$51,Catalogo!$F$6:$F$51,0) -> 54222.52
A53: 45988 | B53: B | C53: LIRA_GALERAS | D53: AC 8-6-4 in La Lira-Galeras | E53: Direct Current Voltage Gradient DCVG | F53: 28000 | G53: 31540 | H53: =IF(Tabla1[[#This Row],[Codigo_actividad]]<>2.5,IF(((Tabla1[[#This Row],[fin]]-Tabla1[[#This Row],[inicio]])/1000)=0,"",((Tabla1[[#This Row],[fin]]-Tabla1[[#This Row],[inicio]])/1000)),"") -> 3.54 | J53: 2.3 | K53: =IF(_xlfn.XLOOKUP($J53,Catalogo!$B$7:$B$210,Catalogo!$I$7:$I$210,"",0)=0,"",_xlfn.XLOOKUP($J53,Catalogo!$B$7:$B$210,Catalogo!$I$7:$I$210,"",0)) -> DCVG | L53: 31.54 | M53: =IF(Tabla1[[#This Row],[Avance_km]]<>"",Tabla1[[#This Row],[Avance_km]],Tabla1[[#This Row],[Avance_Med]])*_xlfn.XLOOKUP(Tabla1[[#This Row],[Codigo_actividad]],Catalogo!$B$6:$B$51,Catalogo!$F$6:$F$51,0) -> 47986.93
A54: 45988 | B54: C | C54: PECO_AGROS | D54: PECO II - GALERAS 10 | E54: Resistividades pH BRS BPA | F54: 0 | G54: 1000 | H54: =IF(Tabla1[[#This Row],[Codigo_actividad]]<>2.5,IF(((Tabla1[[#This Row],[fin]]-Tabla1[[#This Row],[inicio]])/1000)=0,"",((Tabla1[[#This Row],[fin]]-Tabla1[[#This Row],[inicio]])/1000)),"") | I54: 2 | J54: 2.5 | K54: =IF(_xlfn.XLOOKUP($J54,Catalogo!$B$7:$B$210,Catalogo!$I$7:$I$210,"",0)=0,"",_xlfn.XLOOKUP($J54,Catalogo!$B$7:$B$210,Catalogo!$I$7:$I$210,"",0)) -> Resistividades pH BSR BPA | L54: 25.4 | M54: =IF(Tabla1[[#This Row],[Avance_km]]<>"",Tabla1[[#This Row],[Avance_km]],Tabla1[[#This Row],[Avance_Med]])*_xlfn.XLOOKUP(Tabla1[[#This Row],[Codigo_actividad]],Catalogo!$B$6:$B$51,Catalogo!$F$6:$F$51,0) -> 9316
A55: 45988 | B55: C | C55: LIRA_GALERAS | D55: AC 8-6-4 in La Lira-Galeras | E55: Resistividades pH BRS BPA | F55: 30000 | G55: 31540 | H55: =IF(Tabla1[[#This Row],[Codigo_actividad]]<>2.5,IF(((Tabla1[[#This Row],[fin]]-Tabla1[[#This Row],[inicio]])/1000)=0,"",((Tabla1[[#This Row],[fin]]-Tabla1[[#This Row],[inicio]])/1000)),"") | I55: 4 | J55: 2.5 | K55: =IF(_xlfn.XLOOKUP($J55,Catalogo!$B$7:$B$210,Catalogo!$I$7:$I$210,"",0)=0,"",_xlfn.XLOOKUP($J55,Catalogo!$B$7:$B$210,Catalogo!$I$7:$I$210,"",0)) -> Resistividades pH BSR BPA | L55: 31.54 | M55: =IF(Tabla1[[#This Row],[Avance_km]]<>"",Tabla1[[#This Row],[Avance_km]],Tabla1[[#This Row],[Avance_Med]])*_xlfn.XLOOKUP(Tabla1[[#This Row],[Codigo_actividad]],Catalogo!$B$6:$B$51,Catalogo!$F$6:$F$51,0) -> 18632
H56: =IF(Tabla1[[#This Row],[Codigo_actividad]]<>2.5,IF(((Tabla1[[#This Row],[fin]]-Tabla1[[#This Row],[inicio]])/1000)=0,"",((Tabla1[[#This Row],[fin]]-Tabla1[[#This Row],[inicio]])/1000)),"") | K56: =IF(_xlfn.XLOOKUP($J56,Catalogo!$B$7:$B$210,Catalogo!$I$7:$I$210,"",0)=0,"",_xlfn.XLOOKUP($J56,Catalogo!$B$7:$B$210,Catalogo!$I$7:$I$210,"",0)) | M56: =IF(Tabla1[[#This Row],[Avance_km]]<>"",Tabla1[[#This Row],[Avance_km]],Tabla1[[#This Row],[Avance_Med]])*_xlfn.XLOOKUP(Tabla1[[#This Row],[Codigo_actividad]],Catalogo!$B$6:$B$51,Catalogo!$F$6:$F$51,0) -> 0
A57: 45989 | B57: A | C57: PECO_AGROS | D57: PECO II - GALERAS 10 | E57: Direct Current Voltage Gradient DCVG | F57: 0 | G57: 5000 | H57: =IF(Tabla1[[#This Row],[Codigo_actividad]]<>2.5,IF(((Tabla1[[#This Row],[fin]]-Tabla1[[#This Row],[inicio]])/1000)=0,"",((Tabla1[[#This Row],[fin]]-Tabla1[[#This Row],[inicio]])/1000)),"") -> 5 | J57: 2.3 | K57: =IF(_xlfn.XLOOKUP($J57,Catalogo!$B$7:$B$210,Catalogo!$I$7:$I$210,"",0)=0,"",_xlfn.XLOOKUP($J57,Catalogo!$B$7:$B$210,Catalogo!$I$7:$I$210,"",0)) -> DCVG | L57: 25.4 | M57: =IF(Tabla1[[#This Row],[Avance_km]]<>"",Tabla1[[#This Row],[Avance_km]],Tabla1[[#This Row],[Avance_Med]])*_xlfn.XLOOKUP(Tabla1[[#This Row],[Codigo_actividad]],Catalogo!$B$6:$B$51,Catalogo!$F$6:$F$51,0) -> 67778.15
A58: 45989 | B58: B | C58: PECO_AGROS | D58: PECO II - GALERAS 10 | E58: Direct Current Voltage Gradient DCVG | F58: 5000 | G58: 10000 | H58: =IF(Tabla1[[#This Row],[Codigo_actividad]]<>2.5,IF(((Tabla1[[#This Row],[fin]]-Tabla1[[#This Row],[inicio]])/1000)=0,"",((Tabla1[[#This Row],[fin]]-Tabla1[[#This Row],[inicio]])/1000)),"") -> 5 | J58: 2.3 | K58: =IF(_xlfn.XLOOKUP($J58,Catalogo!$B$7:$B$210,Catalogo!$I$7:$I$210,"",0)=0,"",_xlfn.XLOOKUP($J58,Catalogo!$B$7:$B$210,Catalogo!$I$7:$I$210,"",0)) -> DCVG | L58: 25.4 | M58: =IF(Tabla1[[#This Row],[Avance_km]]<>"",Tabla1[[#This Row],[Avance_km]],Tabla1[[#This Row],[Avance_Med]])*_xlfn.XLOOKUP(Tabla1[[#This Row],[Codigo_actividad]],Catalogo!$B$6:$B$51,Catalogo!$F$6:$F$51,0) -> 67778.15
A59: 45989 | B59: C | C59: PECO_AGROS | D59: PECO II - GALERAS 10 | E59: Resistividades pH BRS BPA | F59: 1000 | G59: 10500 | H59: =IF(Tabla1[[#This Row],[Codigo_actividad]]<>2.5,IF(((Tabla1[[#This Row],[fin]]-Tabla1[[#This Row],[inicio]])/1000)=0,"",((Tabla1[[#This Row],[fin]]-Tabla1[[#This Row],[inicio]])/1000)),"") | I59: 20 | J59: 2.5 | K59: =IF(_xlfn.XLOOKUP($J59,Catalogo!$B$7:$B$210,Catalogo!$I$7:$I$210,"",0)=0,"",_xlfn.XLOOKUP($J59,Catalogo!$B$7:$B$210,Catalogo!$I$7:$I$210,"",0)) -> Resistividades pH BSR BPA | L59: 25.4 | M59: =IF(Tabla1[[#This Row],[Avance_km]]<>"",Tabla1[[#This Row],[Avance_km]],Tabla1[[#This Row],[Avance_Med]])*_xlfn.XLOOKUP(Tabla1[[#This Row],[Codigo_actividad]],Catalogo!$B$6:$B$51,Catalogo!$F$6:$F$51,0) -> 93160
H60: =IF(Tabla1[[#This Row],[Codigo_actividad]]<>2.5,IF(((Tabla1[[#This Row],[fin]]-Tabla1[[#This Row],[inicio]])/1000)=0,"",((Tabla1[[#This Row],[fin]]-Tabla1[[#This Row],[inicio]])/1000)),"") | K60: =IF(_xlfn.XLOOKUP($J60,Catalogo!$B$7:$B$210,Catalogo!$I$7:$I$210,"",0)=0,"",_xlfn.XLOOKUP($J60,Catalogo!$B$7:$B$210,Catalogo!$I$7:$I$210,"",0)) | M60: =IF(Tabla1[[#This Row],[Avance_km]]<>"",Tabla1[[#This Row],[Avance_km]],Tabla1[[#This Row],[Avance_Med]])*_xlfn.XLOOKUP(Tabla1[[#This Row],[Codigo_actividad]],Catalogo!$B$6:$B$51,Catalogo!$F$6:$F$51,0) -> 0
A61: 45990 | B61: A | C61: PECO_AGROS | D61: PECO II - GALERAS 10 | E61: Direct Current Voltage Gradient DCVG | F61: 10000 | G61: 15300 | H61: =IF(Tabla1[[#This Row],[Codigo_actividad]]<>2.5,IF(((Tabla1[[#This Row],[fin]]-Tabla1[[#This Row],[inicio]])/1000)=0,"",((Tabla1[[#This Row],[fin]]-Tabla1[[#This Row],[inicio]])/1000)),"") -> 5.3 | J61: 2.3 | K61: =IF(_xlfn.XLOOKUP($J61,Catalogo!$B$7:$B$210,Catalogo!$I$7:$I$210,"",0)=0,"",_xlfn.XLOOKUP($J61,Catalogo!$B$7:$B$210,Catalogo!$I$7:$I$210,"",0)) -> DCVG | L61: 25.4 | M61: =IF(Tabla1[[#This Row],[Avance_km]]<>"",Tabla1[[#This Row],[Avance_km]],Tabla1[[#This Row],[Avance_Med]])*_xlfn.XLOOKUP(Tabla1[[#This Row],[Codigo_actividad]],Catalogo!$B$6:$B$51,Catalogo!$F$6:$F$51,0) -> 71844.839
A62: 45990 | B62: B | C62: PECO_AGROS | D62: PECO II - GALERAS 10 | E62: Direct Current Voltage Gradient DCVG | F62: 15300 | G62: 21500 | H62: =IF(Tabla1[[#This Row],[Codigo_actividad]]<>2.5,IF(((Tabla1[[#This Row],[fin]]-Tabla1[[#This Row],[inicio]])/1000)=0,"",((Tabla1[[#This Row],[fin]]-Tabla1[[#This Row],[inicio]])/1000)),"") -> 6.2 | J62: 2.3 | K62: =IF(_xlfn.XLOOKUP($J62,Catalogo!$B$7:$B$210,Catalogo!$I$7:$I$210,"",0)=0,"",_xlfn.XLOOKUP($J62,Catalogo!$B$7:$B$210,Catalogo!$I$7:$I$210,"",0)) -> DCVG | L62: 25.4 | M62: =IF(Tabla1[[#This Row],[Avance_km]]<>"",Tabla1[[#This Row],[Avance_km]],Tabla1[[#This Row],[Avance_Med]])*_xlfn.XLOOKUP(Tabla1[[#This Row],[Codigo_actividad]],Catalogo!$B$6:$B$51,Catalogo!$F$6:$F$51,0) -> 84044.906
A63: 45990 | B63: C | C63: PECO_AGROS | D63: PECO II - GALERAS 10 | E63: Resistividades pH BRS BPA | F63: 10500 | G63: 16500 | H63: =IF(Tabla1[[#This Row],[Codigo_actividad]]<>2.5,IF(((Tabla1[[#This Row],[fin]]-Tabla1[[#This Row],[inicio]])/1000)=0,"",((Tabla1[[#This Row],[fin]]-Tabla1[[#This Row],[inicio]])/1000)),"") | I63: 12 | J63: 2.5 | K63: =IF(_xlfn.XLOOKUP($J63,Catalogo!$B$7:$B$210,Catalogo!$I$7:$I$210,"",0)=0,"",_xlfn.XLOOKUP($J63,Catalogo!$B$7:$B$210,Catalogo!$I$7:$I$210,"",0)) -> Resistividades pH BSR BPA | L63: 25.4 | M63: =IF(Tabla1[[#This Row],[Avance_km]]<>"",Tabla1[[#This Row],[Avance_km]],Tabla1[[#This Row],[Avance_Med]])*_xlfn.XLOOKUP(Tabla1[[#This Row],[Codigo_actividad]],Catalogo!$B$6:$B$51,Catalogo!$F$6:$F$51,0) -> 55896
H64: =IF(Tabla1[[#This Row],[Codigo_actividad]]<>2.5,IF(((Tabla1[[#This Row],[fin]]-Tabla1[[#This Row],[inicio]])/1000)=0,"",((Tabla1[[#This Row],[fin]]-Tabla1[[#This Row],[inicio]])/1000)),"") | K64: =IF(_xlfn.XLOOKUP($J64,Catalogo!$B$7:$B$210,Catalogo!$I$7:$I$210,"",0)=0,"",_xlfn.XLOOKUP($J64,Catalogo!$B$7:$B$210,Catalogo!$I$7:$I$210,"",0)) | M64: =IF(Tabla1[[#This Row],[Avance_km]]<>"",Tabla1[[#This Row],[Avance_km]],Tabla1[[#This Row],[Avance_Med]])*_xlfn.XLOOKUP(Tabla1[[#This Row],[Codigo_actividad]],Catalogo!$B$6:$B$51,Catalogo!$F$6:$F$51,0) -> 0
A65: 45992 | B65: A | C65: PECO_AGROS | D65: AGROS | E65: Direct Current Voltage Gradient DCVG | F65: 0 | G65: 2200 | H65: =IF(Tabla1[[#This Row],[Codigo_actividad]]<>2.5,IF(((Tabla1[[#This Row],[fin]]-Tabla1[[#This Row],[inicio]])/1000)=0,"",((Tabla1[[#This Row],[fin]]-Tabla1[[#This Row],[inicio]])/1000)),"") -> 2.2 | J65: 2.3 | K65: =IF(_xlfn.XLOOKUP($J65,Catalogo!$B$7:$B$210,Catalogo!$I$7:$I$210,"",0)=0,"",_xlfn.XLOOKUP($J65,Catalogo!$B$7:$B$210,Catalogo!$I$7:$I$210,"",0)) -> DCVG | L65: 2.2 | M65: =IF(Tabla1[[#This Row],[Avance_km]]<>"",Tabla1[[#This Row],[Avance_km]],Tabla1[[#This Row],[Avance_Med]])*_xlfn.XLOOKUP(Tabla1[[#This Row],[Codigo_actividad]],Catalogo!$B$6:$B$51,Catalogo!$F$6:$F$51,0) -> 29822.386
A66: 45992 | B66: A | C66: PECO_AGROS | D66: SUNNY FIELDS | E66: Direct Current Voltage Gradient DCVG | F66: 0 | G66: 2576 | H66: =IF(Tabla1[[#This Row],[Codigo_actividad]]<>2.5,IF(((Tabla1[[#This Row],[fin]]-Tabla1[[#This Row],[inicio]])/1000)=0,"",((Tabla1[[#This Row],[fin]]-Tabla1[[#This Row],[inicio]])/1000)),"") -> 2.576 | J66: 2.3 | K66: =IF(_xlfn.XLOOKUP($J66,Catalogo!$B$7:$B$210,Catalogo!$I$7:$I$210,"",0)=0,"",_xlfn.XLOOKUP($J66,Catalogo!$B$7:$B$210,Catalogo!$I$7:$I$210,"",0)) -> DCVG | L66: 2.576 | M66: =IF(Tabla1[[#This Row],[Avance_km]]<>"",Tabla1[[#This Row],[Avance_km]],Tabla1[[#This Row],[Avance_Med]])*_xlfn.XLOOKUP(Tabla1[[#This Row],[Codigo_actividad]],Catalogo!$B$6:$B$51,Catalogo!$F$6:$F$51,0) -> 34919.303
A67: 45992 | B67: A | C67: PECO_AGROS | D67: MOLINOS ANAHUAC | E67: Direct Current Voltage Gradient DCVG | F67: 0 | G67: 20 | H67: =IF(Tabla1[[#This Row],[Codigo_actividad]]<>2.5,IF(((Tabla1[[#This Row],[fin]]-Tabla1[[#This Row],[inicio]])/1000)=0,"",((Tabla1[[#This Row],[fin]]-Tabla1[[#This Row],[inicio]])/1000)),"") -> 0.02 | J67: 2.3 | K67: =IF(_xlfn.XLOOKUP($J67,Catalogo!$B$7:$B$210,Catalogo!$I$7:$I$210,"",0)=0,"",_xlfn.XLOOKUP($J67,Catalogo!$B$7:$B$210,Catalogo!$I$7:$I$210,"",0)) -> DCVG | L67: 0.02 | M67: =IF(Tabla1[[#This Row],[Avance_km]]<>"",Tabla1[[#This Row],[Avance_km]],Tabla1[[#This Row],[Avance_Med]])*_xlfn.XLOOKUP(Tabla1[[#This Row],[Codigo_actividad]],Catalogo!$B$6:$B$51,Catalogo!$F$6:$F$51,0) -> 271.1126
A68: 45992 | B68: A | C68: PECO_AGROS | D68: MOLINOS ANAHUAC | E68: Localización de Tubería con Equipo de RadioDetección. | F68: 0 | G68: 20 | H68: =IF(Tabla1[[#This Row],[Codigo_actividad]]<>2.5,IF(((Tabla1[[#This Row],[fin]]-Tabla1[[#This Row],[inicio]])/1000)=0,"",((Tabla1[[#This Row],[fin]]-Tabla1[[#This Row],[inicio]])/1000)),"") -> 0.02 | J68: 2.6 | K68: =IF(_xlfn.XLOOKUP($J68,Catalogo!$B$7:$B$210,Catalogo!$I$7:$I$210,"",0)=0,"",_xlfn.XLOOKUP($J68,Catalogo!$B$7:$B$210,Catalogo!$I$7:$I$210,"",0)) -> Localizacion | L68: 0.02 | M68: =IF(Tabla1[[#This Row],[Avance_km]]<>"",Tabla1[[#This Row],[Avance_km]],Tabla1[[#This Row],[Avance_Med]])*_xlfn.XLOOKUP(Tabla1[[#This Row],[Codigo_actividad]],Catalogo!$B$6:$B$51,Catalogo!$F$6:$F$51,0) -> 45.1484
A69: 45992 | B69: A | C69: PECO_AGROS | D69: BEL GIARDINO | E69: Direct Current Voltage Gradient DCVG | F69: 0 | G69: 125 | H69: =IF(Tabla1[[#This Row],[Codigo_actividad]]<>2.5,IF(((Tabla1[[#This Row],[fin]]-Tabla1[[#This Row],[inicio]])/1000)=0,"",((Tabla1[[#This Row],[fin]]-Tabla1[[#This Row],[inicio]])/1000)),"") -> 0.125 | J69: 2.3 | K69: =IF(_xlfn.XLOOKUP($J69,Catalogo!$B$7:$B$210,Catalogo!$I$7:$I$210,"",0)=0,"",_xlfn.XLOOKUP($J69,Catalogo!$B$7:$B$210,Catalogo!$I$7:$I$210,"",0)) -> DCVG | L69: 0.125 | M69: =IF(Tabla1[[#This Row],[Avance_km]]<>"",Tabla1[[#This Row],[Avance_km]],Tabla1[[#This Row],[Avance_Med]])*_xlfn.XLOOKUP(Tabla1[[#This Row],[Codigo_actividad]],Catalogo!$B$6:$B$51,Catalogo!$F$6:$F$51,0) -> 1694.4537
A70: 45992 | B70: A | C70: PECO_AGROS | D70: ERM DESHITEC | E70: Direct Current Voltage Gradient DCVG | F70: 0 | G70: 120 | H70: =IF(Tabla1[[#This Row],[Codigo_actividad]]<>2.5,IF(((Tabla1[[#This Row],[fin]]-Tabla1[[#This Row],[inicio]])/1000)=0,"",((Tabla1[[#This Row],[fin]]-Tabla1[[#This Row],[inicio]])/1000)),"") -> 0.12 | J70: 2.3 | K70: =IF(_xlfn.XLOOKUP($J70,Catalogo!$B$7:$B$210,Catalogo!$I$7:$I$210,"",0)=0,"",_xlfn.XLOOKUP($J70,Catalogo!$B$7:$B$210,Catalogo!$I$7:$I$210,"",0)) -> DCVG | L70: 0.12 | M70: =IF(Tabla1[[#This Row],[Avance_km]]<>"",Tabla1[[#This Row],[Avance_km]],Tabla1[[#This Row],[Avance_Med]])*_xlfn.XLOOKUP(Tabla1[[#This Row],[Codigo_actividad]],Catalogo!$B$6:$B$51,Catalogo!$F$6:$F$51,0) -> 1626.6756
A71: 45992 | B71: B | C71: PECO_AGROS | D71: PECO II - GALERAS 10 | E71: Direct Current Voltage Gradient DCVG | F71: 21500 | G71: 25400 | H71: =IF(Tabla1[[#This Row],[Codigo_actividad]]<>2.5,IF(((Tabla1[[#This Row],[fin]]-Tabla1[[#This Row],[inicio]])/1000)=0,"",((Tabla1[[#This Row],[fin]]-Tabla1[[#This Row],[inicio]])/1000)),"") -> 3.9 | J71: 2.3 | K71: =IF(_xlfn.XLOOKUP($J71,Catalogo!$B$7:$B$210,Catalogo!$I$7:$I$210,"",0)=0,"",_xlfn.XLOOKUP($J71,Catalogo!$B$7:$B$210,Catalogo!$I$7:$I$210,"",0)) -> DCVG | L71: 25.4 | M71: =IF(Tabla1[[#This Row],[Avance_km]]<>"",Tabla1[[#This Row],[Avance_km]],Tabla1[[#This Row],[Avance_Med]])*_xlfn.XLOOKUP(Tabla1[[#This Row],[Codigo_actividad]],Catalogo!$B$6:$B$51,Catalogo!$F$6:$F$51,0) -> 52866.957
A72: 45992 | B72: B | C72: PECO_AGROS | D72: PRIME HASRVEST | E72: Direct Current Voltage Gradient DCVG | F72: 0 | G72: 741 | H72: =IF(Tabla1[[#This Row],[Codigo_actividad]]<>2.5,IF(((Tabla1[[#This Row],[fin]]-Tabla1[[#This Row],[inicio]])/1000)=0,"",((Tabla1[[#This Row],[fin]]-Tabla1[[#This Row],[inicio]])/1000)),"") -> 0.741 | J72: 2.3 | K72: =IF(_xlfn.XLOOKUP($J72,Catalogo!$B$7:$B$210,Catalogo!$I$7:$I$210,"",0)=0,"",_xlfn.XLOOKUP($J72,Catalogo!$B$7:$B$210,Catalogo!$I$7:$I$210,"",0)) -> DCVG | L72: 0.741 | M72: =IF(Tabla1[[#This Row],[Avance_km]]<>"",Tabla1[[#This Row],[Avance_km]],Tabla1[[#This Row],[Avance_Med]])*_xlfn.XLOOKUP(Tabla1[[#This Row],[Codigo_actividad]],Catalogo!$B$6:$B$51,Catalogo!$F$6:$F$51,0) -> 10044.722
A73: 45992 | B73: B | C73: PECO_AGROS | D73: ERM FH FIBRAS | E73: Direct Current Voltage Gradient DCVG | F73: 0 | G73: 40 | H73: =IF(Tabla1[[#This Row],[Codigo_actividad]]<>2.5,IF(((Tabla1[[#This Row],[fin]]-Tabla1[[#This Row],[inicio]])/1000)=0,"",((Tabla1[[#This Row],[fin]]-Tabla1[[#This Row],[inicio]])/1000)),"") -> 0.04 | J73: 2.3 | K73: =IF(_xlfn.XLOOKUP($J73,Catalogo!$B$7:$B$210,Catalogo!$I$7:$I$210,"",0)=0,"",_xlfn.XLOOKUP($J73,Catalogo!$B$7:$B$210,Catalogo!$I$7:$I$210,"",0)) -> DCVG | L73: 0.04 | M73: =IF(Tabla1[[#This Row],[Avance_km]]<>"",Tabla1[[#This Row],[Avance_km]],Tabla1[[#This Row],[Avance_Med]])*_xlfn.XLOOKUP(Tabla1[[#This Row],[Codigo_actividad]],Catalogo!$B$6:$B$51,Catalogo!$F$6:$F$51,0) -> 542.2252
A74: 45992 | B74: B | C74: PECO_AGROS | D74: LA BONITA | E74: Direct Current Voltage Gradient DCVG | F74: 0 | G74: 479 | H74: =IF(Tabla1[[#This Row],[Codigo_actividad]]<>2.5,IF(((Tabla1[[#This Row],[fin]]-Tabla1[[#This Row],[inicio]])/1000)=0,"",((Tabla1[[#This Row],[fin]]-Tabla1[[#This Row],[inicio]])/1000)),"") -> 0.479 | J74: 2.3 | K74: =IF(_xlfn.XLOOKUP($J74,Catalogo!$B$7:$B$210,Catalogo!$I$7:$I$210,"",0)=0,"",_xlfn.XLOOKUP($J74,Catalogo!$B$7:$B$210,Catalogo!$I$7:$I$210,"",0)) -> DCVG | L74: 0.479 | M74: =IF(Tabla1[[#This Row],[Avance_km]]<>"",Tabla1[[#This Row],[Avance_km]],Tabla1[[#This Row],[Avance_Med]])*_xlfn.XLOOKUP(Tabla1[[#This Row],[Codigo_actividad]],Catalogo!$B$6:$B$51,Catalogo!$F$6:$F$51,0) -> 6493.1468
A75: 45992 | B75: C | C75: PECO_AGROS | D75: PECO II - GALERAS 10 | E75: Resistividades pH BRS BPA | F75: 16500 | G75: 25400 | H75: =IF(Tabla1[[#This Row],[Codigo_actividad]]<>2.5,IF(((Tabla1[[#This Row],[fin]]-Tabla1[[#This Row],[inicio]])/1000)=0,"",((Tabla1[[#This Row],[fin]]-Tabla1[[#This Row],[inicio]])/1000)),"") | I75: 18 | J75: 2.5 | K75: =IF(_xlfn.XLOOKUP($J75,Catalogo!$B$7:$B$210,Catalogo!$I$7:$I$210,"",0)=0,"",_xlfn.XLOOKUP($J75,Catalogo!$B$7:$B$210,Catalogo!$I$7:$I$210,"",0)) -> Resistividades pH BSR BPA | L75: 25.4 | M75: =IF(Tabla1[[#This Row],[Avance_km]]<>"",Tabla1[[#This Row],[Avance_km]],Tabla1[[#This Row],[Avance_Med]])*_xlfn.XLOOKUP(Tabla1[[#This Row],[Codigo_actividad]],Catalogo!$B$6:$B$51,Catalogo!$F$6:$F$51,0) -> 83844
A76: 45982 | B76: B | C76: PECO_AGROS | D76: ED AGROPARK II (GAS PRIMO) | E76: Direct Current Voltage Gradient DCVG | F76: 0 | G76: 9 | H76: =IF(Tabla1[[#This Row],[Codigo_actividad]]<>2.5,IF(((Tabla1[[#This Row],[fin]]-Tabla1[[#This Row],[inicio]])/1000)=0,"",((Tabla1[[#This Row],[fin]]-Tabla1[[#This Row],[inicio]])/1000)),"") -> 0.009 | J76: 2.3 | K76: =IF(_xlfn.XLOOKUP($J76,Catalogo!$B$7:$B$210,Catalogo!$I$7:$I$210,"",0)=0,"",_xlfn.XLOOKUP($J76,Catalogo!$B$7:$B$210,Catalogo!$I$7:$I$210,"",0)) -> DCVG | L76: 0.009 | M76: =IF(Tabla1[[#This Row],[Avance_km]]<>"",Tabla1[[#This Row],[Avance_km]],Tabla1[[#This Row],[Avance_Med]])*_xlfn.XLOOKUP(Tabla1[[#This Row],[Codigo_actividad]],Catalogo!$B$6:$B$51,Catalogo!$F$6:$F$51,0) -> 122.00067
H77: =IF(Tabla1[[#This Row],[Codigo_actividad]]<>2.5,IF(((Tabla1[[#This Row],[fin]]-Tabla1[[#This Row],[inicio]])/1000)=0,"",((Tabla1[[#This Row],[fin]]-Tabla1[[#This Row],[inicio]])/1000)),"") | K77: =IF(_xlfn.XLOOKUP($J77,Catalogo!$B$7:$B$210,Catalogo!$I$7:$I$210,"",0)=0,"",_xlfn.XLOOKUP($J77,Catalogo!$B$7:$B$210,Catalogo!$I$7:$I$210,"",0)) | M77: =IF(Tabla1[[#This Row],[Avance_km]]<>"",Tabla1[[#This Row],[Avance_km]],Tabla1[[#This Row],[Avance_Med]])*_xlfn.XLOOKUP(Tabla1[[#This Row],[Codigo_actividad]],Catalogo!$B$6:$B$51,Catalogo!$F$6:$F$51,0) -> 0
A78: 45993 | B78: A | C78: LIRA_GALERAS | D78: FRESHLLACA | E78: Direct Current Voltage Gradient DCVG | F78: 0 | G78: 20 | H78: =IF(Tabla1[[#This Row],[Codigo_actividad]]<>2.5,IF(((Tabla1[[#This Row],[fin]]-Tabla1[[#This Row],[inicio]])/1000)=0,"",((Tabla1[[#This Row],[fin]]-Tabla1[[#This Row],[inicio]])/1000)),"") -> 0.02 | J78: 2.3 | K78: =IF(_xlfn.XLOOKUP($J78,Catalogo!$B$7:$B$210,Catalogo!$I$7:$I$210,"",0)=0,"",_xlfn.XLOOKUP($J78,Catalogo!$B$7:$B$210,Catalogo!$I$7:$I$210,"",0)) -> DCVG | L78: 0.02 | M78: =IF(Tabla1[[#This Row],[Avance_km]]<>"",Tabla1[[#This Row],[Avance_km]],Tabla1[[#This Row],[Avance_Med]])*_xlfn.XLOOKUP(Tabla1[[#This Row],[Codigo_actividad]],Catalogo!$B$6:$B$51,Catalogo!$F$6:$F$51,0) -> 271.1126
A79: 45993 | B79: A | C79: LIRA_GALERAS | D79: FRESHLLACA | E79: Localización de Tubería con Equipo de RadioDetección. | F79: 0 | G79: 20 | H79: =IF(Tabla1[[#This Row],[Codigo_actividad]]<>2.5,IF(((Tabla1[[#This Row],[fin]]-Tabla1[[#This Row],[inicio]])/1000)=0,"",((Tabla1[[#This Row],[fin]]-Tabla1[[#This Row],[inicio]])/1000)),"") -> 0.02 | J79: 2.6 | K79: =IF(_xlfn.XLOOKUP($J79,Catalogo!$B$7:$B$210,Catalogo!$I$7:$I$210,"",0)=0,"",_xlfn.XLOOKUP($J79,Catalogo!$B$7:$B$210,Catalogo!$I$7:$I$210,"",0)) -> Localizacion | L79: 0.02 | M79: =IF(Tabla1[[#This Row],[Avance_km]]<>"",Tabla1[[#This Row],[Avance_km]],Tabla1[[#This Row],[Avance_Med]])*_xlfn.XLOOKUP(Tabla1[[#This Row],[Codigo_actividad]],Catalogo!$B$6:$B$51,Catalogo!$F$6:$F$51,0) -> 45.1484
A80: 45993 | B80: A | C80: LIRA_GALERAS | D80: RANCHO HUMUS | E80: Direct Current Voltage Gradient DCVG | F80: 0 | G80: 70 | H80: =IF(Tabla1[[#This Row],[Codigo_actividad]]<>2.5,IF(((Tabla1[[#This Row],[fin]]-Tabla1[[#This Row],[inicio]])/1000)=0,"",((Tabla1[[#This Row],[fin]]-Tabla1[[#This Row],[inicio]])/1000)),"") -> 0.07 | J80: 2.3 | K80: =IF(_xlfn.XLOOKUP($J80,Catalogo!$B$7:$B$210,Catalogo!$I$7:$I$210,"",0)=0,"",_xlfn.XLOOKUP($J80,Catalogo!$B$7:$B$210,Catalogo!$I$7:$I$210,"",0)) -> DCVG | L80: 0.07 | M80: =IF(Tabla1[[#This Row],[Avance_km]]<>"",Tabla1[[#This Row],[Avance_km]],Tabla1[[#This Row],[Avance_Med]])*_xlfn.XLOOKUP(Tabla1[[#This Row],[Codigo_actividad]],Catalogo!$B$6:$B$51,Catalogo!$F$6:$F$51,0) -> 948.8941
A81: 45993 | B81: A | C81: LIRA_GALERAS | D81: RANCHO HUMUS | E81: Localización de Tubería con Equipo de RadioDetección. | F81: 0 | G81: 70 | H81: =IF(Tabla1[[#This Row],[Codigo_actividad]]<>2.5,IF(((Tabla1[[#This Row],[fin]]-Tabla1[[#This Row],[inicio]])/1000)=0,"",((Tabla1[[#This Row],[fin]]-Tabla1[[#This Row],[inicio]])/1000)),"") -> 0.07 | J81: 2.6 | K81: =IF(_xlfn.XLOOKUP($J81,Catalogo!$B$7:$B$210,Catalogo!$I$7:$I$210,"",0)=0,"",_xlfn.XLOOKUP($J81,Catalogo!$B$7:$B$210,Catalogo!$I$7:$I$210,"",0)) -> Localizacion | L81: 0.07 | M81: =IF(Tabla1[[#This Row],[Avance_km]]<>"",Tabla1[[#This Row],[Avance_km]],Tabla1[[#This Row],[Avance_Med]])*_xlfn.XLOOKUP(Tabla1[[#This Row],[Codigo_actividad]],Catalogo!$B$6:$B$51,Catalogo!$F$6:$F$51,0) -> 158.0194
A82: 45993 | B82: A | C82: LIRA_GALERAS | D82: GPO. PRODUCTIVO LA LIRA | E82: Direct Current Voltage Gradient DCVG | F82: 0 | G82: 70 | H82: =IF(Tabla1[[#This Row],[Codigo_actividad]]<>2.5,IF(((Tabla1[[#This Row],[fin]]-Tabla1[[#This Row],[inicio]])/1000)=0,"",((Tabla1[[#This Row],[fin]]-Tabla1[[#This Row],[inicio]])/1000)),"") -> 0.07 | J82: 2.3 | K82: =IF(_xlfn.XLOOKUP($J82,Catalogo!$B$7:$B$210,Catalogo!$I$7:$I$210,"",0)=0,"",_xlfn.XLOOKUP($J82,Catalogo!$B$7:$B$210,Catalogo!$I$7:$I$210,"",0)) -> DCVG | L82: 0.07 | M82: =IF(Tabla1[[#This Row],[Avance_km]]<>"",Tabla1[[#This Row],[Avance_km]],Tabla1[[#This Row],[Avance_Med]])*_xlfn.XLOOKUP(Tabla1[[#This Row],[Codigo_actividad]],Catalogo!$B$6:$B$51,Catalogo!$F$6:$F$51,0) -> 948.8941
A83: 45993 | B83: A | C83: LIRA_GALERAS | D83: GPO. PRODUCTIVO LA LIRA | E83: Localización de Tubería con Equipo de RadioDetección. | F83: 0 | G83: 70 | H83: =IF(Tabla1[[#This Row],[Codigo_actividad]]<>2.5,IF(((Tabla1[[#This Row],[fin]]-Tabla1[[#This Row],[inicio]])/1000)=0,"",((Tabla1[[#This Row],[fin]]-Tabla1[[#This Row],[inicio]])/1000)),"") -> 0.07 | J83: 2.6 | K83: =IF(_xlfn.XLOOKUP($J83,Catalogo!$B$7:$B$210,Catalogo!$I$7:$I$210,"",0)=0,"",_xlfn.XLOOKUP($J83,Catalogo!$B$7:$B$210,Catalogo!$I$7:$I$210,"",0)) -> Localizacion | L83: 0.07 | M83: =IF(Tabla1[[#This Row],[Avance_km]]<>"",Tabla1[[#This Row],[Avance_km]],Tabla1[[#This Row],[Avance_Med]])*_xlfn.XLOOKUP(Tabla1[[#This Row],[Codigo_actividad]],Catalogo!$B$6:$B$51,Catalogo!$F$6:$F$51,0) -> 158.0194
A84: 45993 | B84: A | C84: LIRA_GALERAS | D84: ED PARQUE INDUSTRIAL PYME | E84: Direct Current Voltage Gradient DCVG | F84: 0 | G84: 15 | H84: =IF(Tabla1[[#This Row],[Codigo_actividad]]<>2.5,IF(((Tabla1[[#This Row],[fin]]-Tabla1[[#This Row],[inicio]])/1000)=0,"",((Tabla1[[#This Row],[fin]]-Tabla1[[#This Row],[inicio]])/1000)),"") -> 0.015 | J84: 2.3 | K84: =IF(_xlfn.XLOOKUP($J84,Catalogo!$B$7:$B$210,Catalogo!$I$7:$I$210,"",0)=0,"",_xlfn.XLOOKUP($J84,Catalogo!$B$7:$B$210,Catalogo!$I$7:$I$210,"",0)) -> DCVG | L84: 0.015 | M84: =IF(Tabla1[[#This Row],[Avance_km]]<>"",Tabla1[[#This Row],[Avance_km]],Tabla1[[#This Row],[Avance_Med]])*_xlfn.XLOOKUP(Tabla1[[#This Row],[Codigo_actividad]],Catalogo!$B$6:$B$51,Catalogo!$F$6:$F$51,0) -> 203.33445
A85: 45993 | B85: A | C85: LIRA_GALERAS | D85: ED PARQUE INDUSTRIAL PYME | E85: Localización de Tubería con Equipo de RadioDetección. | F85: 0 | G85: 15 | H85: =IF(Tabla1[[#This Row],[Codigo_actividad]]<>2.5,IF(((Tabla1[[#This Row],[fin]]-Tabla1[[#This Row],[inicio]])/1000)=0,"",((Tabla1[[#This Row],[fin]]-Tabla1[[#This Row],[inicio]])/1000)),"") -> 0.015 | J85: 2.6 | K85: =IF(_xlfn.XLOOKUP($J85,Catalogo!$B$7:$B$210,Catalogo!$I$7:$I$210,"",0)=0,"",_xlfn.XLOOKUP($J85,Catalogo!$B$7:$B$210,Catalogo!$I$7:$I$210,"",0)) -> Localizacion | L85: 0.015 | M85: =IF(Tabla1[[#This Row],[Avance_km]]<>"",Tabla1[[#This Row],[Avance_km]],Tabla1[[#This Row],[Avance_Med]])*_xlfn.XLOOKUP(Tabla1[[#This Row],[Codigo_actividad]],Catalogo!$B$6:$B$51,Catalogo!$F$6:$F$51,0) -> 33.8613
A86: 45993 | B86: A | C86: LIRA_GALERAS | D86: ALESTRA | E86: Direct Current Voltage Gradient DCVG | F86: 0 | G86: 1982 | H86: =IF(Tabla1[[#This Row],[Codigo_actividad]]<>2.5,IF(((Tabla1[[#This Row],[fin]]-Tabla1[[#This Row],[inicio]])/1000)=0,"",((Tabla1[[#This Row],[fin]]-Tabla1[[#This Row],[inicio]])/1000)),"") -> 1.982 | J86: 2.3 | K86: =IF(_xlfn.XLOOKUP($J86,Catalogo!$B$7:$B$210,Catalogo!$I$7:$I$210,"",0)=0,"",_xlfn.XLOOKUP($J86,Catalogo!$B$7:$B$210,Catalogo!$I$7:$I$210,"",0)) -> DCVG | L86: 1.982 | M86: =IF(Tabla1[[#This Row],[Avance_km]]<>"",Tabla1[[#This Row],[Avance_km]],Tabla1[[#This Row],[Avance_Med]])*_xlfn.XLOOKUP(Tabla1[[#This Row],[Codigo_actividad]],Catalogo!$B$6:$B$51,Catalogo!$F$6:$F$51,0) -> 26867.259
A87: 45993 | B87: A | C87: LIRA_GALERAS | D87: ITASA | E87: Direct Current Voltage Gradient DCVG | F87: 0 | G87: 15 | H87: =IF(Tabla1[[#This Row],[Codigo_actividad]]<>2.5,IF(((Tabla1[[#This Row],[fin]]-Tabla1[[#This Row],[inicio]])/1000)=0,"",((Tabla1[[#This Row],[fin]]-Tabla1[[#This Row],[inicio]])/1000)),"") -> 0.015 | J87: 2.3 | K87: =IF(_xlfn.XLOOKUP($J87,Catalogo!$B$7:$B$210,Catalogo!$I$7:$I$210,"",0)=0,"",_xlfn.XLOOKUP($J87,Catalogo!$B$7:$B$210,Catalogo!$I$7:$I$210,"",0)) -> DCVG | L87: 0.015 | M87: =IF(Tabla1[[#This Row],[Avance_km]]<>"",Tabla1[[#This Row],[Avance_km]],Tabla1[[#This Row],[Avance_Med]])*_xlfn.XLOOKUP(Tabla1[[#This Row],[Codigo_actividad]],Catalogo!$B$6:$B$51,Catalogo!$F$6:$F$51,0) -> 203.33445
A88: 45993 | B88: A | C88: LIRA_GALERAS | D88: HUAWEI | E88: Direct Current Voltage Gradient DCVG | F88: 0 | G88: 175 | H88: =IF(Tabla1[[#This Row],[Codigo_actividad]]<>2.5,IF(((Tabla1[[#This Row],[fin]]-Tabla1[[#This Row],[inicio]])/1000)=0,"",((Tabla1[[#This Row],[fin]]-Tabla1[[#This Row],[inicio]])/1000)),"") -> 0.175 | J88: 2.3 | K88: =IF(_xlfn.XLOOKUP($J88,Catalogo!$B$7:$B$210,Catalogo!$I$7:$I$210,"",0)=0,"",_xlfn.XLOOKUP($J88,Catalogo!$B$7:$B$210,Catalogo!$I$7:$I$210,"",0)) -> DCVG | L88: 0.175 | M88: =IF(Tabla1[[#This Row],[Avance_km]]<>"",Tabla1[[#This Row],[Avance_km]],Tabla1[[#This Row],[Avance_Med]])*_xlfn.XLOOKUP(Tabla1[[#This Row],[Codigo_actividad]],Catalogo!$B$6:$B$51,Catalogo!$F$6:$F$51,0) -> 2372.2352
A89: 45993 | B89: A | C89: LIRA_GALERAS | D89: ED EL COLORADO | E89: Localización de Tubería con Equipo de RadioDetección. | F89: 0 | G89: 19 | H89: =IF(Tabla1[[#This Row],[Codigo_actividad]]<>2.5,IF(((Tabla1[[#This Row],[fin]]-Tabla1[[#This Row],[inicio]])/1000)=0,"",((Tabla1[[#This Row],[fin]]-Tabla1[[#This Row],[inicio]])/1000)),"") -> 0.019 | J89: 2.6 | K89: =IF(_xlfn.XLOOKUP($J89,Catalogo!$B$7:$B$210,Catalogo!$I$7:$I$210,"",0)=0,"",_xlfn.XLOOKUP($J89,Catalogo!$B$7:$B$210,Catalogo!$I$7:$I$210,"",0)) -> Localizacion | L89: 0.019 | M89: =IF(Tabla1[[#This Row],[Avance_km]]<>"",Tabla1[[#This Row],[Avance_km]],Tabla1[[#This Row],[Avance_Med]])*_xlfn.XLOOKUP(Tabla1[[#This Row],[Codigo_actividad]],Catalogo!$B$6:$B$51,Catalogo!$F$6:$F$51,0) -> 42.89098
... A101: 45993 | B101: B | C101: LIRA_GALERAS | D101: STEERINGMEX | E101: Localización de Tubería con Equipo de RadioDetección. | F101: 0 | G101: 12 | H101: =IF(Tabla1[[#This Row],[Codigo_actividad]]<>2.5,IF(((Tabla1[[#This Row],[fin]]-Tabla1[[#This Row],[inicio]])/1000)=0,"",((Tabla1[[#This Row],[fin]]-Tabla1[[#This Row],[inicio]])/1000)),"") -> 0.012 | J101: 2.6 | K101: =IF(_xlfn.XLOOKUP($J101,Catalogo!$B$7:$B$210,Catalogo!$I$7:$I$210,"",0)=0,"",_xlfn.XLOOKUP($J101,Catalogo!$B$7:$B$210,Catalogo!$I$7:$I$210,"",0)) -> Localizacion | L101: 0.012 | M101: =IF(Tabla1[[#This Row],[Avance_km]]<>"",Tabla1[[#This Row],[Avance_km]],Tabla1[[#This Row],[Avance_Med]])*_xlfn.XLOOKUP(Tabla1[[#This Row],[Codigo_actividad]],Catalogo!$B$6:$B$51,Catalogo!$F$6:$F$51,0) -> 27.08904
A102: 45993 | B102: C | C102: LIRA_GALERAS | D102: ATONGO | E102: Resistividades pH BRS BPA | F102: 0 | G102: 6500 | H102: =IF(Tabla1[[#This Row],[Codigo_actividad]]<>2.5,IF(((Tabla1[[#This Row],[fin]]-Tabla1[[#This Row],[inicio]])/1000)=0,"",((Tabla1[[#This Row],[fin]]-Tabla1[[#This Row],[inicio]])/1000)),"") | I102: 12 | J102: 2.5 | K102: =IF(_xlfn.XLOOKUP($J102,Catalogo!$B$7:$B$210,Catalogo!$I$7:$I$210,"",0)=0,"",_xlfn.XLOOKUP($J102,Catalogo!$B$7:$B$210,Catalogo!$I$7:$I$210,"",0)) -> Resistividades pH BSR BPA | L102: 12.657 | M102: =IF(Tabla1[[#This Row],[Avance_km]]<>"",Tabla1[[#This Row],[Avance_km]],Tabla1[[#This Row],[Avance_Med]])*_xlfn.XLOOKUP(Tabla1[[#This Row],[Codigo_actividad]],Catalogo!$B$6:$B$51,Catalogo!$F$6:$F$51,0) -> 55896
H103: =IF(Tabla1[[#This Row],[Codigo_actividad]]<>2.5,IF(((Tabla1[[#This Row],[fin]]-Tabla1[[#This Row],[inicio]])/1000)=0,"",((Tabla1[[#This Row],[fin]]-Tabla1[[#This Row],[inicio]])/1000)),"") | K103: =IF(_xlfn.XLOOKUP($J103,Catalogo!$B$7:$B$210,Catalogo!$I$7:$I$210,"",0)=0,"",_xlfn.XLOOKUP($J103,Catalogo!$B$7:$B$210,Catalogo!$I$7:$I$210,"",0)) | M103: =IF(Tabla1[[#This Row],[Avance_km]]<>"",Tabla1[[#This Row],[Avance_km]],Tabla1[[#This Row],[Avance_Med]])*_xlfn.XLOOKUP(Tabla1[[#This Row],[Codigo_actividad]],Catalogo!$B$6:$B$51,Catalogo!$F$6:$F$51,0) -> 0
A104: 45994 | B104: A | C104: LIRA_GALERAS | D104: NATGAS EL MARQUES | E104: Localización de Tubería con Equipo de RadioDetección. | F104: 0 | G104: 1054 | H104: =IF(Tabla1[[#This Row],[Codigo_actividad]]<>2.5,IF(((Tabla1[[#This Row],[fin]]-Tabla1[[#This Row],[inicio]])/1000)=0,"",((Tabla1[[#This Row],[fin]]-Tabla1[[#This Row],[inicio]])/1000)),"") -> 1.054 | J104: 2.6 | K104: =IF(_xlfn.XLOOKUP($J104,Catalogo!$B$7:$B$210,Catalogo!$I$7:$I$210,"",0)=0,"",_xlfn.XLOOKUP($J104,Catalogo!$B$7:$B$210,Catalogo!$I$7:$I$210,"",0)) -> Localizacion | L104: 1.054 | M104: =IF(Tabla1[[#This Row],[Avance_km]]<>"",Tabla1[[#This Row],[Avance_km]],Tabla1[[#This Row],[Avance_Med]])*_xlfn.XLOOKUP(Tabla1[[#This Row],[Codigo_actividad]],Catalogo!$B$6:$B$51,Catalogo!$F$6:$F$51,0) -> 2379.3207
A105: 45994 | B105: A | C105: LIRA_GALERAS | D105: NATGAS EL MARQUES | E105: Direct Current Voltage Gradient DCVG | F105: 0 | G105: 1054 | H105: =IF(Tabla1[[#This Row],[Codigo_actividad]]<>2.5,IF(((Tabla1[[#This Row],[fin]]-Tabla1[[#This Row],[inicio]])/1000)=0,"",((Tabla1[[#This Row],[fin]]-Tabla1[[#This Row],[inicio]])/1000)),"") -> 1.054 | J105: 2.3 | K105: =IF(_xlfn.XLOOKUP($J105,Catalogo!$B$7:$B$210,Catalogo!$I$7:$I$210,"",0)=0,"",_xlfn.XLOOKUP($J105,Catalogo!$B$7:$B$210,Catalogo!$I$7:$I$210,"",0)) -> DCVG | L105: 1.054 | M105: =IF(Tabla1[[#This Row],[Avance_km]]<>"",Tabla1[[#This Row],[Avance_km]],Tabla1[[#This Row],[Avance_Med]])*_xlfn.XLOOKUP(Tabla1[[#This Row],[Codigo_actividad]],Catalogo!$B$6:$B$51,Catalogo!$F$6:$F$51,0) -> 14287.634
A106: 45994 | B106: A | C106: LIRA_GALERAS | D106: IACNA DE MEXICO | E106: Localización de Tubería con Equipo de RadioDetección. | F106: 0 | G106: 10 | H106: =IF(Tabla1[[#This Row],[Codigo_actividad]]<>2.5,IF(((Tabla1[[#This Row],[fin]]-Tabla1[[#This Row],[inicio]])/1000)=0,"",((Tabla1[[#This Row],[fin]]-Tabla1[[#This Row],[inicio]])/1000)),"") -> 0.01 | J106: 2.6 | K106: =IF(_xlfn.XLOOKUP($J106,Catalogo!$B$7:$B$210,Catalogo!$I$7:$I$210,"",0)=0,"",_xlfn.XLOOKUP($J106,Catalogo!$B$7:$B$210,Catalogo!$I$7:$I$210,"",0)) -> Localizacion | L106: 0.01 | M106: =IF(Tabla1[[#This Row],[Avance_km]]<>"",Tabla1[[#This Row],[Avance_km]],Tabla1[[#This Row],[Avance_Med]])*_xlfn.XLOOKUP(Tabla1[[#This Row],[Codigo_actividad]],Catalogo!$B$6:$B$51,Catalogo!$F$6:$F$51,0) -> 22.5742
A107: 45994 | B107: A | C107: LIRA_GALERAS | D107: IACNA DE MEXICO | E107: Direct Current Voltage Gradient DCVG | F107: 0 | G107: 10 | H107: =IF(Tabla1[[#This Row],[Codigo_actividad]]<>2.5,IF(((Tabla1[[#This Row],[fin]]-Tabla1[[#This Row],[inicio]])/1000)=0,"",((Tabla1[[#This Row],[fin]]-Tabla1[[#This Row],[inicio]])/1000)),"") -> 0.01 | J107: 2.3 | K107: =IF(_xlfn.XLOOKUP($J107,Catalogo!$B$7:$B$210,Catalogo!$I$7:$I$210,"",0)=0,"",_xlfn.XLOOKUP($J107,Catalogo!$B$7:$B$210,Catalogo!$I$7:$I$210,"",0)) -> DCVG | L107: 0.01 | M107: =IF(Tabla1[[#This Row],[Avance_km]]<>"",Tabla1[[#This Row],[Avance_km]],Tabla1[[#This Row],[Avance_Med]])*_xlfn.XLOOKUP(Tabla1[[#This Row],[Codigo_actividad]],Catalogo!$B$6:$B$51,Catalogo!$F$6:$F$51,0) -> 135.5563
A108: 45994 | B108: A | C108: LIRA_GALERAS | D108: KOPPERT | E108: Localización de Tubería con Equipo de RadioDetección. | F108: 0 | G108: 15 | H108: =IF(Tabla1[[#This Row],[Codigo_actividad]]<>2.5,IF(((Tabla1[[#This Row],[fin]]-Tabla1[[#This Row],[inicio]])/1000)=0,"",((Tabla1[[#This Row],[fin]]-Tabla1[[#This Row],[inicio]])/1000)),"") -> 0.015 | J108: 2.6 | K108: =IF(_xlfn.XLOOKUP($J108,Catalogo!$B$7:$B$210,Catalogo!$I$7:$I$210,"",0)=0,"",_xlfn.XLOOKUP($J108,Catalogo!$B$7:$B$210,Catalogo!$I$7:$I$210,"",0)) -> Localizacion | L108: 0.015 | M108: =IF(Tabla1[[#This Row],[Avance_km]]<>"",Tabla1[[#This Row],[Avance_km]],Tabla1[[#This Row],[Avance_Med]])*_xlfn.XLOOKUP(Tabla1[[#This Row],[Codigo_actividad]],Catalogo!$B$6:$B$51,Catalogo!$F$6:$F$51,0) -> 33.8613
A109: 45994 | B109: A | C109: LIRA_GALERAS | D109: KOPPERT | E109: Direct Current Voltage Gradient DCVG | F109: 0 | G109: 15 | H109: =IF(Tabla1[[#This Row],[Codigo_actividad]]<>2.5,IF(((Tabla1[[#This Row],[fin]]-Tabla1[[#This Row],[inicio]])/1000)=0,"",((Tabla1[[#This Row],[fin]]-Tabla1[[#This Row],[inicio]])/1000)),"") -> 0.015 | J109: 2.3 | K109: =IF(_xlfn.XLOOKUP($J109,Catalogo!$B$7:$B$210,Catalogo!$I$7:$I$210,"",0)=0,"",_xlfn.XLOOKUP($J109,Catalogo!$B$7:$B$210,Catalogo!$I$7:$I$210,"",0)) -> DCVG | L109: 0.015 | M109: =IF(Tabla1[[#This Row],[Avance_km]]<>"",Tabla1[[#This Row],[Avance_km]],Tabla1[[#This Row],[Avance_Med]])*_xlfn.XLOOKUP(Tabla1[[#This Row],[Codigo_actividad]],Catalogo!$B$6:$B$51,Catalogo!$F$6:$F$51,0) -> 203.33445
A110: 45994 | B110: A | C110: LIRA_GALERAS | D110: ED EL COLORADO | E110: Direct Current Voltage Gradient DCVG | F110: 0 | G110: 19 | H110: =IF(Tabla1[[#This Row],[Codigo_actividad]]<>2.5,IF(((Tabla1[[#This Row],[fin]]-Tabla1[[#This Row],[inicio]])/1000)=0,"",((Tabla1[[#This Row],[fin]]-Tabla1[[#This Row],[inicio]])/1000)),"") -> 0.019 | J110: 2.3 | K110: =IF(_xlfn.XLOOKUP($J110,Catalogo!$B$7:$B$210,Catalogo!$I$7:$I$210,"",0)=0,"",_xlfn.XLOOKUP($J110,Catalogo!$B$7:$B$210,Catalogo!$I$7:$I$210,"",0)) -> DCVG | L110: 0.019 | M110: =IF(Tabla1[[#This Row],[Avance_km]]<>"",Tabla1[[#This Row],[Avance_km]],Tabla1[[#This Row],[Avance_Med]])*_xlfn.XLOOKUP(Tabla1[[#This Row],[Codigo_actividad]],Catalogo!$B$6:$B$51,Catalogo!$F$6:$F$51,0) -> 257.55697
A111: 45994 | B111: B | C111: LIRA_GALERAS | D111: VIBORILLAS | E111: Direct Current Voltage Gradient DCVG | F111: 0 | G111: 1488 | H111: =IF(Tabla1[[#This Row],[Codigo_actividad]]<>2.5,IF(((Tabla1[[#This Row],[fin]]-Tabla1[[#This Row],[inicio]])/1000)=0,"",((Tabla1[[#This Row],[fin]]-Tabla1[[#This Row],[inicio]])/1000)),"") -> 1.488 | J111: 2.3 | K111: =IF(_xlfn.XLOOKUP($J111,Catalogo!$B$7:$B$210,Catalogo!$I$7:$I$210,"",0)=0,"",_xlfn.XLOOKUP($J111,Catalogo!$B$7:$B$210,Catalogo!$I$7:$I$210,"",0)) -> DCVG | L111: 1.488 | M111: =IF(Tabla1[[#This Row],[Avance_km]]<>"",Tabla1[[#This Row],[Avance_km]],Tabla1[[#This Row],[Avance_Med]])*_xlfn.XLOOKUP(Tabla1[[#This Row],[Codigo_actividad]],Catalogo!$B$6:$B$51,Catalogo!$F$6:$F$51,0) -> 20170.777
A112: 45994 | B112: B | C112: LIRA_GALERAS | D112: ERM VIBORILLAS | E112: Direct Current Voltage Gradient DCVG | F112: 0 | G112: 7 | H112: =IF(Tabla1[[#This Row],[Codigo_actividad]]<>2.5,IF(((Tabla1[[#This Row],[fin]]-Tabla1[[#This Row],[inicio]])/1000)=0,"",((Tabla1[[#This Row],[fin]]-Tabla1[[#This Row],[inicio]])/1000)),"") -> 0.007 | J112: 2.3 | K112: =IF(_xlfn.XLOOKUP($J112,Catalogo!$B$7:$B$210,Catalogo!$I$7:$I$210,"",0)=0,"",_xlfn.XLOOKUP($J112,Catalogo!$B$7:$B$210,Catalogo!$I$7:$I$210,"",0)) -> DCVG | L112: 0.007 | M112: =IF(Tabla1[[#This Row],[Avance_km]]<>"",Tabla1[[#This Row],[Avance_km]],Tabla1[[#This Row],[Avance_Med]])*_xlfn.XLOOKUP(Tabla1[[#This Row],[Codigo_actividad]],Catalogo!$B$6:$B$51,Catalogo!$F$6:$F$51,0) -> 94.88941
A113: 45994 | B113: B | C113: PECO_AGROS | D113: POLLOS QUERÉTARO | E113: Localización de Tubería con Equipo de RadioDetección. | F113: 0 | G113: 13 | H113: =IF(Tabla1[[#This Row],[Codigo_actividad]]<>2.5,IF(((Tabla1[[#This Row],[fin]]-Tabla1[[#This Row],[inicio]])/1000)=0,"",((Tabla1[[#This Row],[fin]]-Tabla1[[#This Row],[inicio]])/1000)),"") -> 0.013 | J113: 2.6 | K113: =IF(_xlfn.XLOOKUP($J113,Catalogo!$B$7:$B$210,Catalogo!$I$7:$I$210,"",0)=0,"",_xlfn.XLOOKUP($J113,Catalogo!$B$7:$B$210,Catalogo!$I$7:$I$210,"",0)) -> Localizacion | L113: 0.013 | M113: =IF(Tabla1[[#This Row],[Avance_km]]<>"",Tabla1[[#This Row],[Avance_km]],Tabla1[[#This Row],[Avance_Med]])*_xlfn.XLOOKUP(Tabla1[[#This Row],[Codigo_actividad]],Catalogo!$B$6:$B$51,Catalogo!$F$6:$F$51,0) -> 29.34646
A114: 45994 | B114: B | C114: PECO_AGROS | D114: POLLOS QUERÉTARO | E114: Direct Current Voltage Gradient DCVG | F114: 0 | G114: 13 | H114: =IF(Tabla1[[#This Row],[Codigo_actividad]]<>2.5,IF(((Tabla1[[#This Row],[fin]]-Tabla1[[#This Row],[inicio]])/1000)=0,"",((Tabla1[[#This Row],[fin]]-Tabla1[[#This Row],[inicio]])/1000)),"") -> 0.013 | J114: 2.3 | K114: =IF(_xlfn.XLOOKUP($J114,Catalogo!$B$7:$B$210,Catalogo!$I$7:$I$210,"",0)=0,"",_xlfn.XLOOKUP($J114,Catalogo!$B$7:$B$210,Catalogo!$I$7:$I$210,"",0)) -> DCVG | L114: 0.013 | M114: =IF(Tabla1[[#This Row],[Avance_km]]<>"",Tabla1[[#This Row],[Avance_km]],Tabla1[[#This Row],[Avance_Med]])*_xlfn.XLOOKUP(Tabla1[[#This Row],[Codigo_actividad]],Catalogo!$B$6:$B$51,Catalogo!$F$6:$F$51,0) -> 176.22319
A115: 45994 | B115: B | C115: PECO_AGROS | D115: NUTEC LOS OLIVOS | E115: Localización de Tubería con Equipo de RadioDetección. | F115: 0 | G115: 11 | H115: =IF(Tabla1[[#This Row],[Codigo_actividad]]<>2.5,IF(((Tabla1[[#This Row],[fin]]-Tabla1[[#This Row],[inicio]])/1000)=0,"",((Tabla1[[#This Row],[fin]]-Tabla1[[#This Row],[inicio]])/1000)),"") -> 0.011 | J115: 2.6 | K115: =IF(_xlfn.XLOOKUP($J115,Catalogo!$B$7:$B$210,Catalogo!$I$7:$I$210,"",0)=0,"",_xlfn.XLOOKUP($J115,Catalogo!$B$7:$B$210,Catalogo!$I$7:$I$210,"",0)) -> Localizacion | L115: 0.011 | M115: =IF(Tabla1[[#This Row],[Avance_km]]<>"",Tabla1[[#This Row],[Avance_km]],Tabla1[[#This Row],[Avance_Med]])*_xlfn.XLOOKUP(Tabla1[[#This Row],[Codigo_actividad]],Catalogo!$B$6:$B$51,Catalogo!$F$6:$F$51,0) -> 24.83162
... A118: 45994 | B118: B | C118: PECO_AGROS | D118: ERM LA PERLA | E118: Direct Current Voltage Gradient DCVG | F118: 0 | G118: 6 | H118: =IF(Tabla1[[#This Row],[Codigo_actividad]]<>2.5,IF(((Tabla1[[#This Row],[fin]]-Tabla1[[#This Row],[inicio]])/1000)=0,"",((Tabla1[[#This Row],[fin]]-Tabla1[[#This Row],[inicio]])/1000)),"") -> 0.006 | J118: 2.3 | K118: =IF(_xlfn.XLOOKUP($J118,Catalogo!$B$7:$B$210,Catalogo!$I$7:$I$210,"",0)=0,"",_xlfn.XLOOKUP($J118,Catalogo!$B$7:$B$210,Catalogo!$I$7:$I$210,"",0)) -> DCVG | L118: 0.006 | M118: =IF(Tabla1[[#This Row],[Avance_km]]<>"",Tabla1[[#This Row],[Avance_km]],Tabla1[[#This Row],[Avance_Med]])*_xlfn.XLOOKUP(Tabla1[[#This Row],[Codigo_actividad]],Catalogo!$B$6:$B$51,Catalogo!$F$6:$F$51,0) -> 81.33378
A119: 45994 | B119: C | C119: LIRA_GALERAS | D119: ATONGO | E119: Resistividades pH BRS BPA | F119: 6500 | G119: 11000 | H119: =IF(Tabla1[[#This Row],[Codigo_actividad]]<>2.5,IF(((Tabla1[[#This Row],[fin]]-Tabla1[[#This Row],[inicio]])/1000)=0,"",((Tabla1[[#This Row],[fin]]-Tabla1[[#This Row],[inicio]])/1000)),"") | I119: 10 | J119: 2.5 | K119: =IF(_xlfn.XLOOKUP($J119,Catalogo!$B$7:$B$210,Catalogo!$I$7:$I$210,"",0)=0,"",_xlfn.XLOOKUP($J119,Catalogo!$B$7:$B$210,Catalogo!$I$7:$I$210,"",0)) -> Resistividades pH BSR BPA | L119: 12.657 | M119: =IF(Tabla1[[#This Row],[Avance_km]]<>"",Tabla1[[#This Row],[Avance_km]],Tabla1[[#This Row],[Avance_Med]])*_xlfn.XLOOKUP(Tabla1[[#This Row],[Codigo_actividad]],Catalogo!$B$6:$B$51,Catalogo!$F$6:$F$51,0) -> 46580
H120: =IF(Tabla1[[#This Row],[Codigo_actividad]]<>2.5,IF(((Tabla1[[#This Row],[fin]]-Tabla1[[#This Row],[inicio]])/1000)=0,"",((Tabla1[[#This Row],[fin]]-Tabla1[[#This Row],[inicio]])/1000)),"") | K120: =IF(_xlfn.XLOOKUP($J120,Catalogo!$B$7:$B$210,Catalogo!$I$7:$I$210,"",0)=0,"",_xlfn.XLOOKUP($J120,Catalogo!$B$7:$B$210,Catalogo!$I$7:$I$210,"",0)) | M120: =IF(Tabla1[[#This Row],[Avance_km]]<>"",Tabla1[[#This Row],[Avance_km]],Tabla1[[#This Row],[Avance_Med]])*_xlfn.XLOOKUP(Tabla1[[#This Row],[Codigo_actividad]],Catalogo!$B$6:$B$51,Catalogo!$F$6:$F$51,0) -> 0
A121: 45995 | B121: A | C121: LIRA_GALERAS | D121: ED PARQUE INDUSTRIAL LA BOMBA | E121: Direct Current Voltage Gradient DCVG | F121: 0 | G121: 88 | H121: =IF(Tabla1[[#This Row],[Codigo_actividad]]<>2.5,IF(((Tabla1[[#This Row],[fin]]-Tabla1[[#This Row],[inicio]])/1000)=0,"",((Tabla1[[#This Row],[fin]]-Tabla1[[#This Row],[inicio]])/1000)),"") -> 0.088 | J121: 2.3 | K121: =IF(_xlfn.XLOOKUP($J121,Catalogo!$B$7:$B$210,Catalogo!$I$7:$I$210,"",0)=0,"",_xlfn.XLOOKUP($J121,Catalogo!$B$7:$B$210,Catalogo!$I$7:$I$210,"",0)) -> DCVG | L121: 0.088 | M121: =IF(Tabla1[[#This Row],[Avance_km]]<>"",Tabla1[[#This Row],[Avance_km]],Tabla1[[#This Row],[Avance_Med]])*_xlfn.XLOOKUP(Tabla1[[#This Row],[Codigo_actividad]],Catalogo!$B$6:$B$51,Catalogo!$F$6:$F$51,0) -> 1192.8954
A122: 45995 | B122: A | C122: LIRA_GALERAS | D122: STERLING BURDS | E122: Direct Current Voltage Gradient DCVG | F122: 0 | G122: 188 | H122: =IF(Tabla1[[#This Row],[Codigo_actividad]]<>2.5,IF(((Tabla1[[#This Row],[fin]]-Tabla1[[#This Row],[inicio]])/1000)=0,"",((Tabla1[[#This Row],[fin]]-Tabla1[[#This Row],[inicio]])/1000)),"") -> 0.188 | J122: 2.3 | K122: =IF(_xlfn.XLOOKUP($J122,Catalogo!$B$7:$B$210,Catalogo!$I$7:$I$210,"",0)=0,"",_xlfn.XLOOKUP($J122,Catalogo!$B$7:$B$210,Catalogo!$I$7:$I$210,"",0)) -> DCVG | L122: 0.188 | M122: =IF(Tabla1[[#This Row],[Avance_km]]<>"",Tabla1[[#This Row],[Avance_km]],Tabla1[[#This Row],[Avance_Med]])*_xlfn.XLOOKUP(Tabla1[[#This Row],[Codigo_actividad]],Catalogo!$B$6:$B$51,Catalogo!$F$6:$F$51,0) -> 2548.4584
A123: 45995 | B123: A | C123: LIRA_GALERAS | D123: FABRICA DE JABON LA CORONA | E123: Direct Current Voltage Gradient DCVG | F123: 0 | G123: 7 | H123: =IF(Tabla1[[#This Row],[Codigo_actividad]]<>2.5,IF(((Tabla1[[#This Row],[fin]]-Tabla1[[#This Row],[inicio]])/1000)=0,"",((Tabla1[[#This Row],[fin]]-Tabla1[[#This Row],[inicio]])/1000)),"") -> 0.007 | J123: 2.3 | K123: =IF(_xlfn.XLOOKUP($J123,Catalogo!$B$7:$B$210,Catalogo!$I$7:$I$210,"",0)=0,"",_xlfn.XLOOKUP($J123,Catalogo!$B$7:$B$210,Catalogo!$I$7:$I$210,"",0)) -> DCVG | L123: 0.007 | M123: =IF(Tabla1[[#This Row],[Avance_km]]<>"",Tabla1[[#This Row],[Avance_km]],Tabla1[[#This Row],[Avance_Med]])*_xlfn.XLOOKUP(Tabla1[[#This Row],[Codigo_actividad]],Catalogo!$B$6:$B$51,Catalogo!$F$6:$F$51,0) -> 94.88941
A124: 45995 | B124: A | C124: LIRA_GALERAS | D124: GRAMOSA ALIMENTOS | E124: Direct Current Voltage Gradient DCVG | F124: 0 | G124: 19 | H124: =IF(Tabla1[[#This Row],[Codigo_actividad]]<>2.5,IF(((Tabla1[[#This Row],[fin]]-Tabla1[[#This Row],[inicio]])/1000)=0,"",((Tabla1[[#This Row],[fin]]-Tabla1[[#This Row],[inicio]])/1000)),"") -> 0.019 | J124: 2.3 | K124: =IF(_xlfn.XLOOKUP($J124,Catalogo!$B$7:$B$210,Catalogo!$I$7:$I$210,"",0)=0,"",_xlfn.XLOOKUP($J124,Catalogo!$B$7:$B$210,Catalogo!$I$7:$I$210,"",0)) -> DCVG | L124: 0.019 | M124: =IF(Tabla1[[#This Row],[Avance_km]]<>"",Tabla1[[#This Row],[Avance_km]],Tabla1[[#This Row],[Avance_Med]])*_xlfn.XLOOKUP(Tabla1[[#This Row],[Codigo_actividad]],Catalogo!$B$6:$B$51,Catalogo!$F$6:$F$51,0) -> 257.55697
...

Sheet Resumen
A1: Sistema | B1: Nombre ducto | C1: Len | D1: Localizacion | E1: CIPS | F1: DCVG | G1: Resistividades pH BSR BPA | H1: ACVG | I1: PCM
A2: =+_xlfn.XLOOKUP(B2,Tabla1[Ducto],Tabla1[Sistema],"") -> LIRA_GALERAS | B2: {=_xlfn._xlws.FILTER(_xlfn.UNIQUE(Tabla1[Ducto]), _xlfn.UNIQUE(Tabla1[Ducto])<>0)} -> AC 8-6-4 in La Lira-Galeras | C2: =+_xlfn.XLOOKUP(B2,Tabla1[Ducto],Tabla1[Length]) -> 31.54 | D2: =IFERROR(SUMIFS(Tabla1[Avance_km],Tabla1[Ducto],Resumen!$B2,Tabla1[nombre_actividad],D$1)/$C2,0) -> 1 | E2: =IFERROR(SUMIFS(Tabla1[Avance_km],Tabla1[Ducto],Resumen!$B2,Tabla1[nombre_actividad],E$1)/$C2,0) -> 1 | F2: =IFERROR(SUMIFS(Tabla1[Avance_km],Tabla1[Ducto],Resumen!$B2,Tabla1[nombre_actividad],F$1)/$C2,0) -> 1 | G2: =IFERROR(SUMIFS(Tabla1[Avance_Med],Tabla1[Ducto],Resumen!$B2,Tabla1[nombre_actividad],G$1)/64,0) -> 1 | H2: =+SUMIFS(Tabla1[Avance_km],Tabla1[Ducto],Resumen!$B2,Tabla1[nombre_actividad],H$1)/$C2 -> 0 | I2: =+SUMIFS(Tabla1[Avance_km],Tabla1[Ducto],Resumen!$B2,Tabla1[nombre_actividad],I$1)/$C2 -> 0 | J2: =+_xlfn.XLOOKUP(B2,'R (s01)'!B:B,'R (s01)'!J:J) -> 0
A3: =+_xlfn.XLOOKUP(B3,Tabla1[Ducto],Tabla1[Sistema],"") -> LIRA_GALERAS | B3: ALESTRA | C3: =+_xlfn.XLOOKUP(B3,Tabla1[Ducto],Tabla1[Length]) -> 1.982 | D3: =IFERROR(SUMIFS(Tabla1[Avance_km],Tabla1[Ducto],Resumen!$B3,Tabla1[nombre_actividad],D$1)/$C3,0) -> 1 | E3: =IFERROR(SUMIFS(Tabla1[Avance_km],Tabla1[Ducto],Resumen!$B3,Tabla1[nombre_actividad],E$1)/$C3,0) -> 1 | F3: =IFERROR(SUMIFS(Tabla1[Avance_km],Tabla1[Ducto],Resumen!$B3,Tabla1[nombre_actividad],F$1)/$C3,0) -> 1 | G3: =IFERROR(SUMIFS(Tabla1[Avance_Med],Tabla1[Ducto],Resumen!$B3,Tabla1[nombre_actividad],G$1)/(ROUNDUP(C3,0)*2),0) -> 1 | H3: =+SUMIFS(Tabla1[Avance_km],Tabla1[Ducto],Resumen!$B3,Tabla1[nombre_actividad],H$1)/$C3 -> 0 | I3: =+SUMIFS(Tabla1[Avance_km],Tabla1[Ducto],Resumen!$B3,Tabla1[nombre_actividad],I$1)/$C3 -> 0 | J3: =+_xlfn.XLOOKUP(B3,'R (s01)'!B:B,'R (s01)'!J:J) -> 4
A4: =+_xlfn.XLOOKUP(B4,Tabla1[Ducto],Tabla1[Sistema],"") -> LIRA_GALERAS | B4: HUAWEI | C4: =+_xlfn.XLOOKUP(B4,Tabla1[Ducto],Tabla1[Length]) -> 0.175 | D4: =IFERROR(SUMIFS(Tabla1[Avance_km],Tabla1[Ducto],Resumen!$B4,Tabla1[nombre_actividad],D$1)/$C4,0) -> 1 | E4: =IFERROR(SUMIFS(Tabla1[Avance_km],Tabla1[Ducto],Resumen!$B4,Tabla1[nombre_actividad],E$1)/$C4,0) -> 1 | F4: =IFERROR(SUMIFS(Tabla1[Avance_km],Tabla1[Ducto],Resumen!$B4,Tabla1[nombre_actividad],F$1)/$C4,0) -> 1 | G4: =IFERROR(SUMIFS(Tabla1[Avance_Med],Tabla1[Ducto],Resumen!$B4,Tabla1[nombre_actividad],G$1)/(ROUNDUP(C4,0)*2),0) -> 1 | H4: =+SUMIFS(Tabla1[Avance_km],Tabla1[Ducto],Resumen!$B4,Tabla1[nombre_actividad],H$1)/$C4 -> 0 | I4: =+SUMIFS(Tabla1[Avance_km],Tabla1[Ducto],Resumen!$B4,Tabla1[nombre_actividad],I$1)/$C4 -> 0 | J4: =+_xlfn.XLOOKUP(B4,'R (s01)'!B:B,'R (s01)'!J:J) -> 2
A5: =+_xlfn.XLOOKUP(B5,Tabla1[Ducto],Tabla1[Sistema],"") -> LIRA_GALERAS | B5: ITASA | C5: =+_xlfn.XLOOKUP(B5,Tabla1[Ducto],Tabla1[Length]) -> 0.015 | D5: =IFERROR(SUMIFS(Tabla1[Avance_km],Tabla1[Ducto],Resumen!$B5,Tabla1[nombre_actividad],D$1)/$C5,0) -> 1 | E5: =IFERROR(SUMIFS(Tabla1[Avance_km],Tabla1[Ducto],Resumen!$B5,Tabla1[nombre_actividad],E$1)/$C5,0) -> 1 | F5: =IFERROR(SUMIFS(Tabla1[Avance_km],Tabla1[Ducto],Resumen!$B5,Tabla1[nombre_actividad],F$1)/$C5,0) -> 1 | H5: =+SUMIFS(Tabla1[Avance_km],Tabla1[Ducto],Resumen!$B5,Tabla1[nombre_actividad],H$1)/$C5 -> 0 | I5: =+SUMIFS(Tabla1[Avance_km],Tabla1[Ducto],Resumen!$B5,Tabla1[nombre_actividad],I$1)/$C5 -> 0 | J5: =+_xlfn.XLOOKUP(B5,'R (s01)'!B:B,'R (s01)'!J:J) -> 0
A6: =+_xlfn.XLOOKUP(B6,Tabla1[Ducto],Tabla1[Sistema],"") -> LIRA_GALERAS | B6: ED PARQUE INDUSTRIAL FINSA II | C6: =+_xlfn.XLOOKUP(B6,Tabla1[Ducto],Tabla1[Length]) -> 1.02 | D6: =IFERROR(SUMIFS(Tabla1[Avance_km],Tabla1[Ducto],Resumen!$B6,Tabla1[nombre_actividad],D$1)/$C6,0) -> 1 | E6: =IFERROR(SUMIFS(Tabla1[Avance_km],Tabla1[Ducto],Resumen!$B6,Tabla1[nombre_actividad],E$1)/$C6,0) -> 1 | F6: =IFERROR(SUMIFS(Tabla1[Avance_km],Tabla1[Ducto],Resumen!$B6,Tabla1[nombre_actividad],F$1)/$C6,0) -> 1 | G6: =IFERROR(SUMIFS(Tabla1[Avance_Med],Tabla1[Ducto],Resumen!$B6,Tabla1[nombre_actividad],G$1)/(3),0) -> 1 | H6: =+SUMIFS(Tabla1[Avance_km],Tabla1[Ducto],Resumen!$B6,Tabla1[nombre_actividad],H$1)/$C6 -> 0 | I6: =+SUMIFS(Tabla1[Avance_km],Tabla1[Ducto],Resumen!$B6,Tabla1[nombre_actividad],I$1)/$C6 -> 0 | J6: =+_xlfn.XLOOKUP(B6,'R (s01)'!B:B,'R (s01)'!J:J) -> 3
A7: =+_xlfn.XLOOKUP(B7,Tabla1[Ducto],Tabla1[Sistema],"") -> LIRA_GALERAS | B7: NUTRIBAQ | C7: =+_xlfn.XLOOKUP(B7,Tabla1[Ducto],Tabla1[Length]) -> 1.055 | D7: =IFERROR(SUMIFS(Tabla1[Avance_km],Tabla1[Ducto],Resumen!$B7,Tabla1[nombre_actividad],D$1)/$C7,0) -> 1 | E7: =IFERROR(SUMIFS(Tabla1[Avance_km],Tabla1[Ducto],Resumen!$B7,Tabla1[nombre_actividad],E$1)/$C7,0) -> 1 | F7: =IFERROR(SUMIFS(Tabla1[Avance_km],Tabla1[Ducto],Resumen!$B7,Tabla1[nombre_actividad],F$1)/$C7,0) -> 1 | G7: =IFERROR(SUMIFS(Tabla1[Avance_Med],Tabla1[Ducto],Resumen!$B7,Tabla1[nombre_actividad],G$1)/(3),0) -> 1 | H7: =+SUMIFS(Tabla1[Avance_km],Tabla1[Ducto],Resumen!$B7,Tabla1[nombre_actividad],H$1)/$C7 -> 0 | I7: =+SUMIFS(Tabla1[Avance_km],Tabla1[Ducto],Resumen!$B7,Tabla1[nombre_actividad],I$1)/$C7 -> 0 | J7: =+_xlfn.XLOOKUP(B7,'R (s01)'!B:B,'R (s01)'!J:J) -> 3
A8: =+_xlfn.XLOOKUP(B8,Tabla1[Ducto],Tabla1[Sistema],"") -> PECO_AGROS | B8: AGROS | C8: =+_xlfn.XLOOKUP(B8,Tabla1[Ducto],Tabla1[Length]) -> 2.2 | D8: =IFERROR(SUMIFS(Tabla1[Avance_km],Tabla1[Ducto],Resumen!$B8,Tabla1[nombre_actividad],D$1)/$C8,0) -> 1 | E8: =IFERROR(SUMIFS(Tabla1[Avance_km],Tabla1[Ducto],Resumen!$B8,Tabla1[nombre_actividad],E$1)/$C8,0) -> 1 | F8: =IFERROR(SUMIFS(Tabla1[Avance_km],Tabla1[Ducto],Resumen!$B8,Tabla1[nombre_actividad],F$1)/$C8,0) -> 1 | G8: =IFERROR(SUMIFS(Tabla1[Avance_Med],Tabla1[Ducto],Resumen!$B8,Tabla1[nombre_actividad],G$1)/(ROUNDUP(C8,0)*2),0) -> 1 | H8: =+SUMIFS(Tabla1[Avance_km],Tabla1[Ducto],Resumen!$B8,Tabla1[nombre_actividad],H$1)/$C8 -> 0 | I8: =+SUMIFS(Tabla1[Avance_km],Tabla1[Ducto],Resumen!$B8,Tabla1[nombre_actividad],I$1)/$C8 -> 0 | J8: =+_xlfn.XLOOKUP(B8,'R (s01)'!B:B,'R (s01)'!J:J) -> #N/A
A9: =+_xlfn.XLOOKUP(B9,Tabla1[Ducto],Tabla1[Sistema],"") -> PECO_AGROS | B9: SUNNY FIELDS | C9: =+_xlfn.XLOOKUP(B9,Tabla1[Ducto],Tabla1[Length]) -> 2.576 | D9: =IFERROR(SUMIFS(Tabla1[Avance_km],Tabla1[Ducto],Resumen!$B9,Tabla1[nombre_actividad],D$1)/$C9,0) -> 1 | E9: =IFERROR(SUMIFS(Tabla1[Avance_km],Tabla1[Ducto],Resumen!$B9,Tabla1[nombre_actividad],E$1)/$C9,0) -> 1 | F9: =IFERROR(SUMIFS(Tabla1[Avance_km],Tabla1[Ducto],Resumen!$B9,Tabla1[nombre_actividad],F$1)/$C9,0) -> 1 | G9: =IFERROR(SUMIFS(Tabla1[Avance_Med],Tabla1[Ducto],Resumen!$B9,Tabla1[nombre_actividad],G$1)/(ROUNDUP(C9,0)*2),0) -> 1 | H9: =+SUMIFS(Tabla1[Avance_km],Tabla1[Ducto],Resumen!$B9,Tabla1[nombre_actividad],H$1)/$C9 -> 0 | I9: =+SUMIFS(Tabla1[Avance_km],Tabla1[Ducto],Resumen!$B9,Tabla1[nombre_actividad],I$1)/$C9 -> 0 | J9: =+_xlfn.XLOOKUP(B9,'R (s01)'!B:B,'R (s01)'!J:J) -> #N/A
A10: =+_xlfn.XLOOKUP(B10,Tabla1[Ducto],Tabla1[Sistema],"") -> PECO_AGROS | B10: BEL GIARDINO | C10: =+_xlfn.XLOOKUP(B10,Tabla1[Ducto],Tabla1[Length]) -> 0.125 | D10: =IFERROR(SUMIFS(Tabla1[Avance_km],Tabla1[Ducto],Resumen!$B10,Tabla1[nombre_actividad],D$1)/$C10,0) -> 1 | E10: =IFERROR(SUMIFS(Tabla1[Avance_km],Tabla1[Ducto],Resumen!$B10,Tabla1[nombre_actividad],E$1)/$C10,0) -> 1 | F10: =IFERROR(SUMIFS(Tabla1[Avance_km],Tabla1[Ducto],Resumen!$B10,Tabla1[nombre_actividad],F$1)/$C10,0) -> 1 | H10: =+SUMIFS(Tabla1[Avance_km],Tabla1[Ducto],Resumen!$B10,Tabla1[nombre_actividad],H$1)/$C10 -> 0 | I10: =+SUMIFS(Tabla1[Avance_km],Tabla1[Ducto],Resumen!$B10,Tabla1[nombre_actividad],I$1)/$C10 -> 0 | J10: =+_xlfn.XLOOKUP(B10,'R (s01)'!B:B,'R (s01)'!J:J) -> #N/A
A11: =+_xlfn.XLOOKUP(B11,Tabla1[Ducto],Tabla1[Sistema],"") -> PECO_AGROS | B11: PRIME HASRVEST | C11: =+_xlfn.XLOOKUP(B11,Tabla1[Ducto],Tabla1[Length]) -> 0.741 | D11: =IFERROR(SUMIFS(Tabla1[Avance_km],Tabla1[Ducto],Resumen!$B11,Tabla1[nombre_actividad],D$1)/$C11,0) -> 1 | E11: =IFERROR(SUMIFS(Tabla1[Avance_km],Tabla1[Ducto],Resumen!$B11,Tabla1[nombre_actividad],E$1)/$C11,0) -> 1 | F11: =IFERROR(SUMIFS(Tabla1[Avance_km],Tabla1[Ducto],Resumen!$B11,Tabla1[nombre_actividad],F$1)/$C11,0) -> 1 | G11: =IFERROR(SUMIFS(Tabla1[Avance_Med],Tabla1[Ducto],Resumen!$B11,Tabla1[nombre_actividad],G$1)/(ROUNDUP(C11,0)*2),0) -> 1 | H11: =+SUMIFS(Tabla1[Avance_km],Tabla1[Ducto],Resumen!$B11,Tabla1[nombre_actividad],H$1)/$C11 -> 0 | I11: =+SUMIFS(Tabla1[Avance_km],Tabla1[Ducto],Resumen!$B11,Tabla1[nombre_actividad],I$1)/$C11 -> 0 | J11: =+_xlfn.XLOOKUP(B11,'R (s01)'!B:B,'R (s01)'!J:J) -> #N/A
A12: =+_xlfn.XLOOKUP(B12,Tabla1[Ducto],Tabla1[Sistema],"") -> PECO_AGROS | B12: PECO II - GALERAS 10 | C12: =+_xlfn.XLOOKUP(B12,Tabla1[Ducto],Tabla1[Length]) -> 25.4 | D12: =IFERROR(SUMIFS(Tabla1[Avance_km],Tabla1[Ducto],Resumen!$B12,Tabla1[nombre_actividad],D$1)/$C12,0) -> 1 | E12: =IFERROR(SUMIFS(Tabla1[Avance_km],Tabla1[Ducto],Resumen!$B12,Tabla1[nombre_actividad],E$1)/$C12,0) -> 1 | F12: =IFERROR(SUMIFS(Tabla1[Avance_km],Tabla1[Ducto],Resumen!$B12,Tabla1[nombre_actividad],F$1)/$C12,0) -> 1 | G12: =IFERROR(SUMIFS(Tabla1[Avance_Med],Tabla1[Ducto],Resumen!$B12,Tabla1[nombre_actividad],G$1)/52,0) -> 1 | H12: =+SUMIFS(Tabla1[Avance_km],Tabla1[Ducto],Resumen!$B12,Tabla1[nombre_actividad],H$1)/$C12 -> 0 | I12: =+SUMIFS(Tabla1[Avance_km],Tabla1[Ducto],Resumen!$B12,Tabla1[nombre_actividad],I$1)/$C12 -> 0 | J12: =+_xlfn.XLOOKUP(B12,'R (s01)'!B:B,'R (s01)'!J:J) -> #N/A
A13: =+_xlfn.XLOOKUP(B13,Tabla1[Ducto],Tabla1[Sistema],"") -> PECO_AGROS | B13: ED AGROPARK II (GAS PRIMO) | C13: =+_xlfn.XLOOKUP(B13,Tabla1[Ducto],Tabla1[Length]) -> 0.009 | D13: =IFERROR(SUMIFS(Tabla1[Avance_km],Tabla1[Ducto],Resumen!$B13,Tabla1[nombre_actividad],D$1)/$C13,0) -> 1 | E13: =IFERROR(SUMIFS(Tabla1[Avance_km],Tabla1[Ducto],Resumen!$B13,Tabla1[nombre_actividad],E$1)/$C13,0) -> 1 | F13: =IFERROR(SUMIFS(Tabla1[Avance_km],Tabla1[Ducto],Resumen!$B13,Tabla1[nombre_actividad],F$1)/$C13,0) -> 1 | G13: =IFERROR(SUMIFS(Tabla1[Avance_Med],Tabla1[Ducto],Resumen!$B13,Tabla1[nombre_actividad],G$1)/(1),0) -> 0 | H13: =+SUMIFS(Tabla1[Avance_km],Tabla1[Ducto],Resumen!$B13,Tabla1[nombre_actividad],H$1)/$C13 -> 0 | I13: =+SUMIFS(Tabla1[Avance_km],Tabla1[Ducto],Resumen!$B13,Tabla1[nombre_actividad],I$1)/$C13 -> 0 | J13: =+_xlfn.XLOOKUP(B13,'R (s01)'!B:B,'R (s01)'!J:J) -> #N/A
A14: =+_xlfn.XLOOKUP(B14,Tabla1[Ducto],Tabla1[Sistema],"") -> PECO_AGROS | B14: LA BONITA | C14: =+_xlfn.XLOOKUP(B14,Tabla1[Ducto],Tabla1[Length]) -> 0.479 | D14: =IFERROR(SUMIFS(Tabla1[Avance_km],Tabla1[Ducto],Resumen!$B14,Tabla1[nombre_actividad],D$1)/$C14,0) -> 1 | E14: =IFERROR(SUMIFS(Tabla1[Avance_km],Tabla1[Ducto],Resumen!$B14,Tabla1[nombre_actividad],E$1)/$C14,0) -> 1 | F14: =IFERROR(SUMIFS(Tabla1[Avance_km],Tabla1[Ducto],Resumen!$B14,Tabla1[nombre_actividad],F$1)/$C14,0) -> 1 | H14: =+SUMIFS(Tabla1[Avance_km],Tabla1[Ducto],Resumen!$B14,Tabla1[nombre_actividad],H$1)/$C14 -> 0 | I14: =+SUMIFS(Tabla1[Avance_km],Tabla1[Ducto],Resumen!$B14,Tabla1[nombre_actividad],I$1)/$C14 -> 0 | J14: =+_xlfn.XLOOKUP(B14,'R (s01)'!B:B,'R (s01)'!J:J) -> #N/A
A15: =+_xlfn.XLOOKUP(B15,Tabla1[Ducto],Tabla1[Sistema],"") -> PECO_AGROS | B15: ERM FH FIBRAS | C15: =+_xlfn.XLOOKUP(B15,Tabla1[Ducto],Tabla1[Length]) -> 0.04 | D15: =IFERROR(SUMIFS(Tabla1[Avance_km],Tabla1[Ducto],Resumen!$B15,Tabla1[nombre_actividad],D$1)/$C15,0) -> 1 | E15: =IFERROR(SUMIFS(Tabla1[Avance_km],Tabla1[Ducto],Resumen!$B15,Tabla1[nombre_actividad],E$1)/$C15,0) -> 1 | F15: =IFERROR(SUMIFS(Tabla1[Avance_km],Tabla1[Ducto],Resumen!$B15,Tabla1[nombre_actividad],F$1)/$C15,0) -> 1 | G15: =IFERROR(SUMIFS(Tabla1[Avance_Med],Tabla1[Ducto],Resumen!$B15,Tabla1[nombre_actividad],G$1)/(1),0) -> 0 | H15: =+SUMIFS(Tabla1[Avance_km],Tabla1[Ducto],Resumen!$B15,Tabla1[nombre_actividad],H$1)/$C15 -> 0 | I15: =+SUMIFS(Tabla1[Avance_km],Tabla1[Ducto],Resumen!$B15,Tabla1[nombre_actividad],I$1)/$C15 -> 0 | J15: =+_xlfn.XLOOKUP(B15,'R (s01)'!B:B,'R (s01)'!J:J) -> #N/A
A16: =+_xlfn.XLOOKUP(B16,Tabla1[Ducto],Tabla1[Sistema],"") -> PECO_AGROS | B16: ERM DESHITEC | C16: =+_xlfn.XLOOKUP(B16,Tabla1[Ducto],Tabla1[Length]) -> 0.12 | D16: =IFERROR(SUMIFS(Tabla1[Avance_km],Tabla1[Ducto],Resumen!$B16,Tabla1[nombre_actividad],D$1)/$C16,0) -> 1 | E16: =IFERROR(SUMIFS(Tabla1[Avance_km],Tabla1[Ducto],Resumen!$B16,Tabla1[nombre_actividad],E$1)/$C16,0) -> 1 | F16: =IFERROR(SUMIFS(Tabla1[Avance_km],Tabla1[Ducto],Resumen!$B16,Tabla1[nombre_actividad],F$1)/$C16,0) -> 1 | G16: =IFERROR(SUMIFS(Tabla1[Avance_Med],Tabla1[Ducto],Resumen!$B16,Tabla1[nombre_actividad],G$1)/(3),0) -> 0.33333333 | J16: =+_xlfn.XLOOKUP(B16,'R (s01)'!B:B,'R (s01)'!J:J) -> #N/A
A17: =+_xlfn.XLOOKUP(B17,Tabla1[Ducto],Tabla1[Sistema],"") -> PECO_AGROS | B17: ED ARKANSAS | C17: =+_xlfn.XLOOKUP(B17,Tabla1[Ducto],Tabla1[Length]) -> 1.195 | D17: =IFERROR(SUMIFS(Tabla1[Avance_km],Tabla1[Ducto],Resumen!$B17,Tabla1[nombre_actividad],D$1)/$C17,0) -> 1 | E17: =IFERROR(SUMIFS(Tabla1[Avance_km],Tabla1[Ducto],Resumen!$B17,Tabla1[nombre_actividad],E$1)/$C17,0) -> 1 | F17: =IFERROR(SUMIFS(Tabla1[Avance_km],Tabla1[Ducto],Resumen!$B17,Tabla1[nombre_actividad],F$1)/$C17,0) -> 1 | G17: =IFERROR(SUMIFS(Tabla1[Avance_Med],Tabla1[Ducto],Resumen!$B17,Tabla1[nombre_actividad],G$1)/(ROUNDUP(C17,0)*2),0) -> 0.75 | J17: =+_xlfn.XLOOKUP(B17,'R (s01)'!B:B,'R (s01)'!J:J) -> #N/A
A18: =+_xlfn.XLOOKUP(B18,Tabla1[Ducto],Tabla1[Sistema],"") -> LIRA_GALERAS | B18: VIBORILLAS | C18: =+_xlfn.XLOOKUP(B18,Tabla1[Ducto],Tabla1[Length]) -> 1.488 | D18: =IFERROR(SUMIFS(Tabla1[Avance_km],Tabla1[Ducto],Resumen!$B18,Tabla1[nombre_actividad],D$1)/$C18,0) -> 1 | E18: =IFERROR(SUMIFS(Tabla1[Avance_km],Tabla1[Ducto],Resumen!$B18,Tabla1[nombre_actividad],E$1)/$C18,0) -> 1 | F18: =IFERROR(SUMIFS(Tabla1[Avance_km],Tabla1[Ducto],Resumen!$B18,Tabla1[nombre_actividad],F$1)/$C18,0) -> 1 | G18: =IFERROR(SUMIFS(Tabla1[Avance_Med],Tabla1[Ducto],Resumen!$B18,Tabla1[nombre_actividad],G$1)/(ROUNDUP(C18,0)*2),0) -> 1 | J18: =+_xlfn.XLOOKUP(B18,'R (s01)'!B:B,'R (s01)'!J:J) -> 4
A19: =+_xlfn.XLOOKUP(B19,Tabla1[Ducto],Tabla1[Sistema],"") -> LIRA_GALERAS | B19: ERM VIBORILLAS | C19: =+_xlfn.XLOOKUP(B19,Tabla1[Ducto],Tabla1[Length]) -> 0.007 | D19: =IFERROR(SUMIFS(Tabla1[Avance_km],Tabla1[Ducto],Resumen!$B19,Tabla1[nombre_actividad],D$1)/$C19,0) -> 1 | E19: =IFERROR(SUMIFS(Tabla1[Avance_km],Tabla1[Ducto],Resumen!$B19,Tabla1[nombre_actividad],E$1)/$C19,0) -> 1 | F19: =IFERROR(SUMIFS(Tabla1[Avance_km],Tabla1[Ducto],Resumen!$B19,Tabla1[nombre_actividad],F$1)/$C19,0) -> 1 | G19: =IFERROR(SUMIFS(Tabla1[Avance_Med],Tabla1[Ducto],Resumen!$B19,Tabla1[nombre_actividad],G$1)/1,0) -> 0 | J19: =+_xlfn.XLOOKUP(B19,'R (s01)'!B:B,'R (s01)'!J:J) -> 0
A20: =+_xlfn.XLOOKUP(B20,Tabla1[Ducto],Tabla1[Sistema],"") -> LIRA_GALERAS | B20: ED BOMBARDIER | C20: =+_xlfn.XLOOKUP(B20,Tabla1[Ducto],Tabla1[Length]) -> 1.855 | D20: =IFERROR(SUMIFS(Tabla1[Avance_km],Tabla1[Ducto],Resumen!$B20,Tabla1[nombre_actividad],D$1)/$C20,0) -> 1 | E20: =IFERROR(SUMIFS(Tabla1[Avance_km],Tabla1[Ducto],Resumen!$B20,Tabla1[nombre_actividad],E$1)/$C20,0) -> 1 | F20: =IFERROR(SUMIFS(Tabla1[Avance_km],Tabla1[Ducto],Resumen!$B20,Tabla1[nombre_actividad],F$1)/$C20,0) -> 1 | G20: =IFERROR(SUMIFS(Tabla1[Avance_Med],Tabla1[Ducto],Resumen!$B20,Tabla1[nombre_actividad],G$1)/(1),0) -> 4 | J20: =+_xlfn.XLOOKUP(B20,'R (s01)'!B:B,'R (s01)'!J:J) -> 4
A21: =+_xlfn.XLOOKUP(B21,Tabla1[Ducto],Tabla1[Sistema],"") -> PECO_AGROS | B21: MOLINOS ANAHUAC | C21: =+_xlfn.XLOOKUP(B21,Tabla1[Ducto],Tabla1[Length]) -> 0.02 | D21: =IFERROR(SUMIFS(Tabla1[Avance_km],Tabla1[Ducto],Resumen!$B21,Tabla1[nombre_actividad],D$1)/$C21,0) -> 1 | E21: =IFERROR(SUMIFS(Tabla1[Avance_km],Tabla1[Ducto],Resumen!$B21,Tabla1[nombre_actividad],E$1)/$C21,0) -> 1 | F21: =IFERROR(SUMIFS(Tabla1[Avance_km],Tabla1[Ducto],Resumen!$B21,Tabla1[nombre_actividad],F$1)/$C21,0) -> 1 | J21: =+_xlfn.XLOOKUP(B21,'R (s01)'!B:B,'R (s01)'!J:J) -> #N/A
A22: =+_xlfn.XLOOKUP(B22,Tabla1[Ducto],Tabla1[Sistema],"") -> LIRA_GALERAS | B22: FRESHLLACA | C22: =+_xlfn.XLOOKUP(B22,Tabla1[Ducto],Tabla1[Length]) -> 0.02 | D22: =IFERROR(SUMIFS(Tabla1[Avance_km],Tabla1[Ducto],Resumen!$B22,Tabla1[nombre_actividad],D$1)/$C22,0) -> 1 | E22: =IFERROR(SUMIFS(Tabla1[Avance_km],Tabla1[Ducto],Resumen!$B22,Tabla1[nombre_actividad],E$1)/$C22,0) -> 1 | F22: =IFERROR(SUMIFS(Tabla1[Avance_km],Tabla1[Ducto],Resumen!$B22,Tabla1[nombre_actividad],F$1)/$C22,0) -> 1 | G22: =IFERROR(SUMIFS(Tabla1[Avance_Med],Tabla1[Ducto],Resumen!$B22,Tabla1[nombre_actividad],G$1)/(1),0) -> 1 | J22: =+_xlfn.XLOOKUP(B22,'R (s01)'!B:B,'R (s01)'!J:J) -> 1
A23: =+_xlfn.XLOOKUP(B23,Tabla1[Ducto],Tabla1[Sistema],"") -> LIRA_GALERAS | B23: RANCHO HUMUS | C23: =+_xlfn.XLOOKUP(B23,Tabla1[Ducto],Tabla1[Length]) -> 0.07 | D23: =IFERROR(SUMIFS(Tabla1[Avance_km],Tabla1[Ducto],Resumen!$B23,Tabla1[nombre_actividad],D$1)/$C23,0) -> 1 | E23: =IFERROR(SUMIFS(Tabla1[Avance_km],Tabla1[Ducto],Resumen!$B23,Tabla1[nombre_actividad],E$1)/$C23,0) -> 1 | F23: =IFERROR(SUMIFS(Tabla1[Avance_km],Tabla1[Ducto],Resumen!$B23,Tabla1[nombre_actividad],F$1)/$C23,0) -> 1 | G23: =IFERROR(SUMIFS(Tabla1[Avance_Med],Tabla1[Ducto],Resumen!$B23,Tabla1[nombre_actividad],G$1)/(1),0) -> 0 | J23: =+_xlfn.XLOOKUP(B23,'R (s01)'!B:B,'R (s01)'!J:J) -> 0
A24: =+_xlfn.XLOOKUP(B24,Tabla1[Ducto],Tabla1[Sistema],"") -> LIRA_GALERAS | B24: GPO. PRODUCTIVO LA LIRA | C24: =+_xlfn.XLOOKUP(B24,Tabla1[Ducto],Tabla1[Length]) -> 0.07 | D24: =IFERROR(SUMIFS(Tabla1[Avance_km],Tabla1[Ducto],Resumen!$B24,Tabla1[nombre_actividad],D$1)/$C24,0) -> 1 | E24: =IFERROR(SUMIFS(Tabla1[Avance_km],Tabla1[Ducto],Resumen!$B24,Tabla1[nombre_actividad],E$1)/$C24,0) -> 1 | F24: =IFERROR(SUMIFS(Tabla1[Avance_km],Tabla1[Ducto],Resumen!$B24,Tabla1[nombre_actividad],F$1)/$C24,0) -> 1 | G24: =IFERROR(SUMIFS(Tabla1[Avance_Med],Tabla1[Ducto],Resumen!$B24,Tabla1[nombre_actividad],G$1)/(1),0) -> 1 | J24: =+_xlfn.XLOOKUP(B24,'R (s01)'!B:B,'R (s01)'!J:J) -> 1
A25: =+_xlfn.XLOOKUP(B25,Tabla1[Ducto],Tabla1[Sistema],"") -> LIRA_GALERAS | B25: ED PARQUE INDUSTRIAL PYME | C25: =+_xlfn.XLOOKUP(B25,Tabla1[Ducto],Tabla1[Length]) -> 0.015 | D25: =IFERROR(SUMIFS(Tabla1[Avance_km],Tabla1[Ducto],Resumen!$B25,Tabla1[nombre_actividad],D$1)/$C25,0) -> 1 | E25: =IFERROR(SUMIFS(Tabla1[Avance_km],Tabla1[Ducto],Resumen!$B25,Tabla1[nombre_actividad],E$1)/$C25,0) -> 1 | F25: =IFERROR(SUMIFS(Tabla1[Avance_km],Tabla1[Ducto],Resumen!$B25,Tabla1[nombre_actividad],F$1)/$C25,0) -> 1 | G25: =IFERROR(SUMIFS(Tabla1[Avance_Med],Tabla1[Ducto],Resumen!$B25,Tabla1[nombre_actividad],G$1)/(1),0) -> 1 | J25: =+_xlfn.XLOOKUP(B25,'R (s01)'!B:B,'R (s01)'!J:J) -> 1
A26: =+_xlfn.XLOOKUP(B26,Tabla1[Ducto],Tabla1[Sistema],"") -> LIRA_GALERAS | B26: ED EL COLORADO | C26: =+_xlfn.XLOOKUP(B26,Tabla1[Ducto],Tabla1[Length]) -> 0.019 | D26: =IFERROR(SUMIFS(Tabla1[Avance_km],Tabla1[Ducto],Resumen!$B26,Tabla1[nombre_actividad],D$1)/$C26,0) -> 1 | E26: =IFERROR(SUMIFS(Tabla1[Avance_km],Tabla1[Ducto],Resumen!$B26,Tabla1[nombre_actividad],E$1)/$C26,0) -> 1 | F26: =IFERROR(SUMIFS(Tabla1[Avance_km],Tabla1[Ducto],Resumen!$B26,Tabla1[nombre_actividad],F$1)/$C26,0) -> 1 | G26: =IFERROR(SUMIFS(Tabla1[Avance_Med],Tabla1[Ducto],Resumen!$B26,Tabla1[nombre_actividad],G$1)/(ROUNDUP(C26,0)*2),0) -> 0.5 | J26: =+_xlfn.XLOOKUP(B26,'R (s01)'!B:B,'R (s01)'!J:J) -> 1
A27: =+_xlfn.XLOOKUP(B27,Tabla1[Ducto],Tabla1[Sistema],"") -> LIRA_GALERAS | B27: PILGRIMS LOS CUES | C27: =+_xlfn.XLOOKUP(B27,Tabla1[Ducto],Tabla1[Length]) -> 0.01 | D27: =IFERROR(SUMIFS(Tabla1[Avance_km],Tabla1[Ducto],Resumen!$B27,Tabla1[nombre_actividad],D$1)/$C27,0) -> 1 | E27: =IFERROR(SUMIFS(Tabla1[Avance_km],Tabla1[Ducto],Resumen!$B27,Tabla1[nombre_actividad],E$1)/$C27,0) -> 1 | F27: =IFERROR(SUMIFS(Tabla1[Avance_km],Tabla1[Ducto],Resumen!$B27,Tabla1[nombre_actividad],F$1)/$C27,0) -> 1 | G27: =IFERROR(SUMIFS(Tabla1[Avance_Med],Tabla1[Ducto],Resumen!$B27,Tabla1[nombre_actividad],G$1)/(1),0) -> 1 | J27: =+_xlfn.XLOOKUP(B27,'R (s01)'!B:B,'R (s01)'!J:J) -> 1
A28: =+_xlfn.XLOOKUP(B28,Tabla1[Ducto],Tabla1[Sistema],"") -> LIRA_GALERAS | B28: ED AEROTECH | C28: =+_xlfn.XLOOKUP(B28,Tabla1[Ducto],Tabla1[Length]) -> 0.267 | D28: =IFERROR(SUMIFS(Tabla1[Avance_km],Tabla1[Ducto],Resumen!$B28,Tabla1[nombre_actividad],D$1)/$C28,0) -> 1 | E28: =IFERROR(SUMIFS(Tabla1[Avance_km],Tabla1[Ducto],Resumen!$B28,Tabla1[nombre_actividad],E$1)/$C28,0) -> 1 | F28: =IFERROR(SUMIFS(Tabla1[Avance_km],Tabla1[Ducto],Resumen!$B28,Tabla1[nombre_actividad],F$1)/$C28,0) -> 1 | J28: =+_xlfn.XLOOKUP(B28,'R (s01)'!B:B,'R (s01)'!J:J) -> 2
A29: =+_xlfn.XLOOKUP(B29,Tabla1[Ducto],Tabla1[Sistema],"") -> LIRA_GALERAS | B29: FINSA II | C29: =+_xlfn.XLOOKUP(B29,Tabla1[Ducto],Tabla1[Length]) -> 0.01 | D29: =IFERROR(SUMIFS(Tabla1[Avance_km],Tabla1[Ducto],Resumen!$B29,Tabla1[nombre_actividad],D$1)/$C29,0) -> 1 | E29: =IFERROR(SUMIFS(Tabla1[Avance_km],Tabla1[Ducto],Resumen!$B29,Tabla1[nombre_actividad],E$1)/$C29,0) -> 1 | F29: =IFERROR(SUMIFS(Tabla1[Avance_km],Tabla1[Ducto],Resumen!$B29,Tabla1[nombre_actividad],F$1)/$C29,0) -> 1 | G29: =IFERROR(SUMIFS(Tabla1[Avance_Med],Tabla1[Ducto],Resumen!$B29,Tabla1[nombre_actividad],G$1)/(27),0) -> 0.037037037 | J29: =+_xlfn.XLOOKUP(B29,'R (s01)'!B:B,'R (s01)'!J:J) -> 1
A30: =+_xlfn.XLOOKUP(B30,Tabla1[Ducto],Tabla1[Sistema],"") -> LIRA_GALERAS | B30: STEERINGMEX | C30: =+_xlfn.XLOOKUP(B30,Tabla1[Ducto],Tabla1[Length]) -> 0.012 | D30: =IFERROR(SUMIFS(Tabla1[Avance_km],Tabla1[Ducto],Resumen!$B30,Tabla1[nombre_actividad],D$1)/$C30,0) -> 1 | E30: =IFERROR(SUMIFS(Tabla1[Avance_km],Tabla1[Ducto],Resumen!$B30,Tabla1[nombre_actividad],E$1)/$C30,0) -> 1 | F30: =IFERROR(SUMIFS(Tabla1[Avance_km],Tabla1[Ducto],Resumen!$B30,Tabla1[nombre_actividad],F$1)/$C30,0) -> 1 | G30: =IFERROR(SUMIFS(Tabla1[Avance_Med],Tabla1[Ducto],Resumen!$B30,Tabla1[nombre_actividad],G$1)/(2),0) -> 0 | J30: =+_xlfn.XLOOKUP(B30,'R (s01)'!B:B,'R (s01)'!J:J) -> 0
A31: =+_xlfn.XLOOKUP(B31,Tabla1[Ducto],Tabla1[Sistema],"") -> LIRA_GALERAS | B31: ATONGO | C31: =+_xlfn.XLOOKUP(B31,Tabla1[Ducto],Tabla1[Length]) -> 12.657 | D31: =IFERROR(SUMIFS(Tabla1[Avance_km],Tabla1[Ducto],Resumen!$B31,Tabla1[nombre_actividad],D$1)/$C31,0) -> 1 | E31: =IFERROR(SUMIFS(Tabla1[Avance_km],Tabla1[Ducto],Resumen!$B31,Tabla1[nombre_actividad],E$1)/$C31,0) -> 1 | F31: =IFERROR(SUMIFS(Tabla1[Avance_km],Tabla1[Ducto],Resumen!$B31,Tabla1[nombre_actividad],F$1)/$C31,0) -> 1 | G31: =IFERROR(SUMIFS(Tabla1[Avance_Med],Tabla1[Ducto],Resumen!$B31,Tabla1[nombre_actividad],G$1)/(1),0) -> 27 | J31: =+_xlfn.XLOOKUP(B31,'R (s01)'!B:B,'R (s01)'!J:J) -> 27
A32: =+_xlfn.XLOOKUP(B32,Tabla1[Ducto],Tabla1[Sistema],"") -> LIRA_GALERAS | B32: NATGAS EL MARQUES | C32: =+_xlfn.XLOOKUP(B32,Tabla1[Ducto],Tabla1[Length]) -> 1.054 | D32: =IFERROR(SUMIFS(Tabla1[Avance_km],Tabla1[Ducto],Resumen!$B32,Tabla1[nombre_actividad],D$1)/$C32,0) -> 1 | E32: =IFERROR(SUMIFS(Tabla1[Avance_km],Tabla1[Ducto],Resumen!$B32,Tabla1[nombre_actividad],E$1)/$C32,0) -> 1 | F32: =IFERROR(SUMIFS(Tabla1[Avance_km],Tabla1[Ducto],Resumen!$B32,Tabla1[nombre_actividad],F$1)/$C32,0) -> 1 | J32: =+_xlfn.XLOOKUP(B32,'R (s01)'!B:B,'R (s01)'!J:J) -> 2
A33: =+_xlfn.XLOOKUP(B33,Tabla1[Ducto],Tabla1[Sistema],"") -> LIRA_GALERAS | B33: IACNA DE MEXICO | C33: =+_xlfn.XLOOKUP(B33,Tabla1[Ducto],Tabla1[Length]) -> 0.01 | D33: =IFERROR(SUMIFS(Tabla1[Avance_km],Tabla1[Ducto],Resumen!$B33,Tabla1[nombre_actividad],D$1)/$C33,0) -> 1 | E33: =IFERROR(SUMIFS(Tabla1[Avance_km],Tabla1[Ducto],Resumen!$B33,Tabla1[nombre_actividad],E$1)/$C33,0) -> 1 | F33: =IFERROR(SUMIFS(Tabla1[Avance_km],Tabla1[Ducto],Resumen!$B33,Tabla1[nombre_actividad],F$1)/$C33,0) -> 1 | J33: =+_xlfn.XLOOKUP(B33,'R (s01)'!B:B,'R (s01)'!J:J) -> 1
A34: =+_xlfn.XLOOKUP(B34,Tabla1[Ducto],Tabla1[Sistema],"") -> LIRA_GALERAS | B34: KOPPERT | C34: =+_xlfn.XLOOKUP(B34,Tabla1[Ducto],Tabla1[Length]) -> 0.015 | D34: =IFERROR(SUMIFS(Tabla1[Avance_km],Tabla1[Ducto],Resumen!$B34,Tabla1[nombre_actividad],D$1)/$C34,0) -> 1 | E34: =IFERROR(SUMIFS(Tabla1[Avance_km],Tabla1[Ducto],Resumen!$B34,Tabla1[nombre_actividad],E$1)/$C34,0) -> 1 | F34: =IFERROR(SUMIFS(Tabla1[Avance_km],Tabla1[Ducto],Resumen!$B34,Tabla1[nombre_actividad],F$1)/$C34,0) -> 1 | J34: =+_xlfn.XLOOKUP(B34,'R (s01)'!B:B,'R (s01)'!J:J) -> 0
A35: =+_xlfn.XLOOKUP(B35,Tabla1[Ducto],Tabla1[Sistema],"") -> PECO_AGROS | B35: POLLOS QUERÉTARO | C35: =+_xlfn.XLOOKUP(B35,Tabla1[Ducto],Tabla1[Length]) -> 0.013 | D35: =IFERROR(SUMIFS(Tabla1[Avance_km],Tabla1[Ducto],Resumen!$B35,Tabla1[nombre_actividad],D$1)/$C35,0) -> 1 | E35: =IFERROR(SUMIFS(Tabla1[Avance_km],Tabla1[Ducto],Resumen!$B35,Tabla1[nombre_actividad],E$1)/$C35,0) -> 1 | F35: =IFERROR(SUMIFS(Tabla1[Avance_km],Tabla1[Ducto],Resumen!$B35,Tabla1[nombre_actividad],F$1)/$C35,0) -> 1 | J35: =+_xlfn.XLOOKUP(B35,'R (s01)'!B:B,'R (s01)'!J:J) -> #N/A
A36: =+_xlfn.XLOOKUP(B36,Tabla1[Ducto],Tabla1[Sistema],"") -> PECO_AGROS | B36: NUTEC LOS OLIVOS | C36: =+_xlfn.XLOOKUP(B36,Tabla1[Ducto],Tabla1[Length]) -> 0.011 | D36: =IFERROR(SUMIFS(Tabla1[Avance_km],Tabla1[Ducto],Resumen!$B36,Tabla1[nombre_actividad],D$1)/$C36,0) -> 1 | E36: =IFERROR(SUMIFS(Tabla1[Avance_km],Tabla1[Ducto],Resumen!$B36,Tabla1[nombre_actividad],E$1)/$C36,0) -> 1 | F36: =IFERROR(SUMIFS(Tabla1[Avance_km],Tabla1[Ducto],Resumen!$B36,Tabla1[nombre_actividad],F$1)/$C36,0) -> 1 | G36: =IFERROR(SUMIFS(Tabla1[Avance_Med],Tabla1[Ducto],Resumen!$B36,Tabla1[nombre_actividad],G$1)/(1),0) -> 0 | J36: =+_xlfn.XLOOKUP(B36,'R (s01)'!B:B,'R (s01)'!J:J) -> #N/A
A37: =+_xlfn.XLOOKUP(B37,Tabla1[Ducto],Tabla1[Sistema],"") -> PECO_AGROS | B37: ERM LA PERLA | C37: =+_xlfn.XLOOKUP(B37,Tabla1[Ducto],Tabla1[Length]) -> 0.006 | D37: =IFERROR(SUMIFS(Tabla1[Avance_km],Tabla1[Ducto],Resumen!$B37,Tabla1[nombre_actividad],D$1)/$C37,0) -> 1 | E37: =IFERROR(SUMIFS(Tabla1[Avance_km],Tabla1[Ducto],Resumen!$B37,Tabla1[nombre_actividad],E$1)/$C37,0) -> 1 | F37: =IFERROR(SUMIFS(Tabla1[Avance_km],Tabla1[Ducto],Resumen!$B37,Tabla1[nombre_actividad],F$1)/$C37,0) -> 1 | J37: =+_xlfn.XLOOKUP(B37,'R (s01)'!B:B,'R (s01)'!J:J) -> #N/A
A38: =+_xlfn.XLOOKUP(B38,Tabla1[Ducto],Tabla1[Sistema],"") -> LIRA_GALERAS | B38: ED PARQUE INDUSTRIAL LA BOMBA | C38: =+_xlfn.XLOOKUP(B38,Tabla1[Ducto],Tabla1[Length]) -> 0.088 | D38: =IFERROR(SUMIFS(Tabla1[Avance_km],Tabla1[Ducto],Resumen!$B38,Tabla1[nombre_actividad],D$1)/$C38,0) -> 1 | E38: =IFERROR(SUMIFS(Tabla1[Avance_km],Tabla1[Ducto],Resumen!$B38,Tabla1[nombre_actividad],E$1)/$C38,0) -> 1 | F38: =IFERROR(SUMIFS(Tabla1[Avance_km],Tabla1[Ducto],Resumen!$B38,Tabla1[nombre_actividad],F$1)/$C38,0) -> 1 | J38: =+_xlfn.XLOOKUP(B38,'R (s01)'!B:B,'R (s01)'!J:J) -> 1
A39: =+_xlfn.XLOOKUP(B39,Tabla1[Ducto],Tabla1[Sistema],"") -> LIRA_GALERAS | B39: STERLING BURDS | C39: =+_xlfn.XLOOKUP(B39,Tabla1[Ducto],Tabla1[Length]) -> 0.188 | D39: =IFERROR(SUMIFS(Tabla1[Avance_km],Tabla1[Ducto],Resumen!$B39,Tabla1[nombre_actividad],D$1)/$C39,0) -> 1 | E39: =IFERROR(SUMIFS(Tabla1[Avance_km],Tabla1[Ducto],Resumen!$B39,Tabla1[nombre_actividad],E$1)/$C39,0) -> 1 | F39: =IFERROR(SUMIFS(Tabla1[Avance_km],Tabla1[Ducto],Resumen!$B39,Tabla1[nombre_actividad],F$1)/$C39,0) -> 1 | J39: =+_xlfn.XLOOKUP(B39,'R (s01)'!B:B,'R (s01)'!J:J) -> 0
A40: =+_xlfn.XLOOKUP(B40,Tabla1[Ducto],Tabla1[Sistema],"") -> LIRA_GALERAS | B40: FABRICA DE JABON LA CORONA | C40: =+_xlfn.XLOOKUP(B40,Tabla1[Ducto],Tabla1[Length]) -> 0.007 | D40: =IFERROR(SUMIFS(Tabla1[Avance_km],Tabla1[Ducto],Resumen!$B40,Tabla1[nombre_actividad],D$1)/$C40,0) -> 1 | E40: =IFERROR(SUMIFS(Tabla1[Avance_km],Tabla1[Ducto],Resumen!$B40,Tabla1[nombre_actividad],E$1)/$C40,0) -> 1 | F40: =IFERROR(SUMIFS(Tabla1[Avance_km],Tabla1[Ducto],Resumen!$B40,Tabla1[nombre_actividad],F$1)/$C40,0) -> 1 | G40: =IFERROR(SUMIFS(Tabla1[Avance_Med],Tabla1[Ducto],Resumen!$B40,Tabla1[nombre_actividad],G$1)/(1),0) -> 0 | J40: =+_xlfn.XLOOKUP(B40,'R (s01)'!B:B,'R (s01)'!J:J) -> 0
A41: =+_xlfn.XLOOKUP(B41,Tabla1[Ducto],Tabla1[Sistema],"") -> LIRA_GALERAS | B41: GRAMOSA ALIMENTOS | C41: =+_xlfn.XLOOKUP(B41,Tabla1[Ducto],Tabla1[Length]) -> 0.019 | D41: =IFERROR(SUMIFS(Tabla1[Avance_km],Tabla1[Ducto],Resumen!$B41,Tabla1[nombre_actividad],D$1)/$C41,0) -> 1 | E41: =IFERROR(SUMIFS(Tabla1[Avance_km],Tabla1[Ducto],Resumen!$B41,Tabla1[nombre_actividad],E$1)/$C41,0) -> 1 | F41: =IFERROR(SUMIFS(Tabla1[Avance_km],Tabla1[Ducto],Resumen!$B41,Tabla1[nombre_actividad],F$1)/$C41,0) -> 1 | G41: =IFERROR(SUMIFS(Tabla1[Avance_Med],Tabla1[Ducto],Resumen!$B41,Tabla1[nombre_actividad],G$1)/(1),0) -> 0 | J41: =+_xlfn.XLOOKUP(B41,'R (s01)'!B:B,'R (s01)'!J:J) -> 0
A42: =+_xlfn.XLOOKUP(B42,Tabla1[Ducto],Tabla1[Sistema],"") -> LIRA_GALERAS | B42: ED O´DONELL | C42: =+_xlfn.XLOOKUP(B42,Tabla1[Ducto],Tabla1[Length]) -> 0.055 | D42: =IFERROR(SUMIFS(Tabla1[Avance_km],Tabla1[Ducto],Resumen!$B42,Tabla1[nombre_actividad],D$1)/$C42,0) -> 1 | E42: =IFERROR(SUMIFS(Tabla1[Avance_km],Tabla1[Ducto],Resumen!$B42,Tabla1[nombre_actividad],E$1)/$C42,0) -> 1 | F42: =IFERROR(SUMIFS(Tabla1[Avance_km],Tabla1[Ducto],Resumen!$B42,Tabla1[nombre_actividad],F$1)/$C42,0) -> 1 | J42: =+_xlfn.XLOOKUP(B42,'R (s01)'!B:B,'R (s01)'!J:J) -> 1
A43: =+_xlfn.XLOOKUP(B43,Tabla1[Ducto],Tabla1[Sistema],"") -> LIRA_GALERAS | B43: EFFEM | C43: =+_xlfn.XLOOKUP(B43,Tabla1[Ducto],Tabla1[Length]) -> 0.063 | D43: =IFERROR(SUMIFS(Tabla1[Avance_km],Tabla1[Ducto],Resumen!$B43,Tabla1[nombre_actividad],D$1)/$C43,0) -> 1 | E43: =IFERROR(SUMIFS(Tabla1[Avance_km],Tabla1[Ducto],Resumen!$B43,Tabla1[nombre_actividad],E$1)/$C43,0) -> 1 | F43: =IFERROR(SUMIFS(Tabla1[Avance_km],Tabla1[Ducto],Resumen!$B43,Tabla1[nombre_actividad],F$1)/$C43,0) -> 1 | J43: =+_xlfn.XLOOKUP(B43,'R (s01)'!B:B,'R (s01)'!J:J) -> 1
A44: =+_xlfn.XLOOKUP(B44,Tabla1[Ducto],Tabla1[Sistema],"") -> LIRA_GALERAS | B44: PAPSA | C44: =+_xlfn.XLOOKUP(B44,Tabla1[Ducto],Tabla1[Length]) -> 0.055 | D44: =IFERROR(SUMIFS(Tabla1[Avance_km],Tabla1[Ducto],Resumen!$B44,Tabla1[nombre_actividad],D$1)/$C44,0) -> 1 | E44: =IFERROR(SUMIFS(Tabla1[Avance_km],Tabla1[Ducto],Resumen!$B44,Tabla1[nombre_actividad],E$1)/$C44,0) -> 1 | F44: =IFERROR(SUMIFS(Tabla1[Avance_km],Tabla1[Ducto],Resumen!$B44,Tabla1[nombre_actividad],F$1)/$C44,0) -> 1 | G44: =IFERROR(SUMIFS(Tabla1[Avance_Med],Tabla1[Ducto],Resumen!$B44,Tabla1[nombre_actividad],G$1)/(22),0) -> 0 | J44: =+_xlfn.XLOOKUP(B44,'R (s01)'!B:B,'R (s01)'!J:J) -> 0
A45: =+_xlfn.XLOOKUP(B45,Tabla1[Ducto],Tabla1[Sistema],"") -> PECO_AGROS | B45: ERM VIMIFUS | C45: =+_xlfn.XLOOKUP(B45,Tabla1[Ducto],Tabla1[Length]) -> 0.017 | D45: =IFERROR(SUMIFS(Tabla1[Avance_km],Tabla1[Ducto],Resumen!$B45,Tabla1[nombre_actividad],D$1)/$C45,0) -> 1 | E45: =IFERROR(SUMIFS(Tabla1[Avance_km],Tabla1[Ducto],Resumen!$B45,Tabla1[nombre_actividad],E$1)/$C45,0) -> 1 | F45: =IFERROR(SUMIFS(Tabla1[Avance_km],Tabla1[Ducto],Resumen!$B45,Tabla1[nombre_actividad],F$1)/$C45,0) -> 1 | G45: =IFERROR(SUMIFS(Tabla1[Avance_Med],Tabla1[Ducto],Resumen!$B45,Tabla1[nombre_actividad],G$1)/(ROUNDUP(C45,0)*2),0) -> 0 | J45: =+_xlfn.XLOOKUP(B45,'R (s01)'!B:B,'R (s01)'!J:J) -> #N/A
A46: =+_xlfn.XLOOKUP(B46,Tabla1[Ducto],Tabla1[Sistema],"") -> LIRA_GALERAS | B46: GUARDIAN | C46: =+_xlfn.XLOOKUP(B46,Tabla1[Ducto],Tabla1[Length]) -> 10.44422 | D46: =IFERROR(SUMIFS(Tabla1[Avance_km],Tabla1[Ducto],Resumen!$B46,Tabla1[nombre_actividad],D$1)/$C46,0) -> 0.99997894 | E46: =IFERROR(SUMIFS(Tabla1[Avance_km],Tabla1[Ducto],Resumen!$B46,Tabla1[nombre_actividad],E$1)/$C46,0) -> 0.99997894 | F46: =IFERROR(SUMIFS(Tabla1[Avance_km],Tabla1[Ducto],Resumen!$B46,Tabla1[nombre_actividad],F$1)/$C46,0) -> 0.99997894 | G46: =IFERROR(SUMIFS(Tabla1[Avance_Med],Tabla1[Ducto],Resumen!$B46,Tabla1[nombre_actividad],G$1)/(1),0) -> 22 | J46: =+_xlfn.XLOOKUP(B46,'R (s01)'!B:B,'R (s01)'!J:J) -> 22
A47: =+_xlfn.XLOOKUP(B47,Tabla1[Ducto],Tabla1[Sistema],"") -> LIRA_GALERAS | B47: REFUERZO ATONGO | C47: =+_xlfn.XLOOKUP(B47,Tabla1[Ducto],Tabla1[Length]) -> 2.277 | D47: =IFERROR(SUMIFS(Tabla1[Avance_km],Tabla1[Ducto],Resumen!$B47,Tabla1[nombre_actividad],D$1)/$C47,0) -> 1 | E47: =IFERROR(SUMIFS(Tabla1[Avance_km],Tabla1[Ducto],Resumen!$B47,Tabla1[nombre_actividad],E$1)/$C47,0) -> 1 | F47: =IFERROR(SUMIFS(Tabla1[Avance_km],Tabla1[Ducto],Resumen!$B47,Tabla1[nombre_actividad],F$1)/$C47,0) -> 1 | J47: =+_xlfn.XLOOKUP(B47,'R (s01)'!B:B,'R (s01)'!J:J) -> 6
A48: =+_xlfn.XLOOKUP(B48,Tabla1[Ducto],Tabla1[Sistema],"") -> LIRA_GALERAS | B48: INDUSTRIAS KI | C48: =+_xlfn.XLOOKUP(B48,Tabla1[Ducto],Tabla1[Length]) -> 0.008 | D48: =IFERROR(SUMIFS(Tabla1[Avance_km],Tabla1[Ducto],Resumen!$B48,Tabla1[nombre_actividad],D$1)/$C48,0) -> 1 | E48: =IFERROR(SUMIFS(Tabla1[Avance_km],Tabla1[Ducto],Resumen!$B48,Tabla1[nombre_actividad],E$1)/$C48,0) -> 1 | F48: =IFERROR(SUMIFS(Tabla1[Avance_km],Tabla1[Ducto],Resumen!$B48,Tabla1[nombre_actividad],F$1)/$C48,0) -> 1 | G48: =IFERROR(SUMIFS(Tabla1[Avance_Med],Tabla1[Ducto],Resumen!$B48,Tabla1[nombre_actividad],G$1)/(1),0) -> 1 | J48: =+_xlfn.XLOOKUP(B48,'R (s01)'!B:B,'R (s01)'!J:J) -> 1
A49: =+_xlfn.XLOOKUP(B49,Tabla1[Ducto],Tabla1[Sistema],"") -> PECO_AGROS | B49: ED PIA | C49: =+_xlfn.XLOOKUP(B49,Tabla1[Ducto],Tabla1[Length]) -> 0.005 | D49: =IFERROR(SUMIFS(Tabla1[Avance_km],Tabla1[Ducto],Resumen!$B49,Tabla1[nombre_actividad],D$1)/$C49,0) -> 1 | E49: =IFERROR(SUMIFS(Tabla1[Avance_km],Tabla1[Ducto],Resumen!$B49,Tabla1[nombre_actividad],E$1)/$C49,0) -> 1 | F49: =IFERROR(SUMIFS(Tabla1[Avance_km],Tabla1[Ducto],Resumen!$B49,Tabla1[nombre_actividad],F$1)/$C49,0) -> 1 | G49: =IFERROR(SUMIFS(Tabla1[Avance_Med],Tabla1[Ducto],Resumen!$B49,Tabla1[nombre_actividad],G$1)/(1),0) -> 0 | J49: =+_xlfn.XLOOKUP(B49,'R (s01)'!B:B,'R (s01)'!J:J) -> #N/A
A50: =+_xlfn.XLOOKUP(B50,Tabla1[Ducto],Tabla1[Sistema],"") -> LIRA_GALERAS | B50: SYNTEK ASPHALT | C50: =+_xlfn.XLOOKUP(B50,Tabla1[Ducto],Tabla1[Length]) -> 0.012 | D50: =IFERROR(SUMIFS(Tabla1[Avance_km],Tabla1[Ducto],Resumen!$B50,Tabla1[nombre_actividad],D$1)/$C50,0) -> 1 | E50: =IFERROR(SUMIFS(Tabla1[Avance_km],Tabla1[Ducto],Resumen!$B50,Tabla1[nombre_actividad],E$1)/$C50,0) -> 1 | F50: =IFERROR(SUMIFS(Tabla1[Avance_km],Tabla1[Ducto],Resumen!$B50,Tabla1[nombre_actividad],F$1)/$C50,0) -> 1 | J50: =+_xlfn.XLOOKUP(B50,'R (s01)'!B:B,'R (s01)'!J:J) -> 1
A51: =+_xlfn.XLOOKUP(B51,Tabla1[Ducto],Tabla1[Sistema],"") -> LIRA_GALERAS | B51: ED LA BARCA | C51: =+_xlfn.XLOOKUP(B51,Tabla1[Ducto],Tabla1[Length]) -> 0.287 | D51: =IFERROR(SUMIFS(Tabla1[Avance_km],Tabla1[Ducto],Resumen!$B51,Tabla1[nombre_actividad],D$1)/$C51,0) -> 1 | E51: =IFERROR(SUMIFS(Tabla1[Avance_km],Tabla1[Ducto],Resumen!$B51,Tabla1[nombre_actividad],E$1)/$C51,0) -> 1 | F51: =IFERROR(SUMIFS(Tabla1[Avance_km],Tabla1[Ducto],Resumen!$B51,Tabla1[nombre_actividad],F$1)/$C51,0) -> 1 | J51: =+_xlfn.XLOOKUP(B51,'R (s01)'!B:B,'R (s01)'!J:J) -> 1
A52: =+_xlfn.XLOOKUP(B52,Tabla1[Ducto],Tabla1[Sistema],"") -> GIVAUDAN | B52: GIVAUDAN | C52: =+_xlfn.XLOOKUP(B52,Tabla1[Ducto],Tabla1[Length]) -> 0.008 | D52: =IFERROR(SUMIFS(Tabla1[Avance_km],Tabla1[Ducto],Resumen!$B52,Tabla1[nombre_actividad],D$1)/$C52,0) -> 0 | E52: =IFERROR(SUMIFS(Tabla1[Avance_km],Tabla1[Ducto],Resumen!$B52,Tabla1[nombre_actividad],E$1)/$C52,0) -> 0 | F52: =IFERROR(SUMIFS(Tabla1[Avance_km],Tabla1[Ducto],Resumen!$B52,Tabla1[nombre_actividad],F$1)/$C52,0) -> 0 | J52: =+_xlfn.XLOOKUP(B52,'R (s01)'!B:B,'R (s01)'!J:J) -> #N/A
A53: =+_xlfn.XLOOKUP(B53,Tabla1[Ducto],Tabla1[Sistema],"") -> GIVAUDAN | B53: NOWPACK | C53: =+_xlfn.XLOOKUP(B53,Tabla1[Ducto],Tabla1[Length]) -> 0.366 | D53: =IFERROR(SUMIFS(Tabla1[Avance_km],Tabla1[Ducto],Resumen!$B53,Tabla1[nombre_actividad],D$1)/$C53,0) -> 0 | E53: =IFERROR(SUMIFS(Tabla1[Avance_km],Tabla1[Ducto],Resumen!$B53,Tabla1[nombre_actividad],E$1)/$C53,0) -> 0 | F53: =IFERROR(SUMIFS(Tabla1[Avance_km],Tabla1[Ducto],Resumen!$B53,Tabla1[nombre_actividad],F$1)/$C53,0) -> 0 | J53: =+_xlfn.XLOOKUP(B53,'R (s01)'!B:B,'R (s01)'!J:J) -> #N/A
A54: =+_xlfn.XLOOKUP(B54,Tabla1[Ducto],Tabla1[Sistema],"") -> GIVAUDAN | B54: PUREMIN | C54: =+_xlfn.XLOOKUP(B54,Tabla1[Ducto],Tabla1[Length]) -> 1.175 | D54: =IFERROR(SUMIFS(Tabla1[Avance_km],Tabla1[Ducto],Resumen!$B54,Tabla1[nombre_actividad],D$1)/$C54,0) -> 0 | E54: =IFERROR(SUMIFS(Tabla1[Avance_km],Tabla1[Ducto],Resumen!$B54,Tabla1[nombre_actividad],E$1)/$C54,0) -> 0 | F54: =IFERROR(SUMIFS(Tabla1[Avance_km],Tabla1[Ducto],Resumen!$B54,Tabla1[nombre_actividad],F$1)/$C54,0) -> 0 | G54: =IFERROR(SUMIFS(Tabla1[Avance_Med],Tabla1[Ducto],Resumen!$B54,Tabla1[nombre_actividad],G$1)/(1),0) -> 3 | J54: =+_xlfn.XLOOKUP(B54,'R (s01)'!B:B,'R (s01)'!J:J) -> #N/A
A55: =+_xlfn.XLOOKUP(B55,Tabla1[Ducto],Tabla1[Sistema],"") -> SAN_GIL | B55: SAN GIL | C55: =+_xlfn.XLOOKUP(B55,Tabla1[Ducto],Tabla1[Length]) -> 3.5 | D55: =IFERROR(SUMIFS(Tabla1[Avance_km],Tabla1[Ducto],Resumen!$B55,Tabla1[nombre_actividad],D$1)/$C55,0) -> 0 | E55: =IFERROR(SUMIFS(Tabla1[Avance_km],Tabla1[Ducto],Resumen!$B55,Tabla1[nombre_actividad],E$1)/$C55,0) -> 0 | F55: =IFERROR(SUMIFS(Tabla1[Avance_km],Tabla1[Ducto],Resumen!$B55,Tabla1[nombre_actividad],F$1)/$C55,0) -> 0 | G55: =IFERROR(SUMIFS(Tabla1[Avance_Med],Tabla1[Ducto],Resumen!$B55,Tabla1[nombre_actividad],G$1)/(1),0) -> 8 | J55: =+_xlfn.XLOOKUP(B55,'R (s01)'!B:B,'R (s01)'!J:J) -> #N/A
A56: =+_xlfn.XLOOKUP(B56,Tabla1[Ducto],Tabla1[Sistema],"") -> SAN_GIL | B56: FINKA AHUEHUETE | C56: =+_xlfn.XLOOKUP(B56,Tabla1[Ducto],Tabla1[Length]) -> 0.024 | D56: =IFERROR(SUMIFS(Tabla1[Avance_km],Tabla1[Ducto],Resumen!$B58,Tabla1[nombre_actividad],D$1)/$C56,0) -> 0.5 | E56: =IFERROR(SUMIFS(Tabla1[Avance_km],Tabla1[Ducto],Resumen!$B58,Tabla1[nombre_actividad],E$1)/$C56,0) -> 0.5 | F56: =IFERROR(SUMIFS(Tabla1[Avance_km],Tabla1[Ducto],Resumen!$B58,Tabla1[nombre_actividad],F$1)/$C56,0) -> 0.5 | G56: =IFERROR(SUMIFS(Tabla1[Avance_Med],Tabla1[Ducto],Resumen!$B56,Tabla1[nombre_actividad],G$1)/(3),0) -> 0.33333333 | J56: =+_xlfn.XLOOKUP(B58,'R (s01)'!B:B,'R (s01)'!J:J) -> 0
A57: =+_xlfn.XLOOKUP(B57,Tabla1[Ducto],Tabla1[Sistema],"") -> HUIMILPAN | B57: HUIMILPAN - CERRO DEL TAMBOR 10 | C57: =+_xlfn.XLOOKUP(B57,Tabla1[Ducto],Tabla1[Length]) -> 23.864 | D57: =IFERROR(SUMIFS(Tabla1[Avance_km],Tabla1[Ducto],Resumen!#REF!,Tabla1[nombre_actividad],D$1)/$C57,0) -> 0 | E57: =IFERROR(SUMIFS(Tabla1[Avance_km],Tabla1[Ducto],Resumen!#REF!,Tabla1[nombre_actividad],E$1)/$C57,0) -> 0 | F57: =IFERROR(SUMIFS(Tabla1[Avance_km],Tabla1[Ducto],Resumen!#REF!,Tabla1[nombre_actividad],F$1)/$C57,0) -> 0 | G57: =IFERROR(SUMIFS(Tabla1[Avance_Med],Tabla1[Ducto],Resumen!$B57,Tabla1[nombre_actividad],G$1)/(8),0) -> 6.125 | J57: =+_xlfn.XLOOKUP(#REF!,'R (s01)'!B:B,'R (s01)'!J:J) -> #REF!
A58: =+_xlfn.XLOOKUP(B58,Tabla1[Ducto],Tabla1[Sistema],"") -> LIRA_GALERAS | B58: WIINERS MARK | C58: =+_xlfn.XLOOKUP(B58,Tabla1[Ducto],Tabla1[Length]) -> 0.012 | D58: =IFERROR(SUMIFS(Tabla1[Avance_km],Tabla1[Ducto],Resumen!#REF!,Tabla1[nombre_actividad],D$1)/$C58,0) -> 0 | E58: =IFERROR(SUMIFS(Tabla1[Avance_km],Tabla1[Ducto],Resumen!#REF!,Tabla1[nombre_actividad],E$1)/$C58,0) -> 0 | F58: =IFERROR(SUMIFS(Tabla1[Avance_km],Tabla1[Ducto],Resumen!#REF!,Tabla1[nombre_actividad],F$1)/$C58,0) -> 0 | G58: =IFERROR(SUMIFS(Tabla1[Avance_Med],Tabla1[Ducto],Resumen!$B58,Tabla1[nombre_actividad],G$1)/(1),0) -> 0 | J58: =+_xlfn.XLOOKUP(#REF!,'R (s01)'!B:B,'R (s01)'!J:J) -> #REF!
A59: =+_xlfn.XLOOKUP(B59,Tabla1[Ducto],Tabla1[Sistema],"") -> PECO_AGROS | B59: MICROSOFT | C59: =+_xlfn.XLOOKUP(B59,Tabla1[Ducto],Tabla1[Length]) -> 0.031 | D59: =IFERROR(SUMIFS(Tabla1[Avance_km],Tabla1[Ducto],Resumen!$B59,Tabla1[nombre_actividad],D$1)/$C59,0) -> 1 | E59: =IFERROR(SUMIFS(Tabla1[Avance_km],Tabla1[Ducto],Resumen!$B59,Tabla1[nombre_actividad],E$1)/$C59,0) -> 1 | F59: =IFERROR(SUMIFS(Tabla1[Avance_km],Tabla1[Ducto],Resumen!$B59,Tabla1[nombre_actividad],F$1)/$C59,0) -> 1 | G59: =IFERROR(SUMIFS(Tabla1[Avance_Med],Tabla1[Ducto],Resumen!$B59,Tabla1[nombre_actividad],G$1)/(49),0) -> 0.020408163 | J59: =+_xlfn.XLOOKUP(B59,'R (s01)'!B:B,'R (s01)'!J:J) -> #N/A
A60: =+_xlfn.XLOOKUP(B60,Tabla1[Ducto],Tabla1[Sistema],"") -> HUIMILPAN | B60: BALVANERA | C60: =+_xlfn.XLOOKUP(B60,Tabla1[Ducto],Tabla1[Length]) -> 1.872 | D60: =IFERROR(SUMIFS(Tabla1[Avance_km],Tabla1[Ducto],Resumen!$B60,Tabla1[nombre_actividad],D$1)/$C60,0) -> 1.025641 | E60: =IFERROR(SUMIFS(Tabla1[Avance_km],Tabla1[Ducto],Resumen!$B60,Tabla1[nombre_actividad],E$1)/$C60,0) -> 1.0042735 | F60: =IFERROR(SUMIFS(Tabla1[Avance_km],Tabla1[Ducto],Resumen!$B60,Tabla1[nombre_actividad],F$1)/$C60,0) -> 1.025641 | G60: =IFERROR(SUMIFS(Tabla1[Avance_Med],Tabla1[Ducto],Resumen!$B60,Tabla1[nombre_actividad],G$1)/(1),0) -> 5 | J60: =+_xlfn.XLOOKUP(B60,'R (s01)'!B:B,'R (s01)'!J:J) -> #N/A
A61: HUIMILPAN | B61: CANDILES | C61: =+_xlfn.XLOOKUP(B61,Tabla1[Ducto],Tabla1[Length]) -> 0.009 | D61: =IFERROR(SUMIFS(Tabla1[Avance_km],Tabla1[Ducto],Resumen!$B61,Tabla1[nombre_actividad],D$1)/$C61,0) -> 1.4444444 | E61: =IFERROR(SUMIFS(Tabla1[Avance_km],Tabla1[Ducto],Resumen!$B61,Tabla1[nombre_actividad],E$1)/$C61,0) -> 1.4444444 | F61: =IFERROR(SUMIFS(Tabla1[Avance_km],Tabla1[Ducto],Resumen!$B61,Tabla1[nombre_actividad],F$1)/$C61,0) -> 1.4444444 | G61: =IFERROR(SUMIFS(Tabla1[Avance_Med],Tabla1[Ducto],Resumen!$B61,Tabla1[nombre_actividad],G$1)/(5),0) -> 0.2
A62: HUIMILPAN | B62: ESTACION ATONGO | C62: =+_xlfn.XLOOKUP(B62,Tabla1[Ducto],Tabla1[Length]) -> 0.037 | D62: =IFERROR(SUMIFS(Tabla1[Avance_km],Tabla1[Ducto],Resumen!$B62,Tabla1[nombre_actividad],D$1)/$C62,0) -> 1 | E62: =IFERROR(SUMIFS(Tabla1[Avance_km],Tabla1[Ducto],Resumen!$B62,Tabla1[nombre_actividad],E$1)/$C62,0) -> 1 | F62: =IFERROR(SUMIFS(Tabla1[Avance_km],Tabla1[Ducto],Resumen!$B62,Tabla1[nombre_actividad],F$1)/$C62,0) -> 1 | G62: =IFERROR(SUMIFS(Tabla1[Avance_Med],Tabla1[Ducto],Resumen!$B62,Tabla1[nombre_actividad],G$1)/(1),0) -> 0
B63: TOM FROG
B64: NATGAS CELAYA CUOTA
B65: ERM NATGAS CELAYA CUOTA
B66: KELLOG´S
B67: TECNOLÓGICO
B68: ED TECNOLÓGICO
B69: EMBOTELLADORA VICTORIA
B70: ED CARRILLO PUERTO
B71: NATGAS OBRERA
B72: AGROGEN
B73: GERRESHEIMER
B74: ED SATELITE
... B130: todos

Sheet Catálogo de conceptos
D1: Catálogo de conceptos: Regional DGQ / Evaluación directa por corrosión externa (ECDA) bajo el estándar practico SP0502-2010 (AMPP) en el total de red de distribucion de la regional DGQ en una longitud de 200 kilometros de red en direferentes diametros (10", 8", 6", 4", 3" y 2").
B3: Nombre del Proveedor | G3: PROYECTO:
G4: ECDA DGQ
B5: POSICIÓN | C5: DESCRIPCIÓN BREVE | G5: CANTIDAD | H5: UNIDAD DE MEDIDA (UM) | I5: PRECIO UNITARIO | J5: TOTAL | K5: MONEDA
B6: 1 | C6: ETAPA 1
B7: 1.1 | C7: Recopilación de Información | G7: 105 | H7: DUCTO | I7: 0 | J7: =I7*G7 -> 0 | K7: MXN
B8: 1.2 | C8: Análisis de Información | G8: 105 | H8: DUCTO | I8: 0 | J8: =I8*G8 -> 0 | K8: MXN
B9: 1.3 | C9: Evaluación de factibilidad de ECDA | G9: 105 | H9: DUCTO | I9: 0 | J9: =I9*G9 -> 0 | K9: MXN
B10: 1,4 | C10: Selección de técnicas de inspección indirecta | G10: 105 | H10: DUCTO | I10: 0 | J10: =I10*G10 -> 0 | K10: MXN
B11: 1.5 | C11: Definición de zonas ECDA | G11: 105 | H11: DUCTO | I11: 0 | J11: =I11*G11 -> 0 | K11: MXN
B12: 1.6 | C12: Reporte final entregable (con resultados, diagnosticos, hallazgos, recomendaciones y conclusiones). Esta partida puede reducir en funcion de la cantidad de ductos principales. | G12: 105 | H12: DUCTO | I12: 0 | J12: =I12*G12 -> 0 | K12: MXN
B13: 2 | C13: ETAPA 2 | I13: Subtotal | J13: =SUM(J7:J12) -> 0
B14: 2.1 | C14: Estudio de potencial a intervalos cortos (Close Interval Potential Survey-CIPS). | G14: 200 | H14: KM | I14: 0 | J14: =I14*G14 -> 0 | K14: MXN
B15: 2.2 | C15: Estudio Gradiente de Voltaje de Corriente Alterna (ACVG). | G15: 200 | H15: KM | I15: 0 | J15: =I15*G15 -> 0 | K15: MXN
B16: 2.3 | C16: Estudio Gradiente de Voltaje de Corriente Directa (DCVG). | G16: 200 | H16: KM | I16: 0 | J16: =I16*G16 -> 0 | K16: MXN
B17: 2.4 | C17: Mapeo de corriente PCM | G17: 200 | H17: KM | I17: 0 | J17: =I17*G17 -> 0 | K17: MXN
B18: 2.5 | C18: Levantamiento de resistividad pH y bacterias a lo largo de la trayectoria del ducto a cada 500 m Incluye mano de obra, kits y equipo | G18: 500 | H18: SERVICIOS | I18: 0 | J18: =I18*G18 -> 0 | K18: MXN
B19: 2.6 | C19: Localización de Ducto. | G19: 200 | H19: KM | I19: 0 | J19: =I19*G19 -> 0 | K19: MXN
B20: 2.7 | C20: Definir y clasificar la severidad de indicaciones | G20: 105 | H20: DUCTO | I20: 0 | J20: =I20*G20 -> 0 | K20: MXN
B21: 2.8 | C21: Reporte final entregable (con resultados, diagnosticos, hallazgos, recomendaciones y conclusiones). Esta partida puede reducir en funcion de la cantidad de ductos principales. | G21: 105 | H21: DUCTO | I21: 0 | J21: =I21*G21 -> 0 | K21: MXN
B22: 3 | C22: ETAPA 3 | I22: Subtotal | J22: =SUM(J14:J21) -> 0
B23: 3.1 | C23: Selección y priorización de indicaciones para examinación directa | G23: 105 | H23: DUCTOS | I23: 0 | J23: =I23*G23 -> 0 | K23: MXN
B24: 3.2 | C24: Recopilación de datos en la excavación | G24: 55 | H24: VERIFICACIONES | I24: 0 | J24: =I24*G24 -> 0 | K24: MXN
B25: 3.3 | C25: Evaluacion de la inspeccion en campo mediante ensayos no destructivos: | I25: 0 | J25: =I25*G25 -> 0 | K25: MXN
B26: 3.3.1 | C26: Inspeccion visual | G26: 55 | H26: VERIFICACIONES | I26: 0 | J26: =I26*G26 -> 0 | K26: MXN
B27: 3.3.2 | C27: Evaluacion de sanidad y medicion de espesores | G27: 100 | H27: SERVICIO | I27: 0 | J27: =I27*G27 -> 0 | K27: MXN
B28: 3.3.3 | C28: Caracterizacion de tuberia | G28: 100 | H28: SERVICIO | I28: 0 | J28: =I28*G28 -> 0 | K28: MXN
B29: 3.3.4 | C29: Evaluacion de soldadura con haz angular | G29: 170 | H29: SERVICIO | I29: 0 | J29: =I29*G29 -> 0 | K29: MXN
B30: 3.3.5 | C30: Inspección de ultrasonido de haz recto | G30: 170 | H30: SERVICIO | I30: 0 | J30: =I30*G30 -> 0 | K30: MXN
B31: 3.3.6 | C31: Inspección con particulas magneticas | G31: 100 | H31: SERVICIO | I31: 0 | J31: =I31*G31 -> 0 | K31: MXN
B32: 3.3.7 | C32: Inspeccion con liquidos penetrantes | G32: 100 | H32: SERVICIO | I32: 0 | J32: =I32*G32 -> 0 | K32: MXN
B33: 3.3.8 | C33: Medicion de PH de suelo dentro de excavación | G33: 55 | H33: SERVICIO | I33: 0 | J33: =I33*G33 -> 0 | K33: MXN
B34: 3.3.9 | C34: Medicion de corrosion por actividadad microbiologica y levantamiento de bacterias. | G34: 55 | H34: SERVICIO | I34: 0 | J34: =I34*G34 -> 0 | K34: MXN
B35: 3.3 | C35: Reportes finales entregables (con resultados, diagnosticos, hallazgos, recomendaciones y conclusiones). Esta partida puede reducir en funcion de la cantidad de ductos principales. | G35: 105 | H35: DUCTO | I35: 0 | J35: =I35*G35 -> 0 | K35: MXN
B36: 4 | C36: ETAPA 4 | I36: Subtotal | J36: =SUM(J23:J35) -> 0
B37: 4.1 | C37: Evaluación de esfuerzo remanente de defectos. | G37: 105 | H37: DUCTO | I37: 0 | J37: =I37*G37 -> 0 | K37: MXN
B38: 4.2 | C38: Análisis de las condiciones encontradas y evaluación del proceso. | G38: 105 | H38: DUCTO | I38: 0 | J38: =I38*G38 -> 0 | K38: MXN
B39: 4.3 | C39: Cálculo de las tasas de corrosión y vida remanente. | G39: 105 | H39: DUCTO | I39: 0 | J39: =I39*G39 -> 0 | K39: MXN
B40: 4.4 | C40: Análisis causa – raíz. | G40: 105 | H40: DUCTO | I40: 0 | J40: =I40*G40 -> 0 | K40: MXN
B41: 4.5 | C41: Definición de intervalos de re-inspección. | G41: 105 | H41: DUCTO | I41: 0 | J41: =I41*G41 -> 0 | K41: MXN
B42: 4.6 | C42: Evaluación de efectividad del proceso de ECDA. | G42: 105 | H42: DUCTO | I42: 0 | J42: =I42*G42 -> 0 | K42: MXN
B43: 4.7 | C43: Elaboración del reporte final ECDA. | G43: 105 | H43: DUCTO | I43: 0 | J43: =I43*G43 -> 0 | K43: MXN
B44: 4.8 | C44: Re-priorización de atención. | G44: 105 | H44: DUCTO | I44: 0 | J44: =I44*G44 -> 0 | K44: MXN
B45: 4.9 | C45: Suministro y aplicación de recubrimiento viscoelastico anticorrosivo en diametros de 2" a 4" de diametro, incluyendo sus pruebas dielectricas, y de adeherencia. | G45: 100 | H45: M LINEAL POR DIAMETRO | I45: 0 | J45: =I45*G45 -> 0 | K45: MXN
B46: 4.1 | C46: Suministro y aplicación de recubrimiento viscoelastico anticorrosivo en diametros de 6" a 8" de diametro, incluyendo sus pruebas dielectricas y de adeherencia. | G46: 500 | H46: M LINEAL POR DIAMETRO | I46: 0 | J46: =I46*G46 -> 0 | K46: MXN
B47: 4.11 | C47: Suministro y aplicación de recubrimiento viscoelastico anticorrosivo en diametros de 10" a 12" de diametro, incluyendo sus pruebas dielectricas y de adeherencia. | G47: 800 | H47: M LINEAL POR DIAMETRO | I47: 0 | J47: =I47*G47 -> 0 | K47: MXN
B48: 4.12 | C48: Reportes finales entregables (con resultados, diagnosticos, hallazgos, recomendaciones y conclusiones). | G48: 105 | H48: DUCTO | I48: 0 | J48: =I48*G48 -> 0 | K48: MXN
B49: 5 | C49: Acompañamiento de seguridad | I49: Subtotal | J49: =SUM(J37:J48) -> 0
B50: 5.1 | C50: Acompañamiento de seguridad en las actividades en campo, ETAPA 2 | H50: Servicio | I50: 0 | J50: =I50*G50 -> 0 | K50: MXN
B51: 5.2 | C51: Acompañamiento de seguridad en las actividades en campo, ETAPA 3 | H51: Servicio | I51: 0 | J51: =I51*G51 -> 0 | K51: MXN
I52: Total | J52: =SUM(J13+J22+J36+J49+J50+J51) -> 0 | K52: MXN
B55: Condiciones comerciales
B60: Observaciones
B66: 6 | C66: LA PROPUESTA TECNICA DEBE CONTENER INFORMACION ADICIONAL
B67: 6.1 | C67: Presentar CV empresarial
B68: 6.2 | C68: Documentos entregables (Formato de reportes)
B69: 6.3 | C69: Procedimientos operativos y su analisis de riesgo de cada actividad operativa.
B70: 6.4 | C70: Plan de trabajo
B71: 6.5 | C71: Propuesta del personal técnico (Cuadrillas de trabajo)
B72: 6.6 | C72: Cumplimiento de Seguridad, salud ocupacional y medio ambiente

Sheet waterfall ENGIE
B1: 2532.81 | C1: 3250.01 | D1: 985.32 | E1: 1062.92 | F1: 1337.25 | G1: 1581.21 | H1: 14521.41 | I1: 13555.63 | J1: 13555.63 | K1: 13696.28 | L1: 4658 | M1: 2257.42 | N1: 3540.12 | O1: 2646.28 | P1: 1970.65 | Q1: 1
B2: 1.1 | C2: 1.2 | D2: 1.3 | E2: 1.4 | F2: 1.5 | G2: 1.6 | H2: 2.1 | I2: 2.2 | J2: 2.3 | K2: 2.4 | L2: 2.5 | M2: 2.6 | N2: 2.7 | O2: 2.8 | P2: 3.1
B3: Etapa 1 | H3: CIPS | I3: ACVG | J3: DCVG | K3: PCM | L3: Resistividades pH BSR BPA | M3: Localizacion | N3: Clasif | O3: Reporte E2 | P3: Priorizacion | Q3: Abono | R3: EV
A4: Pago 1 | Q4: -11162922 | R4: =+SUMPRODUCT(B4:Q4,$B$1:$Q$1) -> -11162922
A5: 45931 | B5: =+SUMIFS(Tabla1[Avance_Med],Tabla1[Fecha],">="&$A5,Tabla1[Fecha],"<="&EOMONTH($A5,0),Tabla1[Codigo_actividad],B$2) -> 0 | C5: =+SUMIFS(Tabla1[Avance_Med],Tabla1[Fecha],">="&$A5,Tabla1[Fecha],"<="&EOMONTH($A5,0),Tabla1[Codigo_actividad],C$2) -> 0 | D5: =+SUMIFS(Tabla1[Avance_Med],Tabla1[Fecha],">="&$A5,Tabla1[Fecha],"<="&EOMONTH($A5,0),Tabla1[Codigo_actividad],D$2) -> 0 | E5: =+SUMIFS(Tabla1[Avance_Med],Tabla1[Fecha],">="&$A5,Tabla1[Fecha],"<="&EOMONTH($A5,0),Tabla1[Codigo_actividad],E$2) -> 0 | F5: =+SUMIFS(Tabla1[Avance_Med],Tabla1[Fecha],">="&$A5,Tabla1[Fecha],"<="&EOMONTH($A5,0),Tabla1[Codigo_actividad],F$2) -> 0 | G5: =+SUMIFS(Tabla1[Avance_Med],Tabla1[Fecha],">="&$A5,Tabla1[Fecha],"<="&EOMONTH($A5,0),Tabla1[Codigo_actividad],G$2) -> 0 | H5: =+SUMIFS(Tabla1[Avance_km],Tabla1[Fecha],">="&$A5,Tabla1[Fecha],"<="&EOMONTH($A5,0),Tabla1[nombre_actividad],H$3) -> 0 | J5: =+SUMIFS(Tabla1[Avance_km],Tabla1[Fecha],">="&$A5,Tabla1[Fecha],"<="&EOMONTH($A5,0),Tabla1[nombre_actividad],$J$3,Tabla1[Avance_km],">0") -> 0 | L5: =+SUMIFS(Tabla1[Avance_Med],Tabla1[Fecha],">="&$A5,Tabla1[Fecha],"<="&EOMONTH($A5,0),Tabla1[Codigo_actividad],L$2) -> 0 | M5: =+SUMIFS(Tabla1[Avance_km],Tabla1[Fecha],">="&$A5,Tabla1[Fecha],"<="&EOMONTH($A5,0),Tabla1[nombre_actividad],$M$3) -> 0 | N5: =+SUMIFS(Tabla1[Avance_Med],Tabla1[Fecha],">="&$A5,Tabla1[Fecha],"<="&EOMONTH($A5,0),Tabla1[Codigo_actividad],N$2) -> 0 | O5: =+SUMIFS(Tabla1[Avance_Med],Tabla1[Fecha],">="&$A5,Tabla1[Fecha],"<="&EOMONTH($A5,0),Tabla1[Codigo_actividad],O$2) -> 0 | P5: =+SUMIFS(Tabla1[Avance_Med],Tabla1[Fecha],">="&$A5,Tabla1[Fecha],"<="&EOMONTH($A5,0),Tabla1[Codigo_actividad],P$2) -> 0 | R5: =+SUMPRODUCT(B5:P5,$B$1:$P$1) -> 0
A6: 45962 | B6: =+SUMIFS(Tabla1[Avance_Med],Tabla1[Fecha],">="&$A6,Tabla1[Fecha],"<="&EOMONTH($A6,0),Tabla1[Codigo_actividad],B$2) -> 0 | C6: =+SUMIFS(Tabla1[Avance_Med],Tabla1[Fecha],">="&$A6,Tabla1[Fecha],"<="&EOMONTH($A6,0),Tabla1[Codigo_actividad],C$2) -> 0 | D6: =+SUMIFS(Tabla1[Avance_Med],Tabla1[Fecha],">="&$A6,Tabla1[Fecha],"<="&EOMONTH($A6,0),Tabla1[Codigo_actividad],D$2) -> 0 | E6: =+SUMIFS(Tabla1[Avance_Med],Tabla1[Fecha],">="&$A6,Tabla1[Fecha],"<="&EOMONTH($A6,0),Tabla1[Codigo_actividad],E$2) -> 0 | F6: =+SUMIFS(Tabla1[Avance_Med],Tabla1[Fecha],">="&$A6,Tabla1[Fecha],"<="&EOMONTH($A6,0),Tabla1[Codigo_actividad],F$2) -> 0 | G6: =+SUMIFS(Tabla1[Avance_Med],Tabla1[Fecha],">="&$A6,Tabla1[Fecha],"<="&EOMONTH($A6,0),Tabla1[Codigo_actividad],G$2) -> 0 | H6: =+SUMIFS(Tabla1[Avance_km],Tabla1[Fecha],">="&$A6,Tabla1[Fecha],"<="&EOMONTH($A6,0),Tabla1[nombre_actividad],H$3) -> 31.549 | J6: =+SUMIFS(Tabla1[Avance_km],Tabla1[Fecha],">="&$A6,Tabla1[Fecha],"<="&EOMONTH($A6,0),Tabla1[nombre_actividad],$J$3,Tabla1[Avance_km],">0") -> 53.049 | L6: =+SUMIFS(Tabla1[Avance_Med],Tabla1[Fecha],">="&$A6,Tabla1[Fecha],"<="&EOMONTH($A6,0),Tabla1[Codigo_actividad],L$2) -> 98 | M6: =+SUMIFS(Tabla1[Avance_km],Tabla1[Fecha],">="&$A6,Tabla1[Fecha],"<="&EOMONTH($A6,0),Tabla1[nombre_actividad],$M$3) -> 72.022 | N6: =+SUMIFS(Tabla1[Avance_Med],Tabla1[Fecha],">="&$A6,Tabla1[Fecha],"<="&EOMONTH($A6,0),Tabla1[Codigo_actividad],N$2) -> 0 | O6: =+SUMIFS(Tabla1[Avance_Med],Tabla1[Fecha],">="&$A6,Tabla1[Fecha],"<="&EOMONTH($A6,0),Tabla1[Codigo_actividad],O$2) -> 0 | P6: =+SUMIFS(Tabla1[Avance_Med],Tabla1[Fecha],">="&$A6,Tabla1[Fecha],"<="&EOMONTH($A6,0),Tabla1[Codigo_actividad],P$2) -> 0 | R6: =+SUMPRODUCT(B6:P6,$B$1:$P$1) -> 1796316.5
A7: 45992 | B7: =+SUMIFS(Tabla1[Avance_Med],Tabla1[Fecha],">="&$A7,Tabla1[Fecha],"<="&EOMONTH($A7,0),Tabla1[Codigo_actividad],B$2) -> 0 | C7: =+SUMIFS(Tabla1[Avance_Med],Tabla1[Fecha],">="&$A7,Tabla1[Fecha],"<="&EOMONTH($A7,0),Tabla1[Codigo_actividad],C$2) -> 0 | D7: =+SUMIFS(Tabla1[Avance_Med],Tabla1[Fecha],">="&$A7,Tabla1[Fecha],"<="&EOMONTH($A7,0),Tabla1[Codigo_actividad],D$2) -> 0 | E7: =+SUMIFS(Tabla1[Avance_Med],Tabla1[Fecha],">="&$A7,Tabla1[Fecha],"<="&EOMONTH($A7,0),Tabla1[Codigo_actividad],E$2) -> 0 | F7: =+SUMIFS(Tabla1[Avance_Med],Tabla1[Fecha],">="&$A7,Tabla1[Fecha],"<="&EOMONTH($A7,0),Tabla1[Codigo_actividad],F$2) -> 0 | G7: =+SUMIFS(Tabla1[Avance_Med],Tabla1[Fecha],">="&$A7,Tabla1[Fecha],"<="&EOMONTH($A7,0),Tabla1[Codigo_actividad],G$2) -> 0 | H7: =+SUMIFS(Tabla1[Avance_km],Tabla1[Fecha],">="&$A7,Tabla1[Fecha],"<="&EOMONTH($A7,0),Tabla1[nombre_actividad],H$3) -> 31.517 | J7: =+SUMIFS(Tabla1[Avance_km],Tabla1[Fecha],">="&$A7,Tabla1[Fecha],"<="&EOMONTH($A7,0),Tabla1[nombre_actividad],$J$3,Tabla1[Avance_km],">0") -> 31.544 | L7: =+SUMIFS(Tabla1[Avance_Med],Tabla1[Fecha],">="&$A7,Tabla1[Fecha],"<="&EOMONTH($A7,0),Tabla1[Codigo_actividad],L$2) -> 130 | M7: =+SUMIFS(Tabla1[Avance_km],Tabla1[Fecha],">="&$A7,Tabla1[Fecha],"<="&EOMONTH($A7,0),Tabla1[nombre_actividad],$M$3) -> 21.183 | N7: =+SUMIFS(Tabla1[Avance_Med],Tabla1[Fecha],">="&$A7,Tabla1[Fecha],"<="&EOMONTH($A7,0),Tabla1[Codigo_actividad],N$2) -> 0 | O7: =+SUMIFS(Tabla1[Avance_Med],Tabla1[Fecha],">="&$A7,Tabla1[Fecha],"<="&EOMONTH($A7,0),Tabla1[Codigo_actividad],O$2) -> 0 | P7: =+SUMIFS(Tabla1[Avance_Med],Tabla1[Fecha],">="&$A7,Tabla1[Fecha],"<="&EOMONTH($A7,0),Tabla1[Codigo_actividad],P$2) -> 0 | R7: =+SUMPRODUCT(B7:P7,$B$1:$P$1) -> 1538629
A8: 46023 | B8: =+SUMIFS(Tabla1[Avance_Med],Tabla1[Fecha],">="&$A8,Tabla1[Fecha],"<="&EOMONTH($A8,0),Tabla1[Codigo_actividad],B$2) -> 0 | C8: =+SUMIFS(Tabla1[Avance_Med],Tabla1[Fecha],">="&$A8,Tabla1[Fecha],"<="&EOMONTH($A8,0),Tabla1[Codigo_actividad],C$2) -> 0 | D8: =+SUMIFS(Tabla1[Avance_Med],Tabla1[Fecha],">="&$A8,Tabla1[Fecha],"<="&EOMONTH($A8,0),Tabla1[Codigo_actividad],D$2) -> 0 | E8: =+SUMIFS(Tabla1[Avance_Med],Tabla1[Fecha],">="&$A8,Tabla1[Fecha],"<="&EOMONTH($A8,0),Tabla1[Codigo_actividad],E$2) -> 0 | F8: =+SUMIFS(Tabla1[Avance_Med],Tabla1[Fecha],">="&$A8,Tabla1[Fecha],"<="&EOMONTH($A8,0),Tabla1[Codigo_actividad],F$2) -> 0 | G8: =+SUMIFS(Tabla1[Avance_Med],Tabla1[Fecha],">="&$A8,Tabla1[Fecha],"<="&EOMONTH($A8,0),Tabla1[Codigo_actividad],G$2) -> 0 | H8: =+SUMIFS(Tabla1[Avance_km],Tabla1[Fecha],">="&$A8,Tabla1[Fecha],"<="&EOMONTH($A8,0),Tabla1[nombre_actividad],H$3) -> 36.84 | J8: =+SUMIFS(Tabla1[Avance_km],Tabla1[Fecha],">="&$A8,Tabla1[Fecha],"<="&EOMONTH($A8,0),Tabla1[nombre_actividad],$J$3,Tabla1[Avance_km],">0") -> 15.313 | L8: =+SUMIFS(Tabla1[Avance_Med],Tabla1[Fecha],">="&$A8,Tabla1[Fecha],"<="&EOMONTH($A8,0),Tabla1[Codigo_actividad],L$2) -> 130 | M8: =+SUMIFS(Tabla1[Avance_km],Tabla1[Fecha],">="&$A8,Tabla1[Fecha],"<="&EOMONTH($A8,0),Tabla1[nombre_actividad],$M$3) -> 6.701 | N8: =+SUMIFS(Tabla1[Avance_Med],Tabla1[Fecha],">="&$A8,Tabla1[Fecha],"<="&EOMONTH($A8,0),Tabla1[Codigo_actividad],N$2) -> 0 | O8: =+SUMIFS(Tabla1[Avance_Med],Tabla1[Fecha],">="&$A8,Tabla1[Fecha],"<="&EOMONTH($A8,0),Tabla1[Codigo_actividad],O$2) -> 0 | P8: =+SUMIFS(Tabla1[Avance_Med],Tabla1[Fecha],">="&$A8,Tabla1[Fecha],"<="&EOMONTH($A8,0),Tabla1[Codigo_actividad],P$2) -> 0 | R8: =+SUMPRODUCT(B8:P8,$B$1:$P$1) -> 1363213.1
A9: 46054 | B9: =+SUMIFS(Tabla1[Avance_Med],Tabla1[Fecha],">="&$A9,Tabla1[Fecha],"<="&EOMONTH($A9,0),Tabla1[Codigo_actividad],B$2) -> 0 | C9: =+SUMIFS(Tabla1[Avance_Med],Tabla1[Fecha],">="&$A9,Tabla1[Fecha],"<="&EOMONTH($A9,0),Tabla1[Codigo_actividad],C$2) -> 0 | D9: =+SUMIFS(Tabla1[Avance_Med],Tabla1[Fecha],">="&$A9,Tabla1[Fecha],"<="&EOMONTH($A9,0),Tabla1[Codigo_actividad],D$2) -> 0 | E9: =+SUMIFS(Tabla1[Avance_Med],Tabla1[Fecha],">="&$A9,Tabla1[Fecha],"<="&EOMONTH($A9,0),Tabla1[Codigo_actividad],E$2) -> 0 | F9: =+SUMIFS(Tabla1[Avance_Med],Tabla1[Fecha],">="&$A9,Tabla1[Fecha],"<="&EOMONTH($A9,0),Tabla1[Codigo_actividad],F$2) -> 0 | G9: =+SUMIFS(Tabla1[Avance_Med],Tabla1[Fecha],">="&$A9,Tabla1[Fecha],"<="&EOMONTH($A9,0),Tabla1[Codigo_actividad],G$2) -> 0 | H9: =+SUMIFS(Tabla1[Avance_km],Tabla1[Fecha],">="&$A9,Tabla1[Fecha],"<="&EOMONTH($A9,0),Tabla1[nombre_actividad],H$3) -> 0 | J9: =+SUMIFS(Tabla1[Avance_km],Tabla1[Fecha],">="&$A9,Tabla1[Fecha],"<="&EOMONTH($A9,0),Tabla1[nombre_actividad],$J$3,Tabla1[Avance_km],">0") -> 0 | L9: =+SUMIFS(Tabla1[Avance_Med],Tabla1[Fecha],">="&$A9,Tabla1[Fecha],"<="&EOMONTH($A9,0),Tabla1[Codigo_actividad],L$2) -> 18 | M9: =+SUMIFS(Tabla1[Avance_km],Tabla1[Fecha],">="&$A9,Tabla1[Fecha],"<="&EOMONTH($A9,0),Tabla1[nombre_actividad],$M$3) -> 0 | N9: =+SUMIFS(Tabla1[Avance_Med],Tabla1[Fecha],">="&$A9,Tabla1[Fecha],"<="&EOMONTH($A9,0),Tabla1[Codigo_actividad],N$2) -> 0 | O9: =+SUMIFS(Tabla1[Avance_Med],Tabla1[Fecha],">="&$A9,Tabla1[Fecha],"<="&EOMONTH($A9,0),Tabla1[Codigo_actividad],O$2) -> 0 | P9: =+SUMIFS(Tabla1[Avance_Med],Tabla1[Fecha],">="&$A9,Tabla1[Fecha],"<="&EOMONTH($A9,0),Tabla1[Codigo_actividad],P$2) -> 0 | R9: =+SUMPRODUCT(B9:P9,$B$1:$P$1) -> 83844
A10: 46082 | B10: =+SUMIFS(Tabla1[Avance_Med],Tabla1[Fecha],">="&$A10,Tabla1[Fecha],"<="&EOMONTH($A10,0),Tabla1[Codigo_actividad],B$2) -> 99 | C10: =+SUMIFS(Tabla1[Avance_Med],Tabla1[Fecha],">="&$A10,Tabla1[Fecha],"<="&EOMONTH($A10,0),Tabla1[Codigo_actividad],C$2) -> 99 | D10: =+SUMIFS(Tabla1[Avance_Med],Tabla1[Fecha],">="&$A10,Tabla1[Fecha],"<="&EOMONTH($A10,0),Tabla1[Codigo_actividad],D$2) -> 99 | E10: =+SUMIFS(Tabla1[Avance_Med],Tabla1[Fecha],">="&$A10,Tabla1[Fecha],"<="&EOMONTH($A10,0),Tabla1[Codigo_actividad],E$2) -> 99 | F10: =+SUMIFS(Tabla1[Avance_Med],Tabla1[Fecha],">="&$A10,Tabla1[Fecha],"<="&EOMONTH($A10,0),Tabla1[Codigo_actividad],F$2) -> 99 | G10: =+SUMIFS(Tabla1[Avance_Med],Tabla1[Fecha],">="&$A10,Tabla1[Fecha],"<="&EOMONTH($A10,0),Tabla1[Codigo_actividad],G$2) -> 99 | H10: =+SUMIFS(Tabla1[Avance_km],Tabla1[Fecha],">="&$A10,Tabla1[Fecha],"<="&EOMONTH($A10,0),Tabla1[nombre_actividad],H$3) -> 0 | J10: =+SUMIFS(Tabla1[Avance_km],Tabla1[Fecha],">="&$A10,Tabla1[Fecha],"<="&EOMONTH($A10,0),Tabla1[nombre_actividad],$J$3,Tabla1[Avance_km],">0") -> 0 | L10: =+SUMIFS(Tabla1[Avance_Med],Tabla1[Fecha],">="&$A10,Tabla1[Fecha],"<="&EOMONTH($A10,0),Tabla1[Codigo_actividad],L$2) -> 0 | M10: =+SUMIFS(Tabla1[Avance_km],Tabla1[Fecha],">="&$A10,Tabla1[Fecha],"<="&EOMONTH($A10,0),Tabla1[nombre_actividad],$M$3) -> 3.6 | N10: =+SUMIFS(Tabla1[Avance_Med],Tabla1[Fecha],">="&$A10,Tabla1[Fecha],"<="&EOMONTH($A10,0),Tabla1[Codigo_actividad],N$2) -> 54 | O10: =+SUMIFS(Tabla1[Avance_Med],Tabla1[Fecha],">="&$A10,Tabla1[Fecha],"<="&EOMONTH($A10,0),Tabla1[Codigo_actividad],O$2) -> 54 | P10: =+SUMIFS(Tabla1[Avance_Med],Tabla1[Fecha],">="&$A10,Tabla1[Fecha],"<="&EOMONTH($A10,0),Tabla1[Codigo_actividad],P$2) -> 54 | R10: =+SUMPRODUCT(B10:P10,$B$1:$P$1) -> 1512809.9
A11: 46113 | B11: =+SUMIFS(Tabla1[Avance_Med],Tabla1[Fecha],">="&$A11,Tabla1[Fecha],"<="&EOMONTH($A11,0),Tabla1[Codigo_actividad],B$2) -> 17 | C11: =+SUMIFS(Tabla1[Avance_Med],Tabla1[Fecha],">="&$A11,Tabla1[Fecha],"<="&EOMONTH($A11,0),Tabla1[Codigo_actividad],C$2) -> 17 | D11: =+SUMIFS(Tabla1[Avance_Med],Tabla1[Fecha],">="&$A11,Tabla1[Fecha],"<="&EOMONTH($A11,0),Tabla1[Codigo_actividad],D$2) -> 17 | E11: =+SUMIFS(Tabla1[Avance_Med],Tabla1[Fecha],">="&$A11,Tabla1[Fecha],"<="&EOMONTH($A11,0),Tabla1[Codigo_actividad],E$2) -> 17 | F11: =+SUMIFS(Tabla1[Avance_Med],Tabla1[Fecha],">="&$A11,Tabla1[Fecha],"<="&EOMONTH($A11,0),Tabla1[Codigo_actividad],F$2) -> 17 | G11: =+SUMIFS(Tabla1[Avance_Med],Tabla1[Fecha],">="&$A11,Tabla1[Fecha],"<="&EOMONTH($A11,0),Tabla1[Codigo_actividad],G$2) -> 17 | H11: =+SUMIFS(Tabla1[Avance_km],Tabla1[Fecha],">="&$A11,Tabla1[Fecha],"<="&EOMONTH($A11,0),Tabla1[nombre_actividad],H$3) -> 0 | J11: =+SUMIFS(Tabla1[Avance_km],Tabla1[Fecha],">="&$A11,Tabla1[Fecha],"<="&EOMONTH($A11,0),Tabla1[nombre_actividad],$J$3,Tabla1[Avance_km],">0") -> 5.955 | L11: =+SUMIFS(Tabla1[Avance_Med],Tabla1[Fecha],">="&$A11,Tabla1[Fecha],"<="&EOMONTH($A11,0),Tabla1[Codigo_actividad],L$2) -> 0 | M11: =+SUMIFS(Tabla1[Avance_km],Tabla1[Fecha],">="&$A11,Tabla1[Fecha],"<="&EOMONTH($A11,0),Tabla1[nombre_actividad],$M$3) -> 21.636 | N11: =+SUMIFS(Tabla1[Avance_Med],Tabla1[Fecha],">="&$A11,Tabla1[Fecha],"<="&EOMONTH($A11,0),Tabla1[Codigo_actividad],N$2) -> 0 | O11: =+SUMIFS(Tabla1[Avance_Med],Tabla1[Fecha],">="&$A11,Tabla1[Fecha],"<="&EOMONTH($A11,0),Tabla1[Codigo_actividad],O$2) -> 0 | P11: =+SUMIFS(Tabla1[Avance_Med],Tabla1[Fecha],">="&$A11,Tabla1[Fecha],"<="&EOMONTH($A11,0),Tabla1[Codigo_actividad],P$2) -> 0 | R11: =+SUMPRODUCT(B11:P11,$B$1:$P$1) -> 312307.16
A12: 46143 | B12: =+SUMIFS(Tabla1[Avance_Med],Tabla1[Fecha],">="&$A12,Tabla1[Fecha],"<="&EOMONTH($A12,0),Tabla1[Codigo_actividad],B$2) -> 0 | C12: =+SUMIFS(Tabla1[Avance_Med],Tabla1[Fecha],">="&$A12,Tabla1[Fecha],"<="&EOMONTH($A12,0),Tabla1[Codigo_actividad],C$2) -> 0 | D12: =+SUMIFS(Tabla1[Avance_Med],Tabla1[Fecha],">="&$A12,Tabla1[Fecha],"<="&EOMONTH($A12,0),Tabla1[Codigo_actividad],D$2) -> 0 | E12: =+SUMIFS(Tabla1[Avance_Med],Tabla1[Fecha],">="&$A12,Tabla1[Fecha],"<="&EOMONTH($A12,0),Tabla1[Codigo_actividad],E$2) -> 0 | F12: =+SUMIFS(Tabla1[Avance_Med],Tabla1[Fecha],">="&$A12,Tabla1[Fecha],"<="&EOMONTH($A12,0),Tabla1[Codigo_actividad],F$2) -> 0 | G12: =+SUMIFS(Tabla1[Avance_Med],Tabla1[Fecha],">="&$A12,Tabla1[Fecha],"<="&EOMONTH($A12,0),Tabla1[Codigo_actividad],G$2) -> 0 | H12: =+SUMIFS(Tabla1[Avance_km],Tabla1[Fecha],">="&$A12,Tabla1[Fecha],"<="&EOMONTH($A12,0),Tabla1[nombre_actividad],H$3) -> 11.253 | J12: =+SUMIFS(Tabla1[Avance_km],Tabla1[Fecha],">="&$A12,Tabla1[Fecha],"<="&EOMONTH($A12,0),Tabla1[nombre_actividad],$J$3,Tabla1[Avance_km],">0") -> 19.906 | L12: =+SUMIFS(Tabla1[Avance_Med],Tabla1[Fecha],">="&$A12,Tabla1[Fecha],"<="&EOMONTH($A12,0),Tabla1[Codigo_actividad],L$2) -> 0 | M12: =+SUMIFS(Tabla1[Avance_km],Tabla1[Fecha],">="&$A12,Tabla1[Fecha],"<="&EOMONTH($A12,0),Tabla1[nombre_actividad],$M$3) -> 3.627 | N12: =+SUMIFS(Tabla1[Avance_Med],Tabla1[Fecha],">="&$A12,Tabla1[Fecha],"<="&EOMONTH($A12,0),Tabla1[Codigo_actividad],N$2) -> 0 | O12: =+SUMIFS(Tabla1[Avance_Med],Tabla1[Fecha],">="&$A12,Tabla1[Fecha],"<="&EOMONTH($A12,0),Tabla1[Codigo_actividad],O$2) -> 0 | P12: =+SUMIFS(Tabla1[Avance_Med],Tabla1[Fecha],">="&$A12,Tabla1[Fecha],"<="&EOMONTH($A12,0),Tabla1[Codigo_actividad],P$2) -> 0 | R12: =+SUMPRODUCT(B12:P12,$B$1:$P$1) -> 441435.46
A13: 46174 | B13: =+SUMIFS(Tabla1[Avance_Med],Tabla1[Fecha],">="&$A13,Tabla1[Fecha],"<="&EOMONTH($A13,0),Tabla1[Codigo_actividad],B$2) -> 0 | C13: =+SUMIFS(Tabla1[Avance_Med],Tabla1[Fecha],">="&$A13,Tabla1[Fecha],"<="&EOMONTH($A13,0),Tabla1[Codigo_actividad],C$2) -> 0 | D13: =+SUMIFS(Tabla1[Avance_Med],Tabla1[Fecha],">="&$A13,Tabla1[Fecha],"<="&EOMONTH($A13,0),Tabla1[Codigo_actividad],D$2) -> 0 | E13: =+SUMIFS(Tabla1[Avance_Med],Tabla1[Fecha],">="&$A13,Tabla1[Fecha],"<="&EOMONTH($A13,0),Tabla1[Codigo_actividad],E$2) -> 0 | F13: =+SUMIFS(Tabla1[Avance_Med],Tabla1[Fecha],">="&$A13,Tabla1[Fecha],"<="&EOMONTH($A13,0),Tabla1[Codigo_actividad],F$2) -> 0 | G13: =+SUMIFS(Tabla1[Avance_Med],Tabla1[Fecha],">="&$A13,Tabla1[Fecha],"<="&EOMONTH($A13,0),Tabla1[Codigo_actividad],G$2) -> 0 | H13: =+SUMIFS(Tabla1[Avance_km],Tabla1[Fecha],">="&$A13,Tabla1[Fecha],"<="&EOMONTH($A13,0),Tabla1[nombre_actividad],H$3) -> 20.328 | J13: =+SUMIFS(Tabla1[Avance_km],Tabla1[Fecha],">="&$A13,Tabla1[Fecha],"<="&EOMONTH($A13,0),Tabla1[nombre_actividad],$J$3,Tabla1[Avance_km],">0") -> 0 | L13: =+SUMIFS(Tabla1[Avance_Med],Tabla1[Fecha],">="&$A13,Tabla1[Fecha],"<="&EOMONTH($A13,0),Tabla1[Codigo_actividad],L$2) -> 0 | M13: =+SUMIFS(Tabla1[Avance_km],Tabla1[Fecha],">="&$A13,Tabla1[Fecha],"<="&EOMONTH($A13,0),Tabla1[nombre_actividad],$M$3) -> 5.417 | N13: =+SUMIFS(Tabla1[Avance_Med],Tabla1[Fecha],">="&$A13,Tabla1[Fecha],"<="&EOMONTH($A13,0),Tabla1[Codigo_actividad],N$2) -> 0 | O13: =+SUMIFS(Tabla1[Avance_Med],Tabla1[Fecha],">="&$A13,Tabla1[Fecha],"<="&EOMONTH($A13,0),Tabla1[Codigo_actividad],O$2) -> 0 | P13: =+SUMIFS(Tabla1[Avance_Med],Tabla1[Fecha],">="&$A13,Tabla1[Fecha],"<="&EOMONTH($A13,0),Tabla1[Codigo_actividad],P$2) -> 0 | R13: =+SUMPRODUCT(B13:P13,$B$1:$P$1) -> 307419.67
A14: 46204 | B14: =+SUMIFS(Tabla1[Avance_Med],Tabla1[Fecha],">="&$A14,Tabla1[Fecha],"<="&EOMONTH($A14,0),Tabla1[Codigo_actividad],B$2) -> 0 | C14: =+SUMIFS(Tabla1[Avance_Med],Tabla1[Fecha],">="&$A14,Tabla1[Fecha],"<="&EOMONTH($A14,0),Tabla1[Codigo_actividad],C$2) -> 0 | D14: =+SUMIFS(Tabla1[Avance_Med],Tabla1[Fecha],">="&$A14,Tabla1[Fecha],"<="&EOMONTH($A14,0),Tabla1[Codigo_actividad],D$2) -> 0 | E14: =+SUMIFS(Tabla1[Avance_Med],Tabla1[Fecha],">="&$A14,Tabla1[Fecha],"<="&EOMONTH($A14,0),Tabla1[Codigo_actividad],E$2) -> 0 | F14: =+SUMIFS(Tabla1[Avance_Med],Tabla1[Fecha],">="&$A14,Tabla1[Fecha],"<="&EOMONTH($A14,0),Tabla1[Codigo_actividad],F$2) -> 0 | G14: =+SUMIFS(Tabla1[Avance_Med],Tabla1[Fecha],">="&$A14,Tabla1[Fecha],"<="&EOMONTH($A14,0),Tabla1[Codigo_actividad],G$2) -> 0 | H14: =+SUMIFS(Tabla1[Avance_km],Tabla1[Fecha],">="&$A14,Tabla1[Fecha],"<="&EOMONTH($A14,0),Tabla1[nombre_actividad],H$3) -> 13.568 | J14: =+SUMIFS(Tabla1[Avance_km],Tabla1[Fecha],">="&$A14,Tabla1[Fecha],"<="&EOMONTH($A14,0),Tabla1[nombre_actividad],$J$3,Tabla1[Avance_km],">0") -> 10.538 | L14: =+SUMIFS(Tabla1[Avance_Med],Tabla1[Fecha],">="&$A14,Tabla1[Fecha],"<="&EOMONTH($A14,0),Tabla1[Codigo_actividad],L$2) -> 0 | M14: =+SUMIFS(Tabla1[Avance_km],Tabla1[Fecha],">="&$A14,Tabla1[Fecha],"<="&EOMONTH($A14,0),Tabla1[nombre_actividad],$M$3) -> 13.835 | N14: =+SUMIFS(Tabla1[Avance_Med],Tabla1[Fecha],">="&$A14,Tabla1[Fecha],"<="&EOMONTH($A14,0),Tabla1[Codigo_actividad],N$2) -> 0 | O14: =+SUMIFS(Tabla1[Avance_Med],Tabla1[Fecha],">="&$A14,Tabla1[Fecha],"<="&EOMONTH($A14,0),Tabla1[Codigo_actividad],O$2) -> 0 | P14: =+SUMIFS(Tabla1[Avance_Med],Tabla1[Fecha],">="&$A14,Tabla1[Fecha],"<="&EOMONTH($A14,0),Tabla1[Codigo_actividad],P$2) -> 0 | R14: =+SUMPRODUCT(B14:P14,$B$1:$P$1) -> 371107.13
A15: 46235 | B15: =+SUMIFS(Tabla1[Avance_Med],Tabla1[Fecha],">="&$A15,Tabla1[Fecha],"<="&EOMONTH($A15,0),Tabla1[Codigo_actividad],B$2) -> 0 | C15: =+SUMIFS(Tabla1[Avance_Med],Tabla1[Fecha],">="&$A15,Tabla1[Fecha],"<="&EOMONTH($A15,0),Tabla1[Codigo_actividad],C$2) -> 0 | D15: =+SUMIFS(Tabla1[Avance_Med],Tabla1[Fecha],">="&$A15,Tabla1[Fecha],"<="&EOMONTH($A15,0),Tabla1[Codigo_actividad],D$2) -> 0 | E15: =+SUMIFS(Tabla1[Avance_Med],Tabla1[Fecha],">="&$A15,Tabla1[Fecha],"<="&EOMONTH($A15,0),Tabla1[Codigo_actividad],E$2) -> 0 | F15: =+SUMIFS(Tabla1[Avance_Med],Tabla1[Fecha],">="&$A15,Tabla1[Fecha],"<="&EOMONTH($A15,0),Tabla1[Codigo_actividad],F$2) -> 0 | G15: =+SUMIFS(Tabla1[Avance_Med],Tabla1[Fecha],">="&$A15,Tabla1[Fecha],"<="&EOMONTH($A15,0),Tabla1[Codigo_actividad],G$2) -> 0 | H15: =+SUMIFS(Tabla1[Avance_km],Tabla1[Fecha],">="&$A15,Tabla1[Fecha],"<="&EOMONTH($A15,0),Tabla1[nombre_actividad],H$3) -> 10.033 | J15: =+SUMIFS(Tabla1[Avance_km],Tabla1[Fecha],">="&$A15,Tabla1[Fecha],"<="&EOMONTH($A15,0),Tabla1[nombre_actividad],$J$3,Tabla1[Avance_km],">0") -> 12.395 | L15: =+SUMIFS(Tabla1[Avance_Med],Tabla1[Fecha],">="&$A15,Tabla1[Fecha],"<="&EOMONTH($A15,0),Tabla1[Codigo_actividad],L$2) -> 0 | M15: =+SUMIFS(Tabla1[Avance_km],Tabla1[Fecha],">="&$A15,Tabla1[Fecha],"<="&EOMONTH($A15,0),Tabla1[nombre_actividad],$M$3) -> 12.17 | N15: =+SUMIFS(Tabla1[Avance_Med],Tabla1[Fecha],">="&$A15,Tabla1[Fecha],"<="&EOMONTH($A15,0),Tabla1[Codigo_actividad],N$2) -> 0 | O15: =+SUMIFS(Tabla1[Avance_Med],Tabla1[Fecha],">="&$A15,Tabla1[Fecha],"<="&EOMONTH($A15,0),Tabla1[Codigo_actividad],O$2) -> 0 | P15: =+SUMIFS(Tabla1[Avance_Med],Tabla1[Fecha],">="&$A15,Tabla1[Fecha],"<="&EOMONTH($A15,0),Tabla1[Codigo_actividad],P$2) -> 0 | R15: =+SUMPRODUCT(B15:P15,$B$1:$P$1) -> 341188.14
A16: 46266 | B16: =+SUMIFS(Tabla1[Avance_Med],Tabla1[Fecha],">="&$A16,Tabla1[Fecha],"<="&EOMONTH($A16,0),Tabla1[Codigo_actividad],B$2) -> 0 | C16: =+SUMIFS(Tabla1[Avance_Med],Tabla1[Fecha],">="&$A16,Tabla1[Fecha],"<="&EOMONTH($A16,0),Tabla1[Codigo_actividad],C$2) -> 0 | D16: =+SUMIFS(Tabla1[Avance_Med],Tabla1[Fecha],">="&$A16,Tabla1[Fecha],"<="&EOMONTH($A16,0),Tabla1[Codigo_actividad],D$2) -> 0 | E16: =+SUMIFS(Tabla1[Avance_Med],Tabla1[Fecha],">="&$A16,Tabla1[Fecha],"<="&EOMONTH($A16,0),Tabla1[Codigo_actividad],E$2) -> 0 | F16: =+SUMIFS(Tabla1[Avance_Med],Tabla1[Fecha],">="&$A16,Tabla1[Fecha],"<="&EOMONTH($A16,0),Tabla1[Codigo_actividad],F$2) -> 0 | G16: =+SUMIFS(Tabla1[Avance_Med],Tabla1[Fecha],">="&$A16,Tabla1[Fecha],"<="&EOMONTH($A16,0),Tabla1[Codigo_actividad],G$2) -> 0 | H16: =+SUMIFS(Tabla1[Avance_km],Tabla1[Fecha],">="&$A16,Tabla1[Fecha],"<="&EOMONTH($A16,0),Tabla1[nombre_actividad],H$3) -> 10.72 | J16: =+SUMIFS(Tabla1[Avance_km],Tabla1[Fecha],">="&$A16,Tabla1[Fecha],"<="&EOMONTH($A16,0),Tabla1[nombre_actividad],$J$3,Tabla1[Avance_km],">0") -> 0 | L16: =+SUMIFS(Tabla1[Avance_Med],Tabla1[Fecha],">="&$A16,Tabla1[Fecha],"<="&EOMONTH($A16,0),Tabla1[Codigo_actividad],L$2) -> 20 | M16: =+SUMIFS(Tabla1[Avance_km],Tabla1[Fecha],">="&$A16,Tabla1[Fecha],"<="&EOMONTH($A16,0),Tabla1[nombre_actividad],$M$3) -> 20.07 | N16: =+SUMIFS(Tabla1[Avance_Med],Tabla1[Fecha],">="&$A16,Tabla1[Fecha],"<="&EOMONTH($A16,0),Tabla1[Codigo_actividad],N$2) -> 34 | O16: =+SUMIFS(Tabla1[Avance_Med],Tabla1[Fecha],">="&$A16,Tabla1[Fecha],"<="&EOMONTH($A16,0),Tabla1[Codigo_actividad],O$2) -> 34 | P16: =+SUMIFS(Tabla1[Avance_Med],Tabla1[Fecha],">="&$A16,Tabla1[Fecha],"<="&EOMONTH($A16,0),Tabla1[Codigo_actividad],P$2) -> 34 | R16: =+SUMPRODUCT(B16:P16,$B$1:$P$1) -> 571475.63
... A19: 46357 | B19: =+SUMIFS(Tabla1[Avance_Med],Tabla1[Fecha],">="&$A19,Tabla1[Fecha],"<="&EOMONTH($A19,0),Tabla1[Codigo_actividad],B$2) -> 0 | C19: =+SUMIFS(Tabla1[Avance_Med],Tabla1[Fecha],">="&$A19,Tabla1[Fecha],"<="&EOMONTH($A19,0),Tabla1[Codigo_actividad],C$2) -> 0 | D19: =+SUMIFS(Tabla1[Avance_Med],Tabla1[Fecha],">="&$A19,Tabla1[Fecha],"<="&EOMONTH($A19,0),Tabla1[Codigo_actividad],D$2) -> 0 | E19: =+SUMIFS(Tabla1[Avance_Med],Tabla1[Fecha],">="&$A19,Tabla1[Fecha],"<="&EOMONTH($A19,0),Tabla1[Codigo_actividad],E$2) -> 0 | F19: =+SUMIFS(Tabla1[Avance_Med],Tabla1[Fecha],">="&$A19,Tabla1[Fecha],"<="&EOMONTH($A19,0),Tabla1[Codigo_actividad],F$2) -> 0 | G19: =+SUMIFS(Tabla1[Avance_Med],Tabla1[Fecha],">="&$A19,Tabla1[Fecha],"<="&EOMONTH($A19,0),Tabla1[Codigo_actividad],G$2) -> 0 | H19: =+SUMIFS(Tabla1[Avance_km],Tabla1[Fecha],">="&$A19,Tabla1[Fecha],"<="&EOMONTH($A19,0),Tabla1[nombre_actividad],H$3) -> 0 | J19: =+SUMIFS(Tabla1[Avance_km],Tabla1[Fecha],">="&$A19,Tabla1[Fecha],"<="&EOMONTH($A19,0),Tabla1[nombre_actividad],$J$3,Tabla1[Avance_km],">0") -> 0 | L19: =+SUMIFS(Tabla1[Avance_Med],Tabla1[Fecha],">="&$A19,Tabla1[Fecha],"<="&EOMONTH($A19,0),Tabla1[Codigo_actividad],L$2) -> 0 | M19: =+SUMIFS(Tabla1[Avance_km],Tabla1[Fecha],">="&$A19,Tabla1[Fecha],"<="&EOMONTH($A19,0),Tabla1[nombre_actividad],$M$3) -> 0 | N19: =+SUMIFS(Tabla1[Avance_Med],Tabla1[Fecha],">="&$A19,Tabla1[Fecha],"<="&EOMONTH($A19,0),Tabla1[Codigo_actividad],N$2) -> 0 | O19: =+SUMIFS(Tabla1[Avance_Med],Tabla1[Fecha],">="&$A19,Tabla1[Fecha],"<="&EOMONTH($A19,0),Tabla1[Codigo_actividad],O$2) -> 0 | P19: =+SUMIFS(Tabla1[Avance_Med],Tabla1[Fecha],">="&$A19,Tabla1[Fecha],"<="&EOMONTH($A19,0),Tabla1[Codigo_actividad],P$2) -> 0 | R19: =+SUMPRODUCT(B19:P19,$B$1:$P$1) -> 0
A20: Por ejecutar | B20: =SUM(B4:B19) -> 116 | C20: =SUM(C4:C19) -> 116 | D20: =SUM(D4:D19) -> 116 | E20: =SUM(E4:E19) -> 116 | F20: =SUM(F4:F19) -> 116 | G20: =SUM(G4:G19) -> 116 | H20: =SUM(H4:H19) -> 181.9255 | I20: =SUM(I4:I19) -> 0 | ... O20: =SUM(O4:O19) -> 92 | R20: =SUM(R4:R19) -> -2230810.9 | S20: =+R4-R20 -> -8932111 | T20: =$S$20/$R$4 -> 0.80015887

Sheet Catalogo
C1: Catálogo de conceptos: Regional DGQ / Evaluación directa por corrosión externa (ECDA) bajo el estándar practico SP0502-2010 (AMPP) en el total de red de distribucion de la regional DGQ en una longitud de 200 kilometros de red en direferentes diametros (10", 8", 6", 4", 3" y 2").
B3: Nombre del Proveedor | D3: PROYECTO:
D4: ECDA DGQ
B5: POSICIÓN | C5: DESCRIPCIÓN BREVE | D5: CANTIDAD | E5: UNIDAD DE MEDIDA (UM) | F5: PRECIO UNITARIO | G5: SUBTOTAL | H5: MONEDA
B6: 1 | C6: ETAPA 1 | G6: =SUM(G7:G12) -> 1246944.3 | K6: S01 | L6: S02 | M6: S03 | N6: S04 | O6: S06 | P6: S07 | Q6: S08 | T6: Rest en la OC
A7: MXN_010 | B7: 1.1 | C7: Recopilación de Información | D7: 105 | E7: DUCTO | F7: 2532.81 | G7: =+F7*R7 -> 293805.96 | H7: MXN | I7: RECOPILACION | K7: 37 | L7: 17 | M7: 40 | N7: 4 | O7: 13 | P7: 3 | Q7: 2 | R7: =SUM(K7:Q7) -> 116 | S7: =+D7*0.9 -> 94.5 | T7: =+D7-S7-(R7-S7) -> -11 | U7: =+R7/105 -> 1.1047619
A8: MXN_020 | B8: 1.2 | C8: Análisis de Información | D8: 105 | E8: DUCTO | F8: 3250.01 | G8: =+F8*R8 -> 377001.16 | H8: MXN | I8: ANALISIS | K8: 37 | L8: 17 | M8: 40 | N8: 4 | O8: 13 | P8: 3 | Q8: 2 | R8: =SUM(K8:Q8) -> 116 | S8: =+D8*0.9 -> 94.5 | T8: =+D8-S8-(R8-S8) -> -11
A9: MXN_030 | B9: 1.3 | C9: Evaluación de factibilidad de ECDA | D9: 105 | E9: DUCTO | F9: 985.32 | G9: =+F9*R9 -> 114297.12 | H9: MXN | I9: FACTIBILIDAD | K9: 37 | L9: 17 | M9: 40 | N9: 4 | O9: 13 | P9: 3 | Q9: 2 | R9: =SUM(K9:Q9) -> 116 | S9: =+D9*0.9 -> 94.5 | T9: =+D9-S9-(R9-S9) -> -11
A10: MXN_040 | B10: 1.4 | C10: Selección de técnicas de inspección indirecta | D10: 105 | E10: DUCTO | F10: 1062.92 | G10: =+F10*R10 -> 123298.72 | H10: MXN | I10: SELECCIÓN HERRAMIENTAS | K10: 37 | L10: 17 | M10: 40 | N10: 4 | O10: 13 | P10: 3 | Q10: 2 | R10: =SUM(K10:Q10) -> 116 | S10: =+D10*0.9 -> 94.5 | T10: =+D10-S10-(R10-S10) -> -11
A11: MXN_050 | B11: 1.5 | C11: Definición de zonas ECDA | D11: 105 | E11: DUCTO | F11: 1337.25 | G11: =+F11*R11 -> 155121 | H11: MXN | I11: REGIONES ECDA | K11: 37 | L11: 17 | M11: 40 | N11: 4 | O11: 13 | P11: 3 | Q11: 2 | R11: =SUM(K11:Q11) -> 116 | S11: =+D11*0.9 -> 94.5 | T11: =+D11-S11-(R11-S11) -> -11
A12: MXN_060 | B12: 1.6 | C12: Reporte final entregable (con resultados, diagnosticos, hallazgos, recomendaciones y conclusiones). Esta partida puede reducir en funcion de la cantidad de ductos principales. | D12: 105 | E12: DUCTO | F12: 1581.21 | G12: =+F12*R12 -> 183420.36 | H12: MXN | I12: REPORTE E1 | K12: 37 | L12: 17 | M12: 40 | N12: 4 | O12: 13 | P12: 3 | Q12: 2 | R12: =SUM(K12:Q12) -> 116 | S12: =+D12*0.9 -> 94.5 | T12: =+D12-S12-(R12-S12) -> -11
B13: 2 | C13: ETAPA 2 | F13: Subtotal | G13: =SUM(G14:G21) -> 7609035.6
A14: MXN_070 | B14: 2.1 | C14: Estudio de potencial a intervalos cortos (Close Interval Potential Survey-CIPS). | D14: 200 | E14: KM | F14: 14521.41 | G14: =+F14*R14 -> 2641814.8 | H14: MXN | I14: CIPS | J14: 7800 | K14: =+SUM('Summary S01'!I2:I41) -> 66.918 | L14: =+SUM('Summary S02'!I2:I18) -> 32.988 | M14: =+SUM('Summary S03'!I2:I45) -> 44.52 | N14: =+SUM('Summary S04'!I2:I6) -> 35.875 | O14: =+SUM('Summary S06'!I2:I13) -> 1.6245 | P14: =+SUM('Summary S07'!I2:I4) -> 0 | Q14: =+SUM('Summary S08'!I2:I3) -> 0 | R14: =SUM(K14:Q14) -> 181.9255 | S14: =+D14*0.7 -> 140 | T14: =+D14-S14-(R14-S14) -> 18.0745
A15: MXN_080 | B15: 2.2 | C15: Estudio Gradiente de Voltaje de Corriente Alterna (ACVG). | D15: 200 | E15: KM | F15: 13555.63 | G15: =+F15*R15 -> 0 | H15: MXN | I15: ACVG | J15: 8200
A16: MXN_090 | B16: 2.3 | C16: Estudio Gradiente de Voltaje de Corriente Directa (DCVG). | D16: 200 | E16: KM | F16: 13555.63 | G16: =+F16*R16 -> 2037743.3 | H16: MXN | I16: DCVG | J16: 8200 | K16: =+SUM('Summary S01'!J2:J41) -> 66.918 | L16: =+SUM('Summary S02'!J2:J18) -> 32.988 | M16: =+SUM('Summary S03'!J2:J45) -> 45.672 | N16: =+SUM('Summary S04'!J2:J6) -> 3.122 | O16: =+SUM('Summary S06'!J2:J13) -> 1.6245 | P16: =+SUM('Summary S07'!J2:J4) -> 0 | Q16: =+SUM('Summary S08'!J2:J3) -> 0 | R16: =SUM(K16:Q16) -> 150.3245 | S16: =+D16*0.7 -> 140 | T16: =+D16-S16-(R16-S16) -> 49.6755
A17: MXN_100 | B17: 2.4 | C17: Mapeo de corriente PCM | D17: 200 | E17: KM | F17: 13696.28 | G17: =+F17*R17 -> 0 | H17: MXN | I17: PCM | J17: 6780
A18: MXN_110 | B18: 2.5 | C18: Levantamiento de resistividad pH y bacterias a lo largo de la trayectoria del ducto a cada 500 m Incluye mano de obra, kits y equipo | D18: 500 | E18: SERVICIOS | F18: 4658 | G18: =+F18*R18 -> 1844568 | H18: MXN | I18: Resistividades pH BSR BPA | J18: 4230 | K18: =+SUM('Summary S01'!K2:K41) -> 156 | L18: =+SUM('Summary S02'!K2:K18) -> 73 | M18: =+SUM('Summary S03'!K2:K45) -> 129 | N18: =+SUM('Summary S04'!K2:K6) -> 10 | O18: =+SUM('Summary S06'!K2:K13) -> 14 | P18: =+SUM('Summary S07'!K2:K4) -> 5 | Q18: =+SUM('Summary S08'!K2:K3) -> 9 | R18: =SUM(K18:Q18) -> 396 | S18: =+D18*0.7 -> 350 | T18: =+D18-S18-(R18-S18) -> 104
A19: MXN_120 | B19: 2.6 | C19: Localización de Ducto. | D19: 200 | E19: KM | F19: 2257.42 | G19: =+F19*R19 -> 410591.97 | H19: MXN | I19: Localizacion | J19: 1600 | K19: =+SUM('Summary S01'!H2:H41) -> 66.918 | L19: =+SUM('Summary S02'!H2:H18) -> 32.988 | M19: =+SUM('Summary S03'!H2:H45) -> 45.014 | N19: =+SUM('Summary S04'!H2:H6) -> 35.341 | O19: =+SUM('Summary S06'!H2:H13) -> 1.6245 | P19: =+SUM('Summary S07'!H2:H4) -> 0 | Q19: =+SUM('Summary S08'!H2:H3) -> 0 | R19: =SUM(K19:Q19) -> 181.8855 | S19: =+D19*0.7 -> 140 | T19: =+D19-S19-(R19-S19) -> 18.1145
A20: MXN_130 | B20: 2.7 | C20: Definir y clasificar la severidad de indicaciones | D20: 105 | E20: DUCTO | F20: 3540.12 | G20: =+F20*R20 -> 385873.08 | H20: MXN | I20: SEVERIDAD | J20: 2200 | K20: 37 | L20: 17 | M20: 34 | N20: 4 | O20: 12 | P20: 3 | Q20: 2 | R20: =SUM(K20:Q20) -> 109 | S20: =+D20*0.7 -> 73.5 | T20: =+D20-S20-(R20-S20) -> -4
A21: MXN_140 | B21: 2.8 | C21: Reporte final entregable (con resultados, diagnosticos, hallazgos, recomendaciones y conclusiones). Esta partida puede reducir en funcion de la cantidad de ductos principales. | D21: 105 | E21: DUCTO | F21: 2646.28 | G21: =+F21*R21 -> 288444.52 | H21: MXN | I21: REPORTE E2 | K21: 37 | L21: 17 | M21: 34 | N21: 4 | O21: 12 | P21: 3 | Q21: 2 | R21: =SUM(K21:Q21) -> 109 | S21: =+D21*0.7 -> 73.5 | T21: =+D21-S21-(R21-S21) -> -4
B22: 3 | C22: ETAPA 3 | F22: Subtotal | G22: =SUM(G23:G35) -> 214800.85
A23: MXN_150 | B23: 3.1 | C23: Selección y priorización de indicaciones para examinación directa | D23: 105 | E23: DUCTOS | F23: 1970.65 | G23: =+F23*R23 -> 214800.85 | H23: MXN | I23: PRIORIZACION | K23: 37 | L23: 17 | M23: 34 | N23: 4 | O23: 12 | P23: 3 | Q23: 2 | R23: =SUM(K23:Q23) -> 109
A24: MXN_160 | B24: 3.2 | C24: Recopilación de datos en la excavación | D24: 55 | E24: VERIFICACIONES | F24: 7585.99 | G24: 0 | H24: MXN | I24: DATA EXC | K24: =+SUMIFS(Tabla1[Avance_Med],Tabla1[nombre_actividad],$I24,Tabla1[Sistema],"LIRA_GALERAS") -> 11 | L24: =+SUMIFS(Tabla1[Avance_Med],Tabla1[nombre_actividad],$I24,Tabla1[Sistema],"PECO_AGROS") -> 3 | M24: =+SUMIFS(Tabla1[Avance_Med],Tabla1[nombre_actividad],$I24,Tabla1[Sistema],"HUIMILPAN") -> 0 | N24: =+SUMIFS(Tabla1[Avance_Med],Tabla1[nombre_actividad],$I24,Tabla1[Sistema],"BUENAVISTA") -> 0 | O24: =+SUMIFS(Tabla1[Avance_Med],Tabla1[nombre_actividad],$I24,Tabla1[Sistema],"SAN JUAN DEL RIO") -> 1 | P24: =+SUMIFS(Tabla1[Avance_Med],Tabla1[nombre_actividad],$I24,Tabla1[Sistema],"GIVAUDAN") -> 0 | Q24: =+SUMIFS(Tabla1[Avance_Med],Tabla1[nombre_actividad],$I24,Tabla1[Sistema],"SAN_GIL") -> 0
B25: 3.3 | C25: Evaluacion de la inspeccion en campo mediante ensayos no destructivos: | M25: =+SUMIFS(Tabla1[Avance_Med],Tabla1[nombre_actividad],$I25,Tabla1[Sistema],"HUIMILPAN") -> 0 | N25: =+SUMIFS(Tabla1[Avance_Med],Tabla1[nombre_actividad],$I25,Tabla1[Sistema],"BUENAVISTA") -> 0 | O25: =+SUMIFS(Tabla1[Avance_Med],Tabla1[nombre_actividad],$I25,Tabla1[Sistema],"SAN JUAN DEL RIO") -> 0 | P25: =+SUMIFS(Tabla1[Avance_Med],Tabla1[nombre_actividad],$I25,Tabla1[Sistema],"GIVAUDAN") -> 0 | Q25: =+SUMIFS(Tabla1[Avance_Med],Tabla1[nombre_actividad],$I25,Tabla1[Sistema],"SAN_GIL") -> 0
A26: MXN_170 | B26: 3.3.1 | C26: Inspeccion visual | D26: 55 | E26: VERIFICACIONES | F26: 1765.59 | G26: 0 | H26: MXN | I26: VT | K26: =+SUMIFS(Tabla1[Avance_Med],Tabla1[nombre_actividad],$I26,Tabla1[Sistema],"LIRA_GALERAS") -> 11 | L26: =+SUMIFS(Tabla1[Avance_Med],Tabla1[nombre_actividad],$I26,Tabla1[Sistema],"PECO_AGROS") -> 3 | M26: =+SUMIFS(Tabla1[Avance_Med],Tabla1[nombre_actividad],$I26,Tabla1[Sistema],"HUIMILPAN") -> 0 | N26: =+SUMIFS(Tabla1[Avance_Med],Tabla1[nombre_actividad],$I26,Tabla1[Sistema],"BUENAVISTA") -> 1 | O26: =+SUMIFS(Tabla1[Avance_Med],Tabla1[nombre_actividad],$I26,Tabla1[Sistema],"SAN JUAN DEL RIO") -> 1 | P26: =+SUMIFS(Tabla1[Avance_Med],Tabla1[nombre_actividad],$I26,Tabla1[Sistema],"GIVAUDAN") -> 0 | Q26: =+SUMIFS(Tabla1[Avance_Med],Tabla1[nombre_actividad],$I26,Tabla1[Sistema],"SAN_GIL") -> 0
A27: MXN_180 | B27: 3.3.2 | C27: Evaluacion de sanidad y medicion de espesores | D27: 100 | E27: SERVICIO | F27: 1934.59 | G27: 0 | H27: MXN | I27: SANIDAD Y ESPESORES | K27: =+SUMIFS(Tabla1[Avance_Med],Tabla1[nombre_actividad],$I27,Tabla1[Sistema],"LIRA_GALERAS") -> 11 | L27: =+SUMIFS(Tabla1[Avance_Med],Tabla1[nombre_actividad],$I27,Tabla1[Sistema],"PECO_AGROS") -> 3 | M27: =+SUMIFS(Tabla1[Avance_Med],Tabla1[nombre_actividad],$I27,Tabla1[Sistema],"HUIMILPAN") -> 0 | N27: =+SUMIFS(Tabla1[Avance_Med],Tabla1[nombre_actividad],$I27,Tabla1[Sistema],"BUENAVISTA") -> 1 | O27: =+SUMIFS(Tabla1[Avance_Med],Tabla1[nombre_actividad],$I27,Tabla1[Sistema],"SAN JUAN DEL RIO") -> 1 | P27: =+SUMIFS(Tabla1[Avance_Med],Tabla1[nombre_actividad],$I27,Tabla1[Sistema],"GIVAUDAN") -> 0 | Q27: =+SUMIFS(Tabla1[Avance_Med],Tabla1[nombre_actividad],$I27,Tabla1[Sistema],"SAN_GIL") -> 0
A28: MXN_190 | B28: 3.3.3 | C28: Caracterizacion de tuberia | D28: 100 | E28: SERVICIO | F28: 1960.59 | G28: 0 | H28: MXN | I28: CARACTERIZACION | K28: =+SUMIFS(Tabla1[Avance_Med],Tabla1[nombre_actividad],$I28,Tabla1[Sistema],"LIRA_GALERAS") -> 11 | L28: =+SUMIFS(Tabla1[Avance_Med],Tabla1[nombre_actividad],$I28,Tabla1[Sistema],"PECO_AGROS") -> 3 | M28: =+SUMIFS(Tabla1[Avance_Med],Tabla1[nombre_actividad],$I28,Tabla1[Sistema],"HUIMILPAN") -> 0 | N28: =+SUMIFS(Tabla1[Avance_Med],Tabla1[nombre_actividad],$I28,Tabla1[Sistema],"BUENAVISTA") -> 1 | O28: =+SUMIFS(Tabla1[Avance_Med],Tabla1[nombre_actividad],$I28,Tabla1[Sistema],"SAN JUAN DEL RIO") -> 1 | P28: =+SUMIFS(Tabla1[Avance_Med],Tabla1[nombre_actividad],$I28,Tabla1[Sistema],"GIVAUDAN") -> 0 | Q28: =+SUMIFS(Tabla1[Avance_Med],Tabla1[nombre_actividad],$I28,Tabla1[Sistema],"SAN_GIL") -> 0
A29: MXN_200 | B29: 3.3.4 | C29: Evaluacion de soldadura con haz angular | D29: 170 | E29: SERVICIO | F29: 2220.59 | G29: 0 | H29: MXN | I29: UTPA | K29: =+SUMIFS(Tabla1[Avance_Med],Tabla1[nombre_actividad],$I29,Tabla1[Sistema],"LIRA_GALERAS") -> 0 | L29: =+SUMIFS(Tabla1[Avance_Med],Tabla1[nombre_actividad],$I29,Tabla1[Sistema],"PECO_AGROS") -> 2 | M29: =+SUMIFS(Tabla1[Avance_Med],Tabla1[nombre_actividad],$I29,Tabla1[Sistema],"HUIMILPAN") -> 0 | N29: =+SUMIFS(Tabla1[Avance_Med],Tabla1[nombre_actividad],$I29,Tabla1[Sistema],"BUENAVISTA") -> 0 | O29: =+SUMIFS(Tabla1[Avance_Med],Tabla1[nombre_actividad],$I29,Tabla1[Sistema],"SAN JUAN DEL RIO") -> 0 | P29: =+SUMIFS(Tabla1[Avance_Med],Tabla1[nombre_actividad],$I29,Tabla1[Sistema],"GIVAUDAN") -> 0 | Q29: =+SUMIFS(Tabla1[Avance_Med],Tabla1[nombre_actividad],$I29,Tabla1[Sistema],"SAN_GIL") -> 0
A30: MXN_210 | B30: 3.3.5 | C30: Inspección de ultrasonido de haz recto | D30: 170 | E30: SERVICIO | F30: 2220.59 | G30: 0 | H30: MXN | I30: UT RECTO | K30: =+SUMIFS(Tabla1[Avance_Med],Tabla1[nombre_actividad],$I30,Tabla1[Sistema],"LIRA_GALERAS") -> 11 | L30: =+SUMIFS(Tabla1[Avance_Med],Tabla1[nombre_actividad],$I30,Tabla1[Sistema],"PECO_AGROS") -> 3 | M30: =+SUMIFS(Tabla1[Avance_Med],Tabla1[nombre_actividad],$I30,Tabla1[Sistema],"HUIMILPAN") -> 0 | N30: =+SUMIFS(Tabla1[Avance_Med],Tabla1[nombre_actividad],$I30,Tabla1[Sistema],"BUENAVISTA") -> 1 | O30: =+SUMIFS(Tabla1[Avance_Med],Tabla1[nombre_actividad],$I30,Tabla1[Sistema],"SAN JUAN DEL RIO") -> 1 | P30: =+SUMIFS(Tabla1[Avance_Med],Tabla1[nombre_actividad],$I30,Tabla1[Sistema],"GIVAUDAN") -> 0 | Q30: =+SUMIFS(Tabla1[Avance_Med],Tabla1[nombre_actividad],$I30,Tabla1[Sistema],"SAN_GIL") -> 0
A31: MXN_220 | B31: 3.3.6 | C31: Inspección con particulas magneticas | D31: 100 | E31: SERVICIO | F31: 2090.59 | G31: 0 | H31: MXN | I31: MT | K31: =+SUMIFS(Tabla1[Avance_Med],Tabla1[nombre_actividad],$I31,Tabla1[Sistema],"LIRA_GALERAS") -> 0 | L31: =+SUMIFS(Tabla1[Avance_Med],Tabla1[nombre_actividad],$I31,Tabla1[Sistema],"PECO_AGROS") -> 2 | M31: =+SUMIFS(Tabla1[Avance_Med],Tabla1[nombre_actividad],$I31,Tabla1[Sistema],"HUIMILPAN") -> 0 | N31: =+SUMIFS(Tabla1[Avance_Med],Tabla1[nombre_actividad],$I31,Tabla1[Sistema],"BUENAVISTA") -> 0 | O31: =+SUMIFS(Tabla1[Avance_Med],Tabla1[nombre_actividad],$I31,Tabla1[Sistema],"SAN JUAN DEL RIO") -> 1 | P31: =+SUMIFS(Tabla1[Avance_Med],Tabla1[nombre_actividad],$I31,Tabla1[Sistema],"GIVAUDAN") -> 0 | Q31: =+SUMIFS(Tabla1[Avance_Med],Tabla1[nombre_actividad],$I31,Tabla1[Sistema],"SAN_GIL") -> 0
A32: MXN_230 | B32: 3.3.7 | C32: Inspeccion con liquidos penetrantes | D32: 100 | E32: SERVICIO | F32: 2090.59 | G32: 0 | H32: MXN | I32: LP | K32: =+SUMIFS(Tabla1[Avance_Med],Tabla1[nombre_actividad],$I32,Tabla1[Sistema],"LIRA_GALERAS") -> 1 | L32: =+SUMIFS(Tabla1[Avance_Med],Tabla1[nombre_actividad],$I32,Tabla1[Sistema],"PECO_AGROS") -> 2 | M32: =+SUMIFS(Tabla1[Avance_Med],Tabla1[nombre_actividad],$I32,Tabla1[Sistema],"HUIMILPAN") -> 0 | N32: =+SUMIFS(Tabla1[Avance_Med],Tabla1[nombre_actividad],$I32,Tabla1[Sistema],"BUENAVISTA") -> 0 | O32: =+SUMIFS(Tabla1[Avance_Med],Tabla1[nombre_actividad],$I32,Tabla1[Sistema],"SAN JUAN DEL RIO") -> 1 | P32: =+SUMIFS(Tabla1[Avance_Med],Tabla1[nombre_actividad],$I32,Tabla1[Sistema],"GIVAUDAN") -> 0 | Q32: =+SUMIFS(Tabla1[Avance_Med],Tabla1[nombre_actividad],$I32,Tabla1[Sistema],"SAN_GIL") -> 0
A33: MXN_240 | B33: 3.3.8 | C33: Medicion de PH de suelo dentro de excavación | D33: 55 | E33: SERVICIO | F33: 656 | G33: 0 | H33: MXN | I33: PH EXC | K33: =+SUMIFS(Tabla1[Avance_Med],Tabla1[nombre_actividad],$I33,Tabla1[Sistema],"LIRA_GALERAS") -> 11 | L33: =+SUMIFS(Tabla1[Avance_Med],Tabla1[nombre_actividad],$I33,Tabla1[Sistema],"PECO_AGROS") -> 3 | M33: =+SUMIFS(Tabla1[Avance_Med],Tabla1[nombre_actividad],$I33,Tabla1[Sistema],"HUIMILPAN") -> 0 | N33: =+SUMIFS(Tabla1[Avance_Med],Tabla1[nombre_actividad],$I33,Tabla1[Sistema],"BUENAVISTA") -> 0 | O33: =+SUMIFS(Tabla1[Avance_Med],Tabla1[nombre_actividad],$I33,Tabla1[Sistema],"SAN JUAN DEL RIO") -> 0 | P33: =+SUMIFS(Tabla1[Avance_Med],Tabla1[nombre_actividad],$I33,Tabla1[Sistema],"GIVAUDAN") -> 0 | Q33: =+SUMIFS(Tabla1[Avance_Med],Tabla1[nombre_actividad],$I33,Tabla1[Sistema],"SAN_GIL") -> 0
A34: MXN_250 | B34: 3.3.9 | C34: Medicion de corrosion por actividadad microbiologica y levantamiento de bacterias. | D34: 55 | E34: SERVICIO | F34: 4676 | G34: 0 | H34: MXN | I34: BACTERIAS EXC | K34: =+SUMIFS(Tabla1[Avance_Med],Tabla1[nombre_actividad],$I34,Tabla1[Sistema],"LIRA_GALERAS") -> 11 | L34: =+SUMIFS(Tabla1[Avance_Med],Tabla1[nombre_actividad],$I34,Tabla1[Sistema],"PECO_AGROS") -> 3 | M34: =+SUMIFS(Tabla1[Avance_Med],Tabla1[nombre_actividad],$I34,Tabla1[Sistema],"HUIMILPAN") -> 0 | N34: =+SUMIFS(Tabla1[Avance_Med],Tabla1[nombre_actividad],$I34,Tabla1[Sistema],"BUENAVISTA") -> 0 | O34: =+SUMIFS(Tabla1[Avance_Med],Tabla1[nombre_actividad],$I34,Tabla1[Sistema],"SAN JUAN DEL RIO") -> 0 | P34: =+SUMIFS(Tabla1[Avance_Med],Tabla1[nombre_actividad],$I34,Tabla1[Sistema],"GIVAUDAN") -> 0 | Q34: =+SUMIFS(Tabla1[Avance_Med],Tabla1[nombre_actividad],$I34,Tabla1[Sistema],"SAN_GIL") -> 0
A35: MXN_260 | B35: 3.4 | C35: Reportes finales entregables (con resultados, diagnosticos, hallazgos, recomendaciones y conclusiones). Esta partida puede reducir en funcion de la cantidad de ductos principales. | D35: 105 | E35: DUCTO | F35: 4124.27 | G35: 0 | H35: MXN | I35: REPORTE E3
B36: 4 | C36: ETAPA 4 | F36: Subtotal | G36: 0
A37: MXN_270 | B37: 4.1 | C37: Evaluación de esfuerzo remanente de defectos. | D37: 105 | E37: DUCTO | F37: 5020.99 | G37: 0 | H37: MXN | I37: REMAING STRENG
A38: MXN_280 | B38: 4.2 | C38: Análisis de las condiciones encontradas y evaluación del proceso. | D38: 105 | E38: DUCTO | F38: 3652.99 | G38: 0 | H38: MXN | I38: ANLISIS
A39: MXN_290 | B39: 4.3 | C39: Cálculo de las tasas de corrosión y vida remanente. | D39: 105 | E39: DUCTO | F39: 3201.98 | G39: 0 | H39: MXN | I39: VCORR Y TVR
A40: MXN_300 | B40: 4.4 | C40: Análisis causa – raíz. | D40: 105 | E40: DUCTO | F40: 6840 | G40: 0 | H40: MXN | I40: CAUSA RAIZ
A41: MXN_310 | B41: 4.5 | C41: Definición de intervalos de re-inspección. | D41: 105 | E41: DUCTO | F41: 2052 | G41: 0 | H41: MXN | I41: T REINPECCION
A42: MXN_320 | B42: 4.6 | C42: Evaluación de efectividad del proceso de ECDA. | D42: 105 | E42: DUCTO | F42: 3420 | G42: 0 | H42: MXN | I42: EFECTIVIDAD
A43: MXN_330 | B43: 4.7 | C43: Elaboración del reporte final ECDA. | D43: 105 | E43: DUCTO | F43: 4212.36 | G43: 0 | H43: MXN | I43: REPORTE ECDA
A44: MXN_340 | B44: 4.8 | C44: Re-priorización de atención. | D44: 105 | E44: DUCTO | F44: 1368 | G44: 0 | H44: MXN | I44: RE-PRIORIZACION | W44: 17.4
A45: MXN_350 | B45: 4.9 | C45: Suministro y aplicación de recubrimiento viscoelastico anticorrosivo en diametros de 2" a 4" de diametro, incluyendo sus pruebas dielectricas, y de adeherencia. | D45: 100 | E45: M LINEAL POR DIAMETRO | F45: 7244.35 | G45: 0 | H45: MXN | I45: COATING 2-4 | K45: 12 | L45: 12 | U45: 24 | V45: =+F45*U45 -> 173864.4 | W45: 638.5 | X45: =+W45*$W$44 -> 11109.9
A46: MXN_360 | B46: 4_10 | C46: Suministro y aplicación de recubrimiento viscoelastico anticorrosivo en diametros de 6" a 8" de diametro, incluyendo sus pruebas dielectricas y de adeherencia. | D46: 500 | E46: M LINEAL POR DIAMETRO | F46: 6977.93 | G46: 0 | H46: MXN | I46: COATING 6-8 | K46: 12 | L46: 12 | U46: 24 | V46: =+F46*U46 -> 167470.32 | W46: 1210.95 | X46: =+W46*$W$44 -> 21070.53
A47: MXN_370 | B47: 4.11 | C47: Suministro y aplicación de recubrimiento viscoelastico anticorrosivo en diametros de 10" a 12" de diametro, incluyendo sus pruebas dielectricas y de adeherencia. | D47: 800 | E47: M LINEAL POR DIAMETRO | F47: 8275.99 | H47: MXN | I47: COATING 10-12
A48: MXN_380 | B48: 4.12 | C48: Reportes finales entregables (con resultados, diagnosticos, hallazgos, recomendaciones y conclusiones). | D48: 105 | E48: DUCTO | F48: 4409.23 | G48: 0 | H48: MXN | I48: REPORTE FINAL | X48: =SUM(X45:X47) -> 32180.43 | Y48: =+X48*0.16 -> 5148.8688 | Z48: =SUM(X48:Y48) -> 37329.299
B49: 5 | C49: Acompañamiento de seguridad | F49: Subtotal | G49: 0
B50: 5.1 | C50: Acompañamiento de seguridad en las actividades en campo, ETAPA 2 | E50: Servicio | F50: 0 | G50: 0 | H50: MXN
B51: 5.2 | C51: Acompañamiento de seguridad en las actividades en campo, ETAPA 3 | E51: Servicio | F51: 0 | G51: 0 | H51: MXN
F52: Total | G52: =SUM(G6+G13+G22+G36+G49+G50+G51) -> 9070780.8 | H52: MXN
A55: P 22.4 | B55: 2.4A | C55: MONITOREO DE POTENCIALES ON/OFF Y POTENCIALES VCA | D55: 357 | E55: Medición | F55: 1913.01 | G55: =+D55*F55 -> 682944.57 | H55: MXN | I55: POTENIALES ON OFF AC | J55: =F55/$F$17 -> 0.13967369 | K55: =+J55*F17 -> 1913.01
A56: P 22.4 | B56: 2.4B | C56: MEDICION DE RESISTIVIDAD DEL SUELO Y PH | D56: 252 | E56: Medición | F56: 3029.6 | G56: =+D56*F56 -> 763459.2 | H56: MXN | I56: RESISTIVIDAD PH | J56: =F56/$F$17 -> 0.22119875
A57: P 22.4 | B57: 2.4C | C57: MONITOREO DE POTENCIAL NATURAL | D57: 372 | E57: Medición | F57: 1821.08 | G57: =+D57*F57 -> 677441.76 | H57: MXN | I57: NATURALES | J57: =F57/$F$17 -> 0.13296165
C58: METALOGRAFIA | D58: 7 | E58: SERVICIO | F58: 19213.19 | G58: =+D58*F58 -> 134492.33 | H58: MXN | I58: METALOGRAFIAS | J58: =F58/$F$17 -> 1.4028035
C65: 46258 | E65: =+$E$67*$J$67 -> 55735 | F65: =+$F$67*$J$67 -> 71000 | G65: =+$G$68*$J$68+$G$69*$J$69 -> 215000 | H65: =+$H$68*$J$68+$H$69*$J$69 -> 272740
C66: ACTIVIDAD | D66: UNIDAD | E66: Agosto | F66: Septiembre | G66: Octubre | H66: Noviembre | I66: TOTAL | J66: P/U | K66: TOTAL
B67: Z.1 | C67: MONITOREO DE POTENCIALES ON/OFF Y POTENCIALES VCA | D67: MEDICION | E67: 157 | F67: 200 | I67: 357 | J67: 355 | K67: =+J67*I67 -> 126735 | L67: POTENIALES ON OFF AC
B68: Z.2 | C68: MEDICION DE RESISTIVIDAD DEL SUELO Y PH | D68: MEDICION | G68: 104 | H68: 148 | I68: 252 | J68: 1500 | K68: =+J68*I68 -> 378000 | L68: RESISTIVIDAD PH
B69: Z.3 | C69: MONITOREO DE POTENCIAL NATURAL | D69: MEDICION | G69: 200 | H69: 172 | I69: 372 | J69: 295 | K69: =+J69*I69 -> 109740 | L69: NATURALES
D71: =+J67/F17 -> 0.025919447 | E71: =+I67*D71 -> 9.2532425

Sheet Conceptos
A1: POSICIÓN | B1: DESCRIPCIÓN BREVE | C1: CANTIDAD | D1: UNIDAD DE MEDIDA (UM) | E1: PRECIO UNITARIO | F1: SUBTOTAL | G1: MONEDA | H1: nom | I1: ETAPA
A2: 1.1 | B2: Recopilación de Información | C2: 105 | D2: DUCTO | E2: 2532.81 | F2: =+C2*E2 -> 265945.05 | G2: MXN | H2: RECOPILACION | I2: ETAPA 1
A3: 1.2 | B3: Análisis de Información | C3: 105 | D3: DUCTO | E3: 3250.01 | F3: =+C3*E3 -> 341251.05 | G3: MXN | H3: ANALISIS | I3: ETAPA 1
A4: 1.3 | B4: Evaluación de factibilidad de ECDA | C4: 105 | D4: DUCTO | E4: 985.32 | F4: =+C4*E4 -> 103458.6 | G4: MXN | H4: FACTIBILIDAD | I4: ETAPA 1
A5: 1.4 | B5: Selección de técnicas de inspección indirecta | C5: 105 | D5: DUCTO | E5: 1062.92 | F5: =+C5*E5 -> 111606.6 | G5: MXN | H5: SELECCIÓN HERRAMIENTAS | I5: ETAPA 1
A6: 1.5 | B6: Definición de zonas ECDA | C6: 105 | D6: DUCTO | E6: 1337.25 | F6: =+C6*E6 -> 140411.25 | G6: MXN | H6: REGIONES ECDA | I6: ETAPA 1
A7: 1.6 | B7: Reporte final entregable (con resultados, diagnosticos, hallazgos, recomendaciones y conclusiones). Esta partida puede reducir en funcion de la cantidad de ductos principales. | C7: 105 | D7: DUCTO | E7: 1581.21 | F7: =+C7*E7 -> 166027.05 | G7: MXN | H7: REPORTE E1 | I7: ETAPA 1
A8: 2.1 | B8: Estudio de potencial a intervalos cortos (Close Interval Potential Survey-CIPS). | C8: 200 | D8: KM | E8: 14521.41 | F8: =+C8*E8 -> 2904282 | G8: MXN | H8: CIPS | I8: ETAPA 2
A9: 2.2 | B9: Estudio Gradiente de Voltaje de Corriente Alterna (ACVG). | C9: 200 | D9: KM | E9: 13555.63 | F9: =+C9*E9 -> 2711126 | G9: MXN | H9: ACVG | I9: ETAPA 2
A10: 2.3 | B10: Estudio Gradiente de Voltaje de Corriente Directa (DCVG). | C10: 200 | D10: KM | E10: 13555.63 | F10: =+C10*E10 -> 2711126 | G10: MXN | H10: DCVG | I10: ETAPA 2
A11: 2.4 | B11: Mapeo de corriente PCM | C11: 200 | D11: KM | E11: 13696.28 | F11: =+C11*E11 -> 2739256 | G11: MXN | H11: PCM | I11: ETAPA 2
A12: 2.5 | B12: Levantamiento de resistividad pH y bacterias a lo largo de la trayectoria del ducto a cada 500 m Incluye mano de obra, kits y equipo | C12: 500 | D12: SERVICIOS | E12: 4658 | F12: =+C12*E12 -> 2329000 | G12: MXN | H12: Resistividades pH BSR BPA | I12: ETAPA 2
A13: 2.6 | B13: Localización de Ducto. | C13: 200 | D13: KM | E13: 2257.42 | F13: =+C13*E13 -> 451484 | G13: MXN | H13: Localizacion | I13: ETAPA 2
... A17: 3.2 | B17: Recopilación de datos en la excavación | C17: 55 | D17: VERIFICACIONES | E17: 7585.99 | F17: =+C17*E17 -> 417229.45 | G17: MXN | H17: DATA EXC | I17: ETAPA 3
A18: 3.3.1 | B18: Inspeccion visual | C18: 55 | D18: VERIFICACIONES | E18: 1765.59 | F18: =+C18*E18 -> 97107.45 | G18: MXN | H18: VT | I18: ETAPA 3
A19: 3.3.2 | B19: Evaluacion de sanidad y medicion de espesores | C19: 100 | D19: SERVICIO | E19: 1934.59 | F19: =+C19*E19 -> 193459 | G19: MXN | H19: SANIDAD Y ESPESORES | I19: ETAPA 3
A20: 3.3.3 | B20: Caracterizacion de tuberia | C20: 100 | D20: SERVICIO | E20: 1960.59 | F20: =+C20*E20 -> 196059 | G20: MXN | H20: CARACTERIZACION | I20: ETAPA 3
A21: 3.3.4 | B21: Evaluacion de soldadura con haz angular | C21: 170 | D21: SERVICIO | E21: 2220.59 | F21: =+C21*E21 -> 377500.3 | G21: MXN | H21: UTPA | I21: ETAPA 3
A22: 3.3.5 | B22: Inspección de ultrasonido de haz recto | C22: 170 | D22: SERVICIO | E22: 2220.59 | F22: =+C22*E22 -> 377500.3 | G22: MXN | H22: UT RECTO | I22: ETAPA 3
A23: 3.3.6 | B23: Inspección con particulas magneticas | C23: 100 | D23: SERVICIO | E23: 2090.59 | F23: =+C23*E23 -> 209059 | G23: MXN | H23: MT | I23: ETAPA 3
A24: 3.3.7 | B24: Inspeccion con liquidos penetrantes | C24: 100 | D24: SERVICIO | E24: 2090.59 | F24: =+C24*E24 -> 209059 | G24: MXN | H24: LP | I24: ETAPA 3
A25: 3.3.8 | B25: Medicion de PH de suelo dentro de excavación | C25: 55 | D25: SERVICIO | E25: 656 | F25: =+C25*E25 -> 36080 | G25: MXN | H25: PH EXC | I25: ETAPA 3
A26: 3.3.9 | B26: Medicion de corrosion por actividadad microbiologica y levantamiento de bacterias. | C26: 55 | D26: SERVICIO | E26: 4676 | F26: =+C26*E26 -> 257180 | G26: MXN | H26: BACTERIAS EXC | I26: ETAPA 3
A27: 3.4 | B27: Reportes finales entregables (con resultados, diagnosticos, hallazgos, recomendaciones y conclusiones). Esta partida puede reducir en funcion de la cantidad de ductos principales. | C27: 105 | D27: DUCTO | E27: 4124.27 | F27: =+C27*E27 -> 433048.35 | G27: MXN | H27: REPORTE E3 | I27: ETAPA 3
A28: 4.1 | B28: Evaluación de esfuerzo remanente de defectos. | C28: 105 | D28: DUCTO | E28: 5020.99 | F28: =+C28*E28 -> 527203.95 | G28: MXN | H28: REMAING STRENG | I28: ETAPA 4
A29: 4.2 | B29: Análisis de las condiciones encontradas y evaluación del proceso. | C29: 105 | D29: DUCTO | E29: 3652.99 | F29: =+C29*E29 -> 383563.95 | G29: MXN | H29: ANLISIS | I29: ETAPA 4
A30: 4.3 | B30: Cálculo de las tasas de corrosión y vida remanente. | C30: 105 | D30: DUCTO | E30: 3201.98 | F30: =+C30*E30 -> 336207.9 | G30: MXN | H30: VCORR Y TVR | I30: ETAPA 4
A31: 4.4 | B31: Análisis causa – raíz. | C31: 105 | D31: DUCTO | E31: 6840 | F31: =+C31*E31 -> 718200 | G31: MXN | H31: CAUSA RAIZ | I31: ETAPA 4
A32: 4.5 | B32: Definición de intervalos de re-inspección. | C32: 105 | D32: DUCTO | E32: 2052 | F32: =+C32*E32 -> 215460 | G32: MXN | H32: T REINPECCION | I32: ETAPA 4
A33: 4.6 | B33: Evaluación de efectividad del proceso de ECDA. | C33: 105 | D33: DUCTO | E33: 3420 | F33: =+C33*E33 -> 359100 | G33: MXN | H33: EFECTIVIDAD | I33: ETAPA 4
A34: 4.7 | B34: Elaboración del reporte final ECDA. | C34: 105 | D34: DUCTO | E34: 4212.36 | F34: =+C34*E34 -> 442297.8 | G34: MXN | H34: REPORTE ECDA | I34: ETAPA 4
A35: 4.8 | B35: Re-priorización de atención. | C35: 105 | D35: DUCTO | E35: 1368 | F35: =+C35*E35 -> 143640 | G35: MXN | H35: RE-PRIORIZACION | I35: ETAPA 4
A36: 4.9 | B36: Suministro y aplicación de recubrimiento viscoelastico anticorrosivo en diametros de 2" a 4" de diametro, incluyendo sus pruebas dielectricas, y de adeherencia. | C36: 100 | D36: M LINEAL POR DIAMETRO | E36: 7244.35 | F36: =+C36*E36 -> 724435 | G36: MXN | H36: COATING 2-4 | I36: ETAPA 4
A37: 4_10 | B37: Suministro y aplicación de recubrimiento viscoelastico anticorrosivo en diametros de 6" a 8" de diametro, incluyendo sus pruebas dielectricas y de adeherencia. | C37: 500 | D37: M LINEAL POR DIAMETRO | E37: 6977.93 | F37: =+C37*E37 -> 3488965 | G37: MXN | H37: COATING 6-8 | I37: ETAPA 4
A38: 4.11 | B38: Suministro y aplicación de recubrimiento viscoelastico anticorrosivo en diametros de 10" a 12" de diametro, incluyendo sus pruebas dielectricas y de adeherencia. | C38: 800 | D38: M LINEAL POR DIAMETRO | E38: 8275.99 | F38: =+C38*E38 -> 6620792 | G38: MXN | H38: COATING 10-12 | I38: ETAPA 4
A39: 4.12 | B39: Reportes finales entregables (con resultados, diagnosticos, hallazgos, recomendaciones y conclusiones). | C39: 105 | D39: DUCTO | E39: 4409.23 | F39: =+C39*E39 -> 462969.15 | G39: MXN | H39: REPORTE FINAL | I39: ETAPA 4

Sheet R (s01)
A1: Sistema | B1: Nombre ducto | C1: Len | D1: Localizacion | E1: CIPS | F1: DCVG | G1: Resistividades pH BSR BPA | H1: ACVG | I1: PCM
A2: LIRA_GALERAS | B2: AC 8-6-4 in La Lira-Galeras | C2: =+_xlfn.XLOOKUP(B2,Tabla1[Ducto],Tabla1[Length]) -> 31.54 | D2: =IFERROR(SUMIFS(Tabla1[Avance_km],Tabla1[Ducto],'R (s01)'!$B2,Tabla1[nombre_actividad],D$1,Tabla1[Sistema],"LIRA_GALERAS")/$C2,0) -> 1 | E2: =IFERROR(SUMIFS(Tabla1[Avance_km],Tabla1[Ducto],'R (s01)'!$B2,Tabla1[nombre_actividad],E$1,Tabla1[Sistema],"LIRA_GALERAS")/$C2,0) -> 1 | F2: =IFERROR(SUMIFS(Tabla1[Avance_km],Tabla1[Ducto],'R (s01)'!$B2,Tabla1[nombre_actividad],F$1,Tabla1[Sistema],"LIRA_GALERAS")/$C2,0) -> 1 | G2: =IFERROR(SUMIFS(Tabla1[Avance_Med],Tabla1[Ducto],'R (s01)'!$B2,Tabla1[nombre_actividad],G$1)/64,0) -> 1 | H2: =+SUMIFS(Tabla1[Avance_km],Tabla1[Ducto],'R (s01)'!$B2,Tabla1[nombre_actividad],H$1)/$C2 -> 0 | I2: =+SUMIFS(Tabla1[Avance_km],Tabla1[Ducto],'R (s01)'!$B2,Tabla1[nombre_actividad],I$1)/$C2 -> 0
A3: LIRA_GALERAS | B3: FRESHLLACA | C3: =+_xlfn.XLOOKUP(B3,Tabla1[Ducto],Tabla1[Length]) -> 0.02 | D3: =IFERROR(SUMIFS(Tabla1[Avance_km],Tabla1[Ducto],'R (s01)'!$B3,Tabla1[nombre_actividad],D$1,Tabla1[Sistema],"LIRA_GALERAS")/$C3,0) -> 1 | E3: =IFERROR(SUMIFS(Tabla1[Avance_km],Tabla1[Ducto],'R (s01)'!$B3,Tabla1[nombre_actividad],E$1,Tabla1[Sistema],"LIRA_GALERAS")/$C3,0) -> 1 | F3: =IFERROR(SUMIFS(Tabla1[Avance_km],Tabla1[Ducto],'R (s01)'!$B3,Tabla1[nombre_actividad],F$1,Tabla1[Sistema],"LIRA_GALERAS")/$C3,0) -> 1 | G3: =IFERROR(SUMIFS(Tabla1[Avance_Med],Tabla1[Ducto],'R (s01)'!$B3,Tabla1[nombre_actividad],G$1)/(1),0) -> 1 | H3: =+SUMIFS(Tabla1[Avance_km],Tabla1[Ducto],'R (s01)'!$B3,Tabla1[nombre_actividad],H$1)/$C3 -> 0 | I3: =+SUMIFS(Tabla1[Avance_km],Tabla1[Ducto],'R (s01)'!$B3,Tabla1[nombre_actividad],I$1)/$C3 -> 0 | J3: =IFERROR(SUMIFS(Tabla1[Avance_Med],Tabla1[Ducto],$B3,Tabla1[nombre_actividad],G$1),0) -> 1
A4: LIRA_GALERAS | B4: RANCHO HUMUS | C4: =+_xlfn.XLOOKUP(B4,Tabla1[Ducto],Tabla1[Length]) -> 0.07 | D4: =IFERROR(SUMIFS(Tabla1[Avance_km],Tabla1[Ducto],'R (s01)'!$B4,Tabla1[nombre_actividad],D$1,Tabla1[Sistema],"LIRA_GALERAS")/$C4,0) -> 1 | E4: =IFERROR(SUMIFS(Tabla1[Avance_km],Tabla1[Ducto],'R (s01)'!$B4,Tabla1[nombre_actividad],E$1,Tabla1[Sistema],"LIRA_GALERAS")/$C4,0) -> 1 | F4: =IFERROR(SUMIFS(Tabla1[Avance_km],Tabla1[Ducto],'R (s01)'!$B4,Tabla1[nombre_actividad],F$1,Tabla1[Sistema],"LIRA_GALERAS")/$C4,0) -> 1 | H4: =+SUMIFS(Tabla1[Avance_km],Tabla1[Ducto],'R (s01)'!$B4,Tabla1[nombre_actividad],H$1)/$C4 -> 0 | I4: =+SUMIFS(Tabla1[Avance_km],Tabla1[Ducto],'R (s01)'!$B4,Tabla1[nombre_actividad],I$1)/$C4 -> 0
A5: LIRA_GALERAS | B5: GPO. PRODUCTIVO LA LIRA | C5: =+_xlfn.XLOOKUP(B5,Tabla1[Ducto],Tabla1[Length]) -> 0.07 | D5: =IFERROR(SUMIFS(Tabla1[Avance_km],Tabla1[Ducto],'R (s01)'!$B5,Tabla1[nombre_actividad],D$1,Tabla1[Sistema],"LIRA_GALERAS")/$C5,0) -> 1 | E5: =IFERROR(SUMIFS(Tabla1[Avance_km],Tabla1[Ducto],'R (s01)'!$B5,Tabla1[nombre_actividad],E$1,Tabla1[Sistema],"LIRA_GALERAS")/$C5,0) -> 1 | F5: =IFERROR(SUMIFS(Tabla1[Avance_km],Tabla1[Ducto],'R (s01)'!$B5,Tabla1[nombre_actividad],F$1,Tabla1[Sistema],"LIRA_GALERAS")/$C5,0) -> 1 | G5: =IFERROR(SUMIFS(Tabla1[Avance_Med],Tabla1[Ducto],'R (s01)'!$B5,Tabla1[nombre_actividad],G$1)/(1),0) -> 1 | H5: =+SUMIFS(Tabla1[Avance_km],Tabla1[Ducto],'R (s01)'!$B5,Tabla1[nombre_actividad],H$1)/$C5 -> 0 | I5: =+SUMIFS(Tabla1[Avance_km],Tabla1[Ducto],'R (s01)'!$B5,Tabla1[nombre_actividad],I$1)/$C5 -> 20.04005 | J5: =IFERROR(SUMIFS(Tabla1[Avance_Med],Tabla1[Ducto],$B5,Tabla1[nombre_actividad],G$1),0) -> 1
A6: LIRA_GALERAS | B6: ED PARQUE INDUSTRIAL PYME | C6: =+_xlfn.XLOOKUP(B6,Tabla1[Ducto],Tabla1[Length]) -> 0.015 | D6: =IFERROR(SUMIFS(Tabla1[Avance_km],Tabla1[Ducto],'R (s01)'!$B6,Tabla1[nombre_actividad],D$1,Tabla1[Sistema],"LIRA_GALERAS")/$C6,0) -> 1 | E6: =IFERROR(SUMIFS(Tabla1[Avance_km],Tabla1[Ducto],'R (s01)'!$B6,Tabla1[nombre_actividad],E$1,Tabla1[Sistema],"LIRA_GALERAS")/$C6,0) -> 1 | F6: =IFERROR(SUMIFS(Tabla1[Avance_km],Tabla1[Ducto],'R (s01)'!$B6,Tabla1[nombre_actividad],F$1,Tabla1[Sistema],"LIRA_GALERAS")/$C6,0) -> 1 | G6: =IFERROR(SUMIFS(Tabla1[Avance_Med],Tabla1[Ducto],'R (s01)'!$B6,Tabla1[nombre_actividad],G$1)/(1),0) -> 1 | H6: =+SUMIFS(Tabla1[Avance_km],Tabla1[Ducto],'R (s01)'!$B6,Tabla1[nombre_actividad],H$1)/$C6 -> 0 | I6: =+SUMIFS(Tabla1[Avance_km],Tabla1[Ducto],'R (s01)'!$B6,Tabla1[nombre_actividad],I$1)/$C6 -> 0 | J6: =IFERROR(SUMIFS(Tabla1[Avance_Med],Tabla1[Ducto],$B6,Tabla1[nombre_actividad],G$1),0) -> 1
A7: LIRA_GALERAS | B7: PILGRIMS LOS CUES | C7: =+_xlfn.XLOOKUP(B7,Tabla1[Ducto],Tabla1[Length]) -> 0.01 | D7: =IFERROR(SUMIFS(Tabla1[Avance_km],Tabla1[Ducto],'R (s01)'!$B7,Tabla1[nombre_actividad],D$1,Tabla1[Sistema],"LIRA_GALERAS")/$C7,0) -> 1 | E7: =IFERROR(SUMIFS(Tabla1[Avance_km],Tabla1[Ducto],'R (s01)'!$B7,Tabla1[nombre_actividad],E$1,Tabla1[Sistema],"LIRA_GALERAS")/$C7,0) -> 1 | F7: =IFERROR(SUMIFS(Tabla1[Avance_km],Tabla1[Ducto],'R (s01)'!$B7,Tabla1[nombre_actividad],F$1,Tabla1[Sistema],"LIRA_GALERAS")/$C7,0) -> 1 | G7: =IFERROR(SUMIFS(Tabla1[Avance_Med],Tabla1[Ducto],'R (s01)'!$B7,Tabla1[nombre_actividad],G$1)/(1),0) -> 1 | H7: =+SUMIFS(Tabla1[Avance_km],Tabla1[Ducto],'R (s01)'!$B7,Tabla1[nombre_actividad],H$1)/$C7 -> 0 | I7: =+SUMIFS(Tabla1[Avance_km],Tabla1[Ducto],'R (s01)'!$B7,Tabla1[nombre_actividad],I$1)/$C7 -> 0 | J7: =IFERROR(SUMIFS(Tabla1[Avance_Med],Tabla1[Ducto],$B7,Tabla1[nombre_actividad],G$1),0) -> 1
A8: LIRA_GALERAS | B8: ALESTRA | C8: =+_xlfn.XLOOKUP(B8,Tabla1[Ducto],Tabla1[Length]) -> 1.982 | D8: =IFERROR(SUMIFS(Tabla1[Avance_km],Tabla1[Ducto],'R (s01)'!$B8,Tabla1[nombre_actividad],D$1,Tabla1[Sistema],"LIRA_GALERAS")/$C8,0) -> 1 | E8: =IFERROR(SUMIFS(Tabla1[Avance_km],Tabla1[Ducto],'R (s01)'!$B8,Tabla1[nombre_actividad],E$1,Tabla1[Sistema],"LIRA_GALERAS")/$C8,0) -> 1 | F8: =IFERROR(SUMIFS(Tabla1[Avance_km],Tabla1[Ducto],'R (s01)'!$B8,Tabla1[nombre_actividad],F$1,Tabla1[Sistema],"LIRA_GALERAS")/$C8,0) -> 1 | G8: =IFERROR(SUMIFS(Tabla1[Avance_Med],Tabla1[Ducto],'R (s01)'!$B8,Tabla1[nombre_actividad],G$1)/(ROUNDUP(C8,0)*2),0) -> 1 | H8: =+SUMIFS(Tabla1[Avance_km],Tabla1[Ducto],'R (s01)'!$B8,Tabla1[nombre_actividad],H$1)/$C8 -> 0 | I8: =+SUMIFS(Tabla1[Avance_km],Tabla1[Ducto],'R (s01)'!$B8,Tabla1[nombre_actividad],I$1)/$C8 -> 0 | J8: =IFERROR(SUMIFS(Tabla1[Avance_Med],Tabla1[Ducto],$B8,Tabla1[nombre_actividad],G$1),0) -> 4
A9: LIRA_GALERAS | B9: HUAWEI | C9: =+_xlfn.XLOOKUP(B9,Tabla1[Ducto],Tabla1[Length]) -> 0.175 | D9: =IFERROR(SUMIFS(Tabla1[Avance_km],Tabla1[Ducto],'R (s01)'!$B9,Tabla1[nombre_actividad],D$1,Tabla1[Sistema],"LIRA_GALERAS")/$C9,0) -> 1 | E9: =IFERROR(SUMIFS(Tabla1[Avance_km],Tabla1[Ducto],'R (s01)'!$B9,Tabla1[nombre_actividad],E$1,Tabla1[Sistema],"LIRA_GALERAS")/$C9,0) -> 1 | F9: =IFERROR(SUMIFS(Tabla1[Avance_km],Tabla1[Ducto],'R (s01)'!$B9,Tabla1[nombre_actividad],F$1,Tabla1[Sistema],"LIRA_GALERAS")/$C9,0) -> 1 | G9: =IFERROR(SUMIFS(Tabla1[Avance_Med],Tabla1[Ducto],'R (s01)'!$B9,Tabla1[nombre_actividad],G$1)/(ROUNDUP(C9,0)*2),0) -> 1 | H9: =+SUMIFS(Tabla1[Avance_km],Tabla1[Ducto],'R (s01)'!$B9,Tabla1[nombre_actividad],H$1)/$C9 -> 0 | I9: =+SUMIFS(Tabla1[Avance_km],Tabla1[Ducto],'R (s01)'!$B9,Tabla1[nombre_actividad],I$1)/$C9 -> 0 | J9: =IFERROR(SUMIFS(Tabla1[Avance_Med],Tabla1[Ducto],$B9,Tabla1[nombre_actividad],G$1),0) -> 2
A10: LIRA_GALERAS | B10: ITASA | C10: =+_xlfn.XLOOKUP(B10,Tabla1[Ducto],Tabla1[Length]) -> 0.015 | D10: =IFERROR(SUMIFS(Tabla1[Avance_km],Tabla1[Ducto],'R (s01)'!$B10,Tabla1[nombre_actividad],D$1,Tabla1[Sistema],"LIRA_GALERAS")/$C10,0) -> 1 | E10: =IFERROR(SUMIFS(Tabla1[Avance_km],Tabla1[Ducto],'R (s01)'!$B10,Tabla1[nombre_actividad],E$1,Tabla1[Sistema],"LIRA_GALERAS")/$C10,0) -> 1 | F10: =IFERROR(SUMIFS(Tabla1[Avance_km],Tabla1[Ducto],'R (s01)'!$B10,Tabla1[nombre_actividad],F$1,Tabla1[Sistema],"LIRA_GALERAS")/$C10,0) -> 1 | H10: =+SUMIFS(Tabla1[Avance_km],Tabla1[Ducto],'R (s01)'!$B10,Tabla1[nombre_actividad],H$1)/$C10 -> 0 | I10: =+SUMIFS(Tabla1[Avance_km],Tabla1[Ducto],'R (s01)'!$B10,Tabla1[nombre_actividad],I$1)/$C10 -> 0
A11: LIRA_GALERAS | B11: IACNA DE MEXICO | C11: =+_xlfn.XLOOKUP(B11,Tabla1[Ducto],Tabla1[Length]) -> 0.01 | D11: =IFERROR(SUMIFS(Tabla1[Avance_km],Tabla1[Ducto],'R (s01)'!$B11,Tabla1[nombre_actividad],D$1,Tabla1[Sistema],"LIRA_GALERAS")/$C11,0) -> 1 | E11: =IFERROR(SUMIFS(Tabla1[Avance_km],Tabla1[Ducto],'R (s01)'!$B11,Tabla1[nombre_actividad],E$1,Tabla1[Sistema],"LIRA_GALERAS")/$C11,0) -> 1 | F11: =IFERROR(SUMIFS(Tabla1[Avance_km],Tabla1[Ducto],'R (s01)'!$B11,Tabla1[nombre_actividad],F$1,Tabla1[Sistema],"LIRA_GALERAS")/$C11,0) -> 1 | G11: =IFERROR(SUMIFS(Tabla1[Avance_Med],Tabla1[Ducto],'R (s01)'!$B11,Tabla1[nombre_actividad],G$1)/(1),0) -> 1 | H11: =+SUMIFS(Tabla1[Avance_km],Tabla1[Ducto],'R (s01)'!$B11,Tabla1[nombre_actividad],H$1)/$C11 -> 0 | I11: =+SUMIFS(Tabla1[Avance_km],Tabla1[Ducto],'R (s01)'!$B11,Tabla1[nombre_actividad],I$1)/$C11 -> 0 | J11: =IFERROR(SUMIFS(Tabla1[Avance_Med],Tabla1[Ducto],$B11,Tabla1[nombre_actividad],G$1),0) -> 1
A12: LIRA_GALERAS | B12: KOPPERT | C12: =+_xlfn.XLOOKUP(B12,Tabla1[Ducto],Tabla1[Length]) -> 0.015 | D12: =IFERROR(SUMIFS(Tabla1[Avance_km],Tabla1[Ducto],'R (s01)'!$B12,Tabla1[nombre_actividad],D$1,Tabla1[Sistema],"LIRA_GALERAS")/$C12,0) -> 1 | E12: =IFERROR(SUMIFS(Tabla1[Avance_km],Tabla1[Ducto],'R (s01)'!$B12,Tabla1[nombre_actividad],E$1,Tabla1[Sistema],"LIRA_GALERAS")/$C12,0) -> 1 | F12: =IFERROR(SUMIFS(Tabla1[Avance_km],Tabla1[Ducto],'R (s01)'!$B12,Tabla1[nombre_actividad],F$1,Tabla1[Sistema],"LIRA_GALERAS")/$C12,0) -> 1 | H12: =+SUMIFS(Tabla1[Avance_km],Tabla1[Ducto],'R (s01)'!$B12,Tabla1[nombre_actividad],H$1)/$C12 -> 0 | I12: =+SUMIFS(Tabla1[Avance_km],Tabla1[Ducto],'R (s01)'!$B12,Tabla1[nombre_actividad],I$1)/$C12 -> 0
A13: LIRA_GALERAS | B13: ED EL COLORADO | C13: =+_xlfn.XLOOKUP(B13,Tabla1[Ducto],Tabla1[Length]) -> 0.019 | D13: =IFERROR(SUMIFS(Tabla1[Avance_km],Tabla1[Ducto],'R (s01)'!$B13,Tabla1[nombre_actividad],D$1,Tabla1[Sistema],"LIRA_GALERAS")/$C13,0) -> 1 | E13: =IFERROR(SUMIFS(Tabla1[Avance_km],Tabla1[Ducto],'R (s01)'!$B13,Tabla1[nombre_actividad],E$1,Tabla1[Sistema],"LIRA_GALERAS")/$C13,0) -> 1 | F13: =IFERROR(SUMIFS(Tabla1[Avance_km],Tabla1[Ducto],'R (s01)'!$B13,Tabla1[nombre_actividad],F$1,Tabla1[Sistema],"LIRA_GALERAS")/$C13,0) -> 1 | G13: =IFERROR(SUMIFS(Tabla1[Avance_Med],Tabla1[Ducto],'R (s01)'!$B13,Tabla1[nombre_actividad],G$1)/(1),0) -> 1 | H13: =+SUMIFS(Tabla1[Avance_km],Tabla1[Ducto],'R (s01)'!$B13,Tabla1[nombre_actividad],H$1)/$C13 -> 0 | I13: =+SUMIFS(Tabla1[Avance_km],Tabla1[Ducto],'R (s01)'!$B13,Tabla1[nombre_actividad],I$1)/$C13 -> 0 | J13: =IFERROR(SUMIFS(Tabla1[Avance_Med],Tabla1[Ducto],$B13,Tabla1[nombre_actividad],G$1),0) -> 1
A14: LIRA_GALERAS | B14: INDUSTRIAS KI | C14: =+_xlfn.XLOOKUP(B14,Tabla1[Ducto],Tabla1[Length]) -> 0.008 | D14: =IFERROR(SUMIFS(Tabla1[Avance_km],Tabla1[Ducto],'R (s01)'!$B14,Tabla1[nombre_actividad],D$1,Tabla1[Sistema],"LIRA_GALERAS")/$C14,0) -> 1 | E14: =IFERROR(SUMIFS(Tabla1[Avance_km],Tabla1[Ducto],'R (s01)'!$B14,Tabla1[nombre_actividad],E$1,Tabla1[Sistema],"LIRA_GALERAS")/$C14,0) -> 1 | F14: =IFERROR(SUMIFS(Tabla1[Avance_km],Tabla1[Ducto],'R (s01)'!$B14,Tabla1[nombre_actividad],F$1,Tabla1[Sistema],"LIRA_GALERAS")/$C14,0) -> 1 | G14: =IFERROR(SUMIFS(Tabla1[Avance_Med],Tabla1[Ducto],'R (s01)'!$B14,Tabla1[nombre_actividad],G$1)/(1),0) -> 1 | H14: =+SUMIFS(Tabla1[Avance_km],Tabla1[Ducto],'R (s01)'!$B14,Tabla1[nombre_actividad],H$1)/$C14 -> 0 | I14: =+SUMIFS(Tabla1[Avance_km],Tabla1[Ducto],'R (s01)'!$B14,Tabla1[nombre_actividad],I$1)/$C14 -> 0 | J14: =IFERROR(SUMIFS(Tabla1[Avance_Med],Tabla1[Ducto],$B14,Tabla1[nombre_actividad],G$1),0) -> 1
A15: LIRA_GALERAS | B15: NATGAS EL MARQUES | C15: =+_xlfn.XLOOKUP(B15,Tabla1[Ducto],Tabla1[Length]) -> 1.054 | D15: =IFERROR(SUMIFS(Tabla1[Avance_km],Tabla1[Ducto],'R (s01)'!$B15,Tabla1[nombre_actividad],D$1,Tabla1[Sistema],"LIRA_GALERAS")/$C15,0) -> 1 | E15: =IFERROR(SUMIFS(Tabla1[Avance_km],Tabla1[Ducto],'R (s01)'!$B15,Tabla1[nombre_actividad],E$1,Tabla1[Sistema],"LIRA_GALERAS")/$C15,0) -> 1 | F15: =IFERROR(SUMIFS(Tabla1[Avance_km],Tabla1[Ducto],'R (s01)'!$B15,Tabla1[nombre_actividad],F$1,Tabla1[Sistema],"LIRA_GALERAS")/$C15,0) -> 1 | G15: =IFERROR(SUMIFS(Tabla1[Avance_Med],Tabla1[Ducto],'R (s01)'!$B15,Tabla1[nombre_actividad],G$1)/(2),0) -> 1 | H15: =+SUMIFS(Tabla1[Avance_km],Tabla1[Ducto],'R (s01)'!$B15,Tabla1[nombre_actividad],H$1)/$C15 -> 0 | I15: =+SUMIFS(Tabla1[Avance_km],Tabla1[Ducto],'R (s01)'!$B15,Tabla1[nombre_actividad],I$1)/$C15 -> 0 | J15: =IFERROR(SUMIFS(Tabla1[Avance_Med],Tabla1[Ducto],$B15,Tabla1[nombre_actividad],G$1),0) -> 2
A16: LIRA_GALERAS | B16: FUTURO NATGAS EL MARQUES | C16: =+_xlfn.XLOOKUP(B16,Tabla1[Ducto],Tabla1[Length]) -> #N/A | D16: - | E16: - | F16: - | G16: - | J16: =IFERROR(SUMIFS(Tabla1[Avance_Med],Tabla1[Ducto],$B16,Tabla1[nombre_actividad],G$1),0) -> 0
A17: LIRA_GALERAS | B17: ED PARQUE INDUSTRIAL LA BOMBA | C17: =+_xlfn.XLOOKUP(B17,Tabla1[Ducto],Tabla1[Length]) -> 0.088 | D17: =IFERROR(SUMIFS(Tabla1[Avance_km],Tabla1[Ducto],'R (s01)'!$B17,Tabla1[nombre_actividad],D$1,Tabla1[Sistema],"LIRA_GALERAS")/$C17,0) -> 1 | E17: =IFERROR(SUMIFS(Tabla1[Avance_km],Tabla1[Ducto],'R (s01)'!$B17,Tabla1[nombre_actividad],E$1,Tabla1[Sistema],"LIRA_GALERAS")/$C17,0) -> 1 | F17: =IFERROR(SUMIFS(Tabla1[Avance_km],Tabla1[Ducto],'R (s01)'!$B17,Tabla1[nombre_actividad],F$1,Tabla1[Sistema],"LIRA_GALERAS")/$C17,0) -> 1 | G17: =IFERROR(SUMIFS(Tabla1[Avance_Med],Tabla1[Ducto],'R (s01)'!$B17,Tabla1[nombre_actividad],G$1)/(1),0) -> 1 | J17: =IFERROR(SUMIFS(Tabla1[Avance_Med],Tabla1[Ducto],$B17,Tabla1[nombre_actividad],G$1),0) -> 1
A18: LIRA_GALERAS | B18: STERLING BURDS | C18: =+_xlfn.XLOOKUP(B18,Tabla1[Ducto],Tabla1[Length]) -> 0.188 | D18: =IFERROR(SUMIFS(Tabla1[Avance_km],Tabla1[Ducto],'R (s01)'!$B18,Tabla1[nombre_actividad],D$1,Tabla1[Sistema],"LIRA_GALERAS")/$C18,0) -> 1 | E18: =IFERROR(SUMIFS(Tabla1[Avance_km],Tabla1[Ducto],'R (s01)'!$B18,Tabla1[nombre_actividad],E$1,Tabla1[Sistema],"LIRA_GALERAS")/$C18,0) -> 1 | F18: =IFERROR(SUMIFS(Tabla1[Avance_km],Tabla1[Ducto],'R (s01)'!$B18,Tabla1[nombre_actividad],F$1,Tabla1[Sistema],"LIRA_GALERAS")/$C18,0) -> 1
A19: LIRA_GALERAS | B19: ED PARQUE INDUSTRIAL FINSA II | C19: =+_xlfn.XLOOKUP(B19,Tabla1[Ducto],Tabla1[Length]) -> 1.02 | D19: =IFERROR(SUMIFS(Tabla1[Avance_km],Tabla1[Ducto],'R (s01)'!$B19,Tabla1[nombre_actividad],D$1,Tabla1[Sistema],"LIRA_GALERAS")/$C19,0) -> 1 | E19: =IFERROR(SUMIFS(Tabla1[Avance_km],Tabla1[Ducto],'R (s01)'!$B19,Tabla1[nombre_actividad],E$1,Tabla1[Sistema],"LIRA_GALERAS")/$C19,0) -> 1 | F19: =IFERROR(SUMIFS(Tabla1[Avance_km],Tabla1[Ducto],'R (s01)'!$B19,Tabla1[nombre_actividad],F$1,Tabla1[Sistema],"LIRA_GALERAS")/$C19,0) -> 1 | G19: =IFERROR(SUMIFS(Tabla1[Avance_Med],Tabla1[Ducto],'R (s01)'!$B19,Tabla1[nombre_actividad],G$1)/(3),0) -> 1 | J19: =IFERROR(SUMIFS(Tabla1[Avance_Med],Tabla1[Ducto],$B19,Tabla1[nombre_actividad],G$1),0) -> 3
A20: LIRA_GALERAS | B20: FINSA II | C20: =+_xlfn.XLOOKUP(B20,Tabla1[Ducto],Tabla1[Length]) -> 0.01 | D20: =IFERROR(SUMIFS(Tabla1[Avance_km],Tabla1[Ducto],'R (s01)'!$B20,Tabla1[nombre_actividad],D$1,Tabla1[Sistema],"LIRA_GALERAS")/$C20,0) -> 1 | E20: =IFERROR(SUMIFS(Tabla1[Avance_km],Tabla1[Ducto],'R (s01)'!$B20,Tabla1[nombre_actividad],E$1,Tabla1[Sistema],"LIRA_GALERAS")/$C20,0) -> 1 | F20: =IFERROR(SUMIFS(Tabla1[Avance_km],Tabla1[Ducto],'R (s01)'!$B20,Tabla1[nombre_actividad],F$1,Tabla1[Sistema],"LIRA_GALERAS")/$C20,0) -> 1 | G20: =IFERROR(SUMIFS(Tabla1[Avance_Med],Tabla1[Ducto],'R (s01)'!$B20,Tabla1[nombre_actividad],G$1)/(1),0) -> 1 | J20: =IFERROR(SUMIFS(Tabla1[Avance_Med],Tabla1[Ducto],$B20,Tabla1[nombre_actividad],G$1),0) -> 1
A21: LIRA_GALERAS | B21: STEERINGMEX | C21: =+_xlfn.XLOOKUP(B21,Tabla1[Ducto],Tabla1[Length]) -> 0.012 | D21: =IFERROR(SUMIFS(Tabla1[Avance_km],Tabla1[Ducto],'R (s01)'!$B21,Tabla1[nombre_actividad],D$1,Tabla1[Sistema],"LIRA_GALERAS")/$C21,0) -> 1 | E21: =IFERROR(SUMIFS(Tabla1[Avance_km],Tabla1[Ducto],'R (s01)'!$B21,Tabla1[nombre_actividad],E$1,Tabla1[Sistema],"LIRA_GALERAS")/$C21,0) -> 1 | F21: =IFERROR(SUMIFS(Tabla1[Avance_km],Tabla1[Ducto],'R (s01)'!$B21,Tabla1[nombre_actividad],F$1,Tabla1[Sistema],"LIRA_GALERAS")/$C21,0) -> 1
A22: LIRA_GALERAS | B22: SYNTEK ASPHALT | C22: =+_xlfn.XLOOKUP(B22,Tabla1[Ducto],Tabla1[Length]) -> 0.012 | D22: =IFERROR(SUMIFS(Tabla1[Avance_km],Tabla1[Ducto],'R (s01)'!$B22,Tabla1[nombre_actividad],D$1,Tabla1[Sistema],"LIRA_GALERAS")/$C22,0) -> 1 | E22: =IFERROR(SUMIFS(Tabla1[Avance_km],Tabla1[Ducto],'R (s01)'!$B22,Tabla1[nombre_actividad],E$1,Tabla1[Sistema],"LIRA_GALERAS")/$C22,0) -> 1 | F22: =IFERROR(SUMIFS(Tabla1[Avance_km],Tabla1[Ducto],'R (s01)'!$B22,Tabla1[nombre_actividad],F$1,Tabla1[Sistema],"LIRA_GALERAS")/$C22,0) -> 1 | G22: =IFERROR(SUMIFS(Tabla1[Avance_Med],Tabla1[Ducto],'R (s01)'!$B22,Tabla1[nombre_actividad],G$1)/(1),0) -> 1 | J22: =IFERROR(SUMIFS(Tabla1[Avance_Med],Tabla1[Ducto],$B22,Tabla1[nombre_actividad],G$1),0) -> 1
A23: LIRA_GALERAS | B23: WIINERS MARK | C23: 0.012 | D23: =IFERROR(SUMIFS(Tabla1[Avance_km],Tabla1[Ducto],'R (s01)'!$B23,Tabla1[nombre_actividad],D$1,Tabla1[Sistema],"LIRA_GALERAS")/$C23,0) -> 1 | E23: =IFERROR(SUMIFS(Tabla1[Avance_km],Tabla1[Ducto],'R (s01)'!$B23,Tabla1[nombre_actividad],E$1,Tabla1[Sistema],"LIRA_GALERAS")/$C23,0) -> 1 | F23: =IFERROR(SUMIFS(Tabla1[Avance_km],Tabla1[Ducto],'R (s01)'!$B23,Tabla1[nombre_actividad],F$1,Tabla1[Sistema],"LIRA_GALERAS")/$C23,0) -> 1
A24: LIRA_GALERAS | B24: GUARDIAN | C24: =+_xlfn.XLOOKUP(B24,Tabla1[Ducto],Tabla1[Length]) -> 10.44422 | D24: =IFERROR(SUMIFS(Tabla1[Avance_km],Tabla1[Ducto],'R (s01)'!$B24,Tabla1[nombre_actividad],D$1,Tabla1[Sistema],"LIRA_GALERAS")/$C24,0) -> 0.99997894 | E24: =IFERROR(SUMIFS(Tabla1[Avance_km],Tabla1[Ducto],'R (s01)'!$B24,Tabla1[nombre_actividad],E$1,Tabla1[Sistema],"LIRA_GALERAS")/$C24,0) -> 0.99997894 | F24: =IFERROR(SUMIFS(Tabla1[Avance_km],Tabla1[Ducto],'R (s01)'!$B24,Tabla1[nombre_actividad],F$1,Tabla1[Sistema],"LIRA_GALERAS")/$C24,0) -> 0.99997894 | G24: =IFERROR(SUMIFS(Tabla1[Avance_Med],Tabla1[Ducto],'R (s01)'!$B24,Tabla1[nombre_actividad],G$1)/(ROUNDUP(C24,0)*2),0) -> 1 | J24: =IFERROR(SUMIFS(Tabla1[Avance_Med],Tabla1[Ducto],$B24,Tabla1[nombre_actividad],G$1),0) -> 22
A25: LIRA_GALERAS | B25: ED O´DONELL | C25: =+_xlfn.XLOOKUP(B25,Tabla1[Ducto],Tabla1[Length]) -> 0.055 | D25: =IFERROR(SUMIFS(Tabla1[Avance_km],Tabla1[Ducto],'R (s01)'!$B25,Tabla1[nombre_actividad],D$1,Tabla1[Sistema],"LIRA_GALERAS")/$C25,0) -> 1 | E25: =IFERROR(SUMIFS(Tabla1[Avance_km],Tabla1[Ducto],'R (s01)'!$B25,Tabla1[nombre_actividad],E$1,Tabla1[Sistema],"LIRA_GALERAS")/$C25,0) -> 1 | F25: =IFERROR(SUMIFS(Tabla1[Avance_km],Tabla1[Ducto],'R (s01)'!$B25,Tabla1[nombre_actividad],F$1,Tabla1[Sistema],"LIRA_GALERAS")/$C25,0) -> 1 | G25: =IFERROR(SUMIFS(Tabla1[Avance_Med],Tabla1[Ducto],'R (s01)'!$B25,Tabla1[nombre_actividad],G$1)/(1),0) -> 1 | J25: =IFERROR(SUMIFS(Tabla1[Avance_Med],Tabla1[Ducto],$B25,Tabla1[nombre_actividad],G$1),0) -> 1
A26: LIRA_GALERAS | B26: EFFEM | C26: =+_xlfn.XLOOKUP(B26,Tabla1[Ducto],Tabla1[Length]) -> 0.063 | D26: =IFERROR(SUMIFS(Tabla1[Avance_km],Tabla1[Ducto],'R (s01)'!$B26,Tabla1[nombre_actividad],D$1,Tabla1[Sistema],"LIRA_GALERAS")/$C26,0) -> 1 | E26: =IFERROR(SUMIFS(Tabla1[Avance_km],Tabla1[Ducto],'R (s01)'!$B26,Tabla1[nombre_actividad],E$1,Tabla1[Sistema],"LIRA_GALERAS")/$C26,0) -> 1 | F26: =IFERROR(SUMIFS(Tabla1[Avance_km],Tabla1[Ducto],'R (s01)'!$B26,Tabla1[nombre_actividad],F$1,Tabla1[Sistema],"LIRA_GALERAS")/$C26,0) -> 1 | G26: =IFERROR(SUMIFS(Tabla1[Avance_Med],Tabla1[Ducto],'R (s01)'!$B26,Tabla1[nombre_actividad],G$1)/(1),0) -> 1 | J26: =IFERROR(SUMIFS(Tabla1[Avance_Med],Tabla1[Ducto],$B26,Tabla1[nombre_actividad],G$1),0) -> 1
A27: LIRA_GALERAS | B27: PAPSA | C27: =+_xlfn.XLOOKUP(B27,Tabla1[Ducto],Tabla1[Length]) -> 0.055 | D27: =IFERROR(SUMIFS(Tabla1[Avance_km],Tabla1[Ducto],'R (s01)'!$B27,Tabla1[nombre_actividad],D$1,Tabla1[Sistema],"LIRA_GALERAS")/$C27,0) -> 1 | E27: =IFERROR(SUMIFS(Tabla1[Avance_km],Tabla1[Ducto],'R (s01)'!$B27,Tabla1[nombre_actividad],E$1,Tabla1[Sistema],"LIRA_GALERAS")/$C27,0) -> 1 | F27: =IFERROR(SUMIFS(Tabla1[Avance_km],Tabla1[Ducto],'R (s01)'!$B27,Tabla1[nombre_actividad],F$1,Tabla1[Sistema],"LIRA_GALERAS")/$C27,0) -> 1
A28: LIRA_GALERAS | B28: ED LA BARCA | C28: =+_xlfn.XLOOKUP(B28,Tabla1[Ducto],Tabla1[Length]) -> 0.287 | D28: =IFERROR(SUMIFS(Tabla1[Avance_km],Tabla1[Ducto],'R (s01)'!$B28,Tabla1[nombre_actividad],D$1,Tabla1[Sistema],"LIRA_GALERAS")/$C28,0) -> 1 | E28: =IFERROR(SUMIFS(Tabla1[Avance_km],Tabla1[Ducto],'R (s01)'!$B28,Tabla1[nombre_actividad],E$1,Tabla1[Sistema],"LIRA_GALERAS")/$C28,0) -> 1 | F28: =IFERROR(SUMIFS(Tabla1[Avance_km],Tabla1[Ducto],'R (s01)'!$B28,Tabla1[nombre_actividad],F$1,Tabla1[Sistema],"LIRA_GALERAS")/$C28,0) -> 1 | G28: =IFERROR(SUMIFS(Tabla1[Avance_Med],Tabla1[Ducto],'R (s01)'!$B28,Tabla1[nombre_actividad],G$1)/(1),0) -> 1 | J28: =IFERROR(SUMIFS(Tabla1[Avance_Med],Tabla1[Ducto],$B28,Tabla1[nombre_actividad],G$1),0) -> 1
A29: LIRA_GALERAS | B29: ATONGO | C29: =+_xlfn.XLOOKUP(B29,Tabla1[Ducto],Tabla1[Length]) -> 12.657 | D29: =IFERROR(SUMIFS(Tabla1[Avance_km],Tabla1[Ducto],'R (s01)'!$B29,Tabla1[nombre_actividad],D$1,Tabla1[Sistema],"LIRA_GALERAS")/$C29,0) -> 1 | E29: =IFERROR(SUMIFS(Tabla1[Avance_km],Tabla1[Ducto],'R (s01)'!$B29,Tabla1[nombre_actividad],E$1,Tabla1[Sistema],"LIRA_GALERAS")/$C29,0) -> 1 | F29: =IFERROR(SUMIFS(Tabla1[Avance_km],Tabla1[Ducto],'R (s01)'!$B29,Tabla1[nombre_actividad],F$1,Tabla1[Sistema],"LIRA_GALERAS")/$C29,0) -> 1 | G29: =IFERROR(SUMIFS(Tabla1[Avance_Med],Tabla1[Ducto],'R (s01)'!$B29,Tabla1[nombre_actividad],G$1)/(27),0) -> 1 | J29: =IFERROR(SUMIFS(Tabla1[Avance_Med],Tabla1[Ducto],$B29,Tabla1[nombre_actividad],G$1),0) -> 27
A30: LIRA_GALERAS | B30: ESTACION ATONGO | C30: =+_xlfn.XLOOKUP(B30,Tabla1[Ducto],Tabla1[Length]) -> 0.037 | D30: =IFERROR(SUMIFS(Tabla1[Avance_km],Tabla1[Ducto],'R (s01)'!$B30,Tabla1[nombre_actividad],D$1,Tabla1[Sistema],"LIRA_GALERAS")/$C30,0) -> 1 | E30: =IFERROR(SUMIFS(Tabla1[Avance_km],Tabla1[Ducto],'R (s01)'!$B30,Tabla1[nombre_actividad],E$1,Tabla1[Sistema],"LIRA_GALERAS")/$C30,0) -> 1 | F30: =IFERROR(SUMIFS(Tabla1[Avance_km],Tabla1[Ducto],'R (s01)'!$B30,Tabla1[nombre_actividad],F$1,Tabla1[Sistema],"LIRA_GALERAS")/$C30,0) -> 1
A31: LIRA_GALERAS | B31: REFUERZO ATONGO | C31: =+_xlfn.XLOOKUP(B31,Tabla1[Ducto],Tabla1[Length]) -> 2.277 | D31: =IFERROR(SUMIFS(Tabla1[Avance_km],Tabla1[Ducto],'R (s01)'!$B31,Tabla1[nombre_actividad],D$1,Tabla1[Sistema],"LIRA_GALERAS")/$C31,0) -> 1 | E31: =IFERROR(SUMIFS(Tabla1[Avance_km],Tabla1[Ducto],'R (s01)'!$B31,Tabla1[nombre_actividad],E$1,Tabla1[Sistema],"LIRA_GALERAS")/$C31,0) -> 1 | F31: =IFERROR(SUMIFS(Tabla1[Avance_km],Tabla1[Ducto],'R (s01)'!$B31,Tabla1[nombre_actividad],F$1,Tabla1[Sistema],"LIRA_GALERAS")/$C31,0) -> 1 | G31: =IFERROR(SUMIFS(Tabla1[Avance_Med],Tabla1[Ducto],'R (s01)'!$B31,Tabla1[nombre_actividad],G$1)/(ROUNDUP(C31,0)*2),0) -> 1 | J31: =IFERROR(SUMIFS(Tabla1[Avance_Med],Tabla1[Ducto],$B31,Tabla1[nombre_actividad],G$1),0) -> 6
A32: LIRA_GALERAS | B32: ATONGO SN5 POR ACTUALIZAR | C32: =+_xlfn.XLOOKUP(B32,Tabla1[Ducto],Tabla1[Length]) -> #N/A | D32: - | E32: - | F32: - | G32: - | J32: =IFERROR(SUMIFS(Tabla1[Avance_Med],Tabla1[Ducto],$B32,Tabla1[nombre_actividad],G$1),0) -> 0
A33: LIRA_GALERAS | B33: BG PRIME 1 | C33: =+_xlfn.XLOOKUP(B33,Tabla1[Ducto],Tabla1[Length]) -> #N/A | D33: =IFERROR(SUMIFS(Tabla1[Avance_km],Tabla1[Ducto],'R (s01)'!$B33,Tabla1[nombre_actividad],D$1,Tabla1[Sistema],"LIRA_GALERAS")/$C33,0) -> 0 | E33: =IFERROR(SUMIFS(Tabla1[Avance_km],Tabla1[Ducto],'R (s01)'!$B33,Tabla1[nombre_actividad],E$1,Tabla1[Sistema],"LIRA_GALERAS")/$C33,0) -> 0 | F33: =IFERROR(SUMIFS(Tabla1[Avance_km],Tabla1[Ducto],'R (s01)'!$B33,Tabla1[nombre_actividad],F$1,Tabla1[Sistema],"LIRA_GALERAS")/$C33,0) -> 0
A34: LIRA_GALERAS | B34: BG PRIME 2 | C34: =+_xlfn.XLOOKUP(B34,Tabla1[Ducto],Tabla1[Length]) -> #N/A | D34: =IFERROR(SUMIFS(Tabla1[Avance_km],Tabla1[Ducto],'R (s01)'!$B34,Tabla1[nombre_actividad],D$1,Tabla1[Sistema],"LIRA_GALERAS")/$C34,0) -> 0 | E34: =IFERROR(SUMIFS(Tabla1[Avance_km],Tabla1[Ducto],'R (s01)'!$B34,Tabla1[nombre_actividad],E$1,Tabla1[Sistema],"LIRA_GALERAS")/$C34,0) -> 0 | F34: =IFERROR(SUMIFS(Tabla1[Avance_km],Tabla1[Ducto],'R (s01)'!$B34,Tabla1[nombre_actividad],F$1,Tabla1[Sistema],"LIRA_GALERAS")/$C34,0) -> 0
A35: LIRA_GALERAS | B35: FABRICA DE JABON LA CORONA | C35: =+_xlfn.XLOOKUP(B35,Tabla1[Ducto],Tabla1[Length]) -> 0.007 | D35: =IFERROR(SUMIFS(Tabla1[Avance_km],Tabla1[Ducto],'R (s01)'!$B35,Tabla1[nombre_actividad],D$1,Tabla1[Sistema],"LIRA_GALERAS")/$C35,0) -> 1 | E35: =IFERROR(SUMIFS(Tabla1[Avance_km],Tabla1[Ducto],'R (s01)'!$B35,Tabla1[nombre_actividad],E$1,Tabla1[Sistema],"LIRA_GALERAS")/$C35,0) -> 1 | F35: =IFERROR(SUMIFS(Tabla1[Avance_km],Tabla1[Ducto],'R (s01)'!$B35,Tabla1[nombre_actividad],F$1,Tabla1[Sistema],"LIRA_GALERAS")/$C35,0) -> 1
A36: LIRA_GALERAS | B36: GRAMOSA ALIMENTOS | C36: =+_xlfn.XLOOKUP(B36,Tabla1[Ducto],Tabla1[Length]) -> 0.019 | D36: =IFERROR(SUMIFS(Tabla1[Avance_km],Tabla1[Ducto],'R (s01)'!$B36,Tabla1[nombre_actividad],D$1,Tabla1[Sistema],"LIRA_GALERAS")/$C36,0) -> 1 | E36: =IFERROR(SUMIFS(Tabla1[Avance_km],Tabla1[Ducto],'R (s01)'!$B36,Tabla1[nombre_actividad],E$1,Tabla1[Sistema],"LIRA_GALERAS")/$C36,0) -> 1 | F36: =IFERROR(SUMIFS(Tabla1[Avance_km],Tabla1[Ducto],'R (s01)'!$B36,Tabla1[nombre_actividad],F$1,Tabla1[Sistema],"LIRA_GALERAS")/$C36,0) -> 1
